project_01/5_fsm_traffic_light/fsm.v
// ==================================================
//	[ VLSISYS Lab. ]
//	* Author		: Daseul Moon (daseul@sm.ac.kr)
//	* Filename		: fsm.v
//	* Date			: 2025-03-19 12:09:34
//	* Description	: 
// ==================================================

module fsm
(
	output reg [1:0] o_light_a,
	output reg [1:0] o_light_b,
	input 			 i_traff_a,
	input		     i_traff_b,
	input  			 i_mode_p,
	input			 i_mode_r,
	input			 i_clk,
	input			 i_rstn
);

	// Light_A & Light_B
	parameter S_S0 = 2'b00;
	parameter S_S1 = 2'b01;
	parameter S_S2 = 2'b10;
	parameter S_S3 = 2'b11;

	parameter M_S0 = 1'b0;
	parameter M_S1 = 1'b1;

	parameter L_R = 2'b00;
	parameter L_G = 2'b01;
	parameter L_Y = 2'b10;

	// For Mode FSM Output
	reg		  mode;

	// Main State Register
	reg [1:0] nState;
	reg [1:0] cState;
	always @(posedge i_clk or negedge i_rstn) begin
		if(!i_rstn) begin
			cState <= S_S0;
		end else begin
			cState <= nState;
		end
	end
	
	// Sub State Register
	reg		nMode;
	reg		cMode;
	always @(posedge i_clk or negedge i_rstn) begin
		if(!i_rstn) begin
			cMode <= M_S0;
		end else begin
			cMode <= nMode;
		end
	end

	// Next State Logic
	always @(*) begin
		case(cState)
			S_S0: nState = i_traff_a ? S_S0 : S_S1;
			S_S1: nState = S_S2;
			S_S2: nState = (mode | i_traff_b) ? S_S2 : S_S3;
			S_S3: nState = S_S0;
		endcase
	end

	// Next Mode Logic
	always @(*) begin
		case(cMode)
			M_S0: nMode = i_mode_p ? M_S1 : M_S0;
			M_S1: nMode = i_mode_r ? M_S0 : M_S1;
		endcase
	end
	
	// Output Logic (Light)
	always @(*) begin
		case(cState)
			S_S0: {o_light_a, o_light_b} = {L_G, L_R};
			S_S1: {o_light_a, o_light_b} = {L_Y, L_R};
			S_S2: {o_light_a, o_light_b} = {L_R, L_G};
			S_S3: {o_light_a, o_light_b} = {L_R, L_Y};
		endcase
	end

	// Output Logic (Mode)
	always @(*) begin
		case(cMode)
			M_S0: mode = 1'b0;
			M_S1: mode = 1'b1;
		endcase
	end

	`ifdef DEBUG
		reg [8*8-1:0] strLA;
		reg [8*8-1:0] strLB;
		always @(*) begin
			case(o_light_a)
				L_G: strLA = "GREEN";
				L_R: strLA = "RED";
				L_Y: strLA = "YELLOW";
			endcase
			case(o_light_b)
				L_G: strLB = "GREEN";
				L_R: strLB = "RED";
				L_Y: strLB = "YELLOW";
			endcase
		end
	`endif
endmodule

project_01/5_fsm_traffic_light/fsm_tb.v
// ==================================================
//	[ VLSISYS Lab. ]
//	* Author		: Daseul Moon (daseul@sm.ac.kr)
//	* Filename		: fsm_tb.v
//	* Date			: 2025-03-19 12:24:06
//	* Description	: 
// ==================================================

// --------------------------------------------------
//	Define Global Variables
// --------------------------------------------------
`define	CLKFREQ		100		// Clock Freq. (Unit: MHz)
`define	SIMCYCLE	`NVEC	// Sim. Cycles
`define NVEC		50		// # of Test Vector
`define DEBUG

// --------------------------------------------------
//	Includes
// --------------------------------------------------
`include	"fsm.v"

module fsm_tb;
// --------------------------------------------------
//	DUT Signals & Instantiate
// --------------------------------------------------
	wire [1:0] o_light_a;
	wire [1:0] o_light_b;
	reg 	   i_traff_a;
	reg		   i_traff_b;
	reg 	   i_mode_p;
	reg 	   i_mode_r;
	reg 	   i_clk;
	reg 	   i_rstn;

	fsm
	u_fsm(
		.o_light_a (o_light_a),
		.o_light_b (o_light_b),
		.i_traff_a (i_traff_a),
		.i_traff_b (i_traff_b),
		.i_mode_p  (i_mode_p ),
		.i_mode_r  (i_mode_r ),
		.i_clk     (i_clk    ),
		.i_rstn    (i_rstn   )
	);

// -------------------------------------------------
// 	Clock
// -------------------------------------------------
	always #(500/`CLKFREQ) i_clk = ~i_clk;

// -------------------------------------------------
// 	Task
// -------------------------------------------------
	reg [8*32-1:0] taskState;
	task init;
		begin
			taskState = "Init(Reset)";
			i_traff_a = 1'b0;
			i_traff_b = 1'b0;
			i_mode_p  = 1'b0;
			i_mode_r  = 1'b0;
			i_clk     = 1'b0;
			i_rstn    = 1'b0;
		end
	endtask

	task reset_n_cycle;
		input [3:0] n;
		begin
			#(n*1000/`CLKFREQ);
			taskState = "Operate";
			i_rstn = 1'b1;
		end
	endtask

// --------------------------------------------------
//	Test Stimulus
// --------------------------------------------------
	integer		i, j;
	initial begin
		init();
		reset_n_cycle(10);

		for (i=0; i<`SIMCYCLE; i++) begin
			{i_traff_a, i_traff_b} = $urandom;
			{i_mode_p, i_mode_r}   = 2'b00;
			#(1000/`CLKFREQ);
		end

		for (i=0; i<`SIMCYCLE; i++) begin
			{i_traff_a, i_traff_b} = $urandom;
			{i_mode_p, i_mode_r}   = 2'b01;
			#(1000/`CLKFREQ);
		end

		for (i=0; i<`SIMCYCLE; i++) begin
			{i_traff_a, i_traff_a} = $urandom;
			{i_mode_p, i_mode_r}   = 2'b01;
			#(1000/`CLKFREQ);
		end
		#(1000/`CLKFREQ);
		$finish;
	end

// --------------------------------------------------
//	Dump VCD
// --------------------------------------------------
	reg	[8*32-1:0]	vcd_file;
	initial begin
		if ($value$plusargs("vcd_file=%s", vcd_file)) begin
			$dumpfile(vcd_file);
			$dumpvars;
		end else begin
			$dumpfile("fsm_tb.vcd");
			$dumpvars;
		end
	end

endmodule

project_01/5_fsm_traffic_light/vcd/fsm.vcd
$date
	Wed Mar 19 12:23:29 2025
$end
$version
	Icarus Verilog
$end
$timescale
	1ps
$end
$scope module fsm_tb $end
$var wire 2 ! o_light_b [1:0] $end
$var wire 2 " o_light_a [1:0] $end
$var reg 1 # i_clk $end
$var reg 1 $ i_mode_p $end
$var reg 1 % i_mode_r $end
$var reg 1 & i_rstn $end
$var reg 1 ' i_traff_a $end
$var reg 1 ( i_traff_b $end
$var reg 256 ) taskState [255:0] $end
$var reg 256 * vcd_file [255:0] $end
$var integer 32 + i [31:0] $end
$scope module u_fsm $end
$var wire 1 # i_clk $end
$var wire 1 $ i_mode_p $end
$var wire 1 % i_mode_r $end
$var wire 1 & i_rstn $end
$var wire 1 ' i_traff_a $end
$var wire 1 ( i_traff_b $end
$var reg 1 , cMode $end
$var reg 2 - cState [1:0] $end
$var reg 1 . mode $end
$var reg 1 / nMode $end
$var reg 2 0 nState [1:0] $end
$var reg 2 1 o_light_a [1:0] $end
$var reg 2 2 o_light_b [1:0] $end
$var reg 64 3 strLA [63:0] $end
$var reg 64 4 strLB [63:0] $end
$upscope $end
$scope task init $end
$upscope $end
$scope task reset_n_cycle $end
$var reg 4 5 n [3:0] $end
$upscope $end
$upscope $end
$enddefinitions $end
#0
$dumpvars
b1010 5
b10100100100010101000100 4
b100011101010010010001010100010101001110 3
b0 2
b1 1
b1 0
0/
0.
b0 -
0,
bx +
b101110001011110111011001100011011001000010111101100110011100110110110100101110011101100110001101100100 *
b100100101101110011010010111010000101000010100100110010101110011011001010111010000101001 )
0(
0'
0&
0%
0$
0#
b1 "
b0 !
$end
#5000
1#
#10000
0#
#15000
1#
#20000
0#
#25000
1#
#30000
0#
#35000
1#
#40000
0#
#45000
1#
#50000
0#
#55000
1#
#60000
0#
#65000
1#
#70000
0#
#75000
1#
#80000
0#
#85000
1#
#90000
0#
#95000
1#
#100000
0#
b0 +
1&
b1001111011100000110010101110010011000010111010001100101 )
#105000
b10110010100010101001100010011000100111101010111 3
b10 "
b10 1
b10 0
b1 -
1#
#110000
0#
1(
b1 +
#115000
b100011101010010010001010100010101001110 4
b10100100100010101000100 3
b0 "
b0 1
b1 !
b1 2
b10 -
1#
#120000
0#
b10 +
#125000
1#
#130000
0#
1'
b11 +
#135000
1#
#140000
0#
0'
b100 +
#145000
1#
#150000
0#
b101 +
#155000
1#
#160000
0#
b110 +
#165000
1#
#170000
b11 0
0#
1'
0(
b111 +
#175000
b10110010100010101001100010011000100111101010111 4
b10 !
b10 2
b0 0
b11 -
1#
#180000
0#
0'
1(
b1000 +
#185000
b10100100100010101000100 4
b100011101010010010001010100010101001110 3
b1 "
b1 1
b0 !
b0 2
b1 0
b0 -
1#
#190000
0#
b1001 +
#195000
b10110010100010101001100010011000100111101010111 3
b10 "
b10 1
b10 0
b1 -
1#
#200000
0#
1'
0(
b1010 +
#205000
b100011101010010010001010100010101001110 4
b10100100100010101000100 3
b0 "
b0 1
b1 !
b1 2
b11 0
b10 -
1#
#210000
b10 0
0#
0'
1(
b1011 +
#215000
1#
#220000
0#
b1100 +
#225000
1#
#230000
b11 0
0#
0(
b1101 +
#235000
b10110010100010101001100010011000100111101010111 4
b10 !
b10 2
b0 0
b11 -
1#
#240000
0#
1(
b1110 +
#245000
b10100100100010101000100 4
b100011101010010010001010100010101001110 3
b1 "
b1 1
b0 !
b0 2
b1 0
b0 -
1#
#250000
b0 0
0#
1'
0(
b1111 +
#255000
1#
#260000
b1 0
0#
0'
1(
b10000 +
#265000
b10110010100010101001100010011000100111101010111 3
b10 "
b10 1
b10 0
b1 -
1#
#270000
0#
1'
0(
b10001 +
#275000
b100011101010010010001010100010101001110 4
b10100100100010101000100 3
b0 "
b0 1
b1 !
b1 2
b11 0
b10 -
1#
#280000
b10 0
0#
0'
1(
b10010 +
#285000
1#
#290000
0#
1'
b10011 +
#295000
1#
#300000
b11 0
0#
0(
b10100 +
#305000
b10110010100010101001100010011000100111101010111 4
b10 !
b10 2
b0 0
b11 -
1#
#310000
0#
1(
b10101 +
#315000
b10100100100010101000100 4
b100011101010010010001010100010101001110 3
b1 "
b1 1
b0 !
b0 2
b0 -
1#
#320000
0#
0(
b10110 +
#325000
1#
#330000
0#
b10111 +
#335000
1#
#340000
b1 0
0#
0'
b11000 +
#345000
b10110010100010101001100010011000100111101010111 3
b10 "
b10 1
b10 0
b1 -
1#
#350000
0#
1(
b11001 +
#355000
b100011101010010010001010100010101001110 4
b10100100100010101000100 3
b0 "
b0 1
b1 !
b1 2
b10 -
1#
#360000
b11 0
0#
0(
b11010 +
#365000
b10110010100010101001100010011000100111101010111 4
b10 !
b10 2
b0 0
b11 -
1#
#370000
0#
1(
b11011 +
#375000
b10100100100010101000100 4
b100011101010010010001010100010101001110 3
b1 "
b1 1
b0 !
b0 2
b1 0
b0 -
1#
#380000
0#
b11100 +
#385000
b10110010100010101001100010011000100111101010111 3
b10 "
b10 1
b10 0
b1 -
1#
#390000
0#
b11101 +
#395000
b100011101010010010001010100010101001110 4
b10100100100010101000100 3
b0 "
b0 1
b1 !
b1 2
b10 -
1#
#400000
0#
1'
b11110 +
#405000
1#
#410000
b11 0
0#
0(
b11111 +
#415000
b10110010100010101001100010011000100111101010111 4
b10 !
b10 2
b0 0
b11 -
1#
#420000
0#
0'
b100000 +
#425000
b10100100100010101000100 4
b100011101010010010001010100010101001110 3
b1 "
b1 1
b0 !
b0 2
b1 0
b0 -
1#
#430000
0#
b100001 +
#435000
b10110010100010101001100010011000100111101010111 3
b10 "
b10 1
b10 0
b1 -
1#
#440000
0#
1'
b100010 +
#445000
b100011101010010010001010100010101001110 4
b10100100100010101000100 3
b0 "
b0 1
b1 !
b1 2
b11 0
b10 -
1#
#450000
b10 0
0#
0'
1(
b100011 +
#455000
1#
#460000
b11 0
0#
1'
0(
b100100 +
#465000
b10110010100010101001100010011000100111101010111 4
b10 !
b10 2
b0 0
b11 -
1#
#470000
0#
1(
b100101 +
#475000
b10100100100010101000100 4
b100011101010010010001010100010101001110 3
b1 "
b1 1
b0 !
b0 2
b0 -
1#
#480000
b1 0
0#
0'
b100110 +
#485000
b10110010100010101001100010011000100111101010111 3
b10 "
b10 1
b10 0
b1 -
1#
#490000
0#
1'
b100111 +
#495000
b100011101010010010001010100010101001110 4
b10100100100010101000100 3
b0 "
b0 1
b1 !
b1 2
b10 -
1#
#500000
0#
b101000 +
#505000
1#
#510000
0#
0'
b101001 +
#515000
1#
#520000
b11 0
0#
1'
0(
b101010 +
#525000
b10110010100010101001100010011000100111101010111 4
b10 !
b10 2
b0 0
b11 -
1#
#530000
0#
b101011 +
#535000
b10100100100010101000100 4
b100011101010010010001010100010101001110 3
b1 "
b1 1
b0 !
b0 2
b0 -
1#
#540000
b1 0
0#
0'
1(
b101100 +
#545000
b10110010100010101001100010011000100111101010111 3
b10 "
b10 1
b10 0
b1 -
1#
#550000
0#
1'
b101101 +
#555000
b100011101010010010001010100010101001110 4
b10100100100010101000100 3
b0 "
b0 1
b1 !
b1 2
b10 -
1#
#560000
0#
b101110 +
#565000
1#
#570000
b11 0
0#
0(
b101111 +
#575000
b10110010100010101001100010011000100111101010111 4
b10 !
b10 2
b0 0
b11 -
1#
#580000
0#
b110000 +
#585000
b10100100100010101000100 4
b100011101010010010001010100010101001110 3
b1 "
b1 1
b0 !
b0 2
b0 -
1#
#590000
b1 0
0#
0'
b110001 +
#595000
b10110010100010101001100010011000100111101010111 3
b10 "
b10 1
b10 0
b1 -
1#
#600000
0#
1%
1'
b0 +
#605000
b100011101010010010001010100010101001110 4
b10100100100010101000100 3
b0 "
b0 1
b1 !
b1 2
b11 0
b10 -
1#
#610000
0#
b1 +
#615000
b10110010100010101001100010011000100111101010111 4
b10 !
b10 2
b0 0
b11 -
1#
#620000
0#
0'
1(
b10 +
#625000
b10100100100010101000100 4
b100011101010010010001010100010101001110 3
b1 "
b1 1
b0 !
b0 2
b1 0
b0 -
1#
#630000
0#
0(
b11 +
#635000
b10110010100010101001100010011000100111101010111 3
b10 "
b10 1
b10 0
b1 -
1#
#640000
0#
b100 +
#645000
b100011101010010010001010100010101001110 4
b10100100100010101000100 3
b0 "
b0 1
b1 !
b1 2
b11 0
b10 -
1#
#650000
b10 0
0#
1(
b101 +
#655000
1#
#660000
0#
1'
b110 +
#665000
1#
#670000
b11 0
0#
0(
b111 +
#675000
b10110010100010101001100010011000100111101010111 4
b10 !
b10 2
b0 0
b11 -
1#
#680000
0#
b1000 +
#685000
b10100100100010101000100 4
b100011101010010010001010100010101001110 3
b1 "
b1 1
b0 !
b0 2
b0 -
1#
#690000
0#
b1001 +
#695000
1#
#700000
b1 0
0#
0'
b1010 +
#705000
b10110010100010101001100010011000100111101010111 3
b10 "
b10 1
b10 0
b1 -
1#
#710000
0#
1'
b1011 +
#715000
b100011101010010010001010100010101001110 4
b10100100100010101000100 3
b0 "
b0 1
b1 !
b1 2
b11 0
b10 -
1#
#720000
b10 0
0#
1(
b1100 +
#725000
1#
#730000
0#
0'
b1101 +
#735000
1#
#740000
0#
b1110 +
#745000
1#
#750000
0#
1'
b1111 +
#755000
1#
#760000
0#
b10000 +
#765000
1#
#770000
b11 0
0#
0(
b10001 +
#775000
b10110010100010101001100010011000100111101010111 4
b10 !
b10 2
b0 0
b11 -
1#
#780000
0#
b10010 +
#785000
b10100100100010101000100 4
b100011101010010010001010100010101001110 3
b1 "
b1 1
b0 !
b0 2
b0 -
1#
#790000
b1 0
0#
0'
1(
b10011 +
#795000
b10110010100010101001100010011000100111101010111 3
b10 "
b10 1
b10 0
b1 -
1#
#800000
0#
b10100 +
#805000
b100011101010010010001010100010101001110 4
b10100100100010101000100 3
b0 "
b0 1
b1 !
b1 2
b10 -
1#
#810000
0#
b10101 +
#815000
1#
#820000
b11 0
0#
1'
0(
b10110 +
#825000
b10110010100010101001100010011000100111101010111 4
b10 !
b10 2
b0 0
b11 -
1#
#830000
0#
0'
b10111 +
#835000
b10100100100010101000100 4
b100011101010010010001010100010101001110 3
b1 "
b1 1
b0 !
b0 2
b1 0
b0 -
1#
#840000
b0 0
0#
1'
1(
b11000 +
#845000
1#
#850000
0#
b11001 +
#855000
1#
#860000
b1 0
0#
0'
0(
b11010 +
#865000
b10110010100010101001100010011000100111101010111 3
b10 "
b10 1
b10 0
b1 -
1#
#870000
0#
1'
1(
b11011 +
#875000
b100011101010010010001010100010101001110 4
b10100100100010101000100 3
b0 "
b0 1
b1 !
b1 2
b10 -
1#
#880000
0#
b11100 +
#885000
1#
#890000
b11 0
0#
0'
0(
b11101 +
#895000
b10110010100010101001100010011000100111101010111 4
b10 !
b10 2
b0 0
b11 -
1#
#900000
0#
1'
1(
b11110 +
#905000
b10100100100010101000100 4
b100011101010010010001010100010101001110 3
b1 "
b1 1
b0 !
b0 2
b0 -
1#
#910000
b1 0
0#
0'
b11111 +
#915000
b10110010100010101001100010011000100111101010111 3
b10 "
b10 1
b10 0
b1 -
1#
#920000
0#
b100000 +
#925000
b100011101010010010001010100010101001110 4
b10100100100010101000100 3
b0 "
b0 1
b1 !
b1 2
b10 -
1#
#930000
b11 0
0#
0(
b100001 +
#935000
b10110010100010101001100010011000100111101010111 4
b10 !
b10 2
b0 0
b11 -
1#
#940000
0#
1'
1(
b100010 +
#945000
b10100100100010101000100 4
b100011101010010010001010100010101001110 3
b1 "
b1 1
b0 !
b0 2
b0 -
1#
#950000
b1 0
0#
0'
b100011 +
#955000
b10110010100010101001100010011000100111101010111 3
b10 "
b10 1
b10 0
b1 -
1#
#960000
0#
1'
0(
b100100 +
#965000
b100011101010010010001010100010101001110 4
b10100100100010101000100 3
b0 "
b0 1
b1 !
b1 2
b11 0
b10 -
1#
#970000
0#
0'
b100101 +
#975000
b10110010100010101001100010011000100111101010111 4
b10 !
b10 2
b0 0
b11 -
1#
#980000
0#
1'
b100110 +
#985000
b10100100100010101000100 4
b100011101010010010001010100010101001110 3
b1 "
b1 1
b0 !
b0 2
b0 -
1#
#990000
b1 0
0#
0'
b100111 +
#995000
b10110010100010101001100010011000100111101010111 3
b10 "
b10 1
b10 0
b1 -
1#
#1000000
0#
1'
1(
b101000 +
#1005000
b100011101010010010001010100010101001110 4
b10100100100010101000100 3
b0 "
b0 1
b1 !
b1 2
b10 -
1#
#1010000
0#
0'
b101001 +
#1015000
1#
#1020000
b11 0
0#
1'
0(
b101010 +
#1025000
b10110010100010101001100010011000100111101010111 4
b10 !
b10 2
b0 0
b11 -
1#
#1030000
0#
b101011 +
#1035000
b10100100100010101000100 4
b100011101010010010001010100010101001110 3
b1 "
b1 1
b0 !
b0 2
b0 -
1#
#1040000
b1 0
0#
0'
1(
b101100 +
#1045000
b10110010100010101001100010011000100111101010111 3
b10 "
b10 1
b10 0
b1 -
1#
#1050000
0#
b101101 +
#1055000
b100011101010010010001010100010101001110 4
b10100100100010101000100 3
b0 "
b0 1
b1 !
b1 2
b10 -
1#
#1060000
0#
1'
b101110 +
#1065000
1#
#1070000
0#
b101111 +
#1075000
1#
#1080000
0#
0'
b110000 +
#1085000
1#
#1090000
b11 0
0#
0(
b110001 +
#1095000
b10110010100010101001100010011000100111101010111 4
b10 !
b10 2
b0 0
b11 -
1#
#1100000
0#
1'
b0 +
#1105000
b10100100100010101000100 4
b100011101010010010001010100010101001110 3
b1 "
b1 1
b0 !
b0 2
b0 -
1#
#1110000
b1 0
0#
0'
b1 +
#1115000
b10110010100010101001100010011000100111101010111 3
b10 "
b10 1
b10 0
b1 -
1#
#1120000
0#
1'
b10 +
#1125000
b100011101010010010001010100010101001110 4
b10100100100010101000100 3
b0 "
b0 1
b1 !
b1 2
b11 0
b10 -
1#
#1130000
0#
1'
b11 +
#1135000
b10110010100010101001100010011000100111101010111 4
b10 !
b10 2
b0 0
b11 -
1#
#1140000
0#
0'
b100 +
#1145000
b10100100100010101000100 4
b100011101010010010001010100010101001110 3
b1 "
b1 1
b0 !
b0 2
b1 0
b0 -
1#
#1150000
b0 0
0#
1'
b101 +
#1155000
1#
#1160000
0#
1'
b110 +
#1165000
1#
#1170000
b1 0
0#
0'
b111 +
#1175000
b10110010100010101001100010011000100111101010111 3
b10 "
b10 1
b10 0
b1 -
1#
#1180000
0#
1'
b1000 +
#1185000
b100011101010010010001010100010101001110 4
b10100100100010101000100 3
b0 "
b0 1
b1 !
b1 2
b11 0
b10 -
1#
#1190000
0#
1'
b1001 +
#1195000
b10110010100010101001100010011000100111101010111 4
b10 !
b10 2
b0 0
b11 -
1#
#1200000
0#
b1010 +
#1205000
b10100100100010101000100 4
b100011101010010010001010100010101001110 3
b1 "
b1 1
b0 !
b0 2
b0 -
1#
#1210000
0#
b1011 +
#1215000
1#
#1220000
0#
b1100 +
#1225000
1#
#1230000
0#
b1101 +
#1235000
1#
#1240000
0#
b1110 +
#1245000
1#
#1250000
b1 0
0#
0'
b1111 +
#1255000
b10110010100010101001100010011000100111101010111 3
b10 "
b10 1
b10 0
b1 -
1#
#1260000
0#
1'
b10000 +
#1265000
b100011101010010010001010100010101001110 4
b10100100100010101000100 3
b0 "
b0 1
b1 !
b1 2
b11 0
b10 -
1#
#1270000
0#
b10001 +
#1275000
b10110010100010101001100010011000100111101010111 4
b10 !
b10 2
b0 0
b11 -
1#
#1280000
0#
1'
b10010 +
#1285000
b10100100100010101000100 4
b100011101010010010001010100010101001110 3
b1 "
b1 1
b0 !
b0 2
b0 -
1#
#1290000
0#
1'
b10011 +
#1295000
1#
#1300000
b1 0
0#
0'
b10100 +
#1305000
b10110010100010101001100010011000100111101010111 3
b10 "
b10 1
b10 0
b1 -
1#
#1310000
0#
0'
b10101 +
#1315000
b100011101010010010001010100010101001110 4
b10100100100010101000100 3
b0 "
b0 1
b1 !
b1 2
b11 0
b10 -
1#
#1320000
0#
1'
b10110 +
#1325000
b10110010100010101001100010011000100111101010111 4
b10 !
b10 2
b0 0
b11 -
1#
#1330000
0#
0'
b10111 +
#1335000
b10100100100010101000100 4
b100011101010010010001010100010101001110 3
b1 "
b1 1
b0 !
b0 2
b1 0
b0 -
1#
#1340000
0#
0'
b11000 +
#1345000
b10110010100010101001100010011000100111101010111 3
b10 "
b10 1
b10 0
b1 -
1#
#1350000
0#
1'
b11001 +
#1355000
b100011101010010010001010100010101001110 4
b10100100100010101000100 3
b0 "
b0 1
b1 !
b1 2
b11 0
b10 -
1#
#1360000
0#
0'
b11010 +
#1365000
b10110010100010101001100010011000100111101010111 4
b10 !
b10 2
b0 0
b11 -
1#
#1370000
0#
b11011 +
#1375000
b10100100100010101000100 4
b100011101010010010001010100010101001110 3
b1 "
b1 1
b0 !
b0 2
b1 0
b0 -
1#
#1380000
0#
b11100 +
#1385000
b10110010100010101001100010011000100111101010111 3
b10 "
b10 1
b10 0
b1 -
1#
#1390000
0#
1'
b11101 +
#1395000
b100011101010010010001010100010101001110 4
b10100100100010101000100 3
b0 "
b0 1
b1 !
b1 2
b11 0
b10 -
1#
#1400000
0#
b11110 +
#1405000
b10110010100010101001100010011000100111101010111 4
b10 !
b10 2
b0 0
b11 -
1#
#1410000
0#
1'
b11111 +
#1415000
b10100100100010101000100 4
b100011101010010010001010100010101001110 3
b1 "
b1 1
b0 !
b0 2
b0 -
1#
#1420000
b1 0
0#
0'
b100000 +
#1425000
b10110010100010101001100010011000100111101010111 3
b10 "
b10 1
b10 0
b1 -
1#
#1430000
0#
1'
b100001 +
#1435000
b100011101010010010001010100010101001110 4
b10100100100010101000100 3
b0 "
b0 1
b1 !
b1 2
b11 0
b10 -
1#
#1440000
0#
0'
b100010 +
#1445000
b10110010100010101001100010011000100111101010111 4
b10 !
b10 2
b0 0
b11 -
1#
#1450000
0#
1'
b100011 +
#1455000
b10100100100010101000100 4
b100011101010010010001010100010101001110 3
b1 "
b1 1
b0 !
b0 2
b0 -
1#
#1460000
0#
1'
b100100 +
#1465000
1#
#1470000
0#
1'
b100101 +
#1475000
1#
#1480000
0#
b100110 +
#1485000
1#
#1490000
0#
1'
b100111 +
#1495000
1#
#1500000
0#
1'
b101000 +
#1505000
1#
#1510000
b1 0
0#
0'
b101001 +
#1515000
b10110010100010101001100010011000100111101010111 3
b10 "
b10 1
b10 0
b1 -
1#
#1520000
0#
0'
b101010 +
#1525000
b100011101010010010001010100010101001110 4
b10100100100010101000100 3
b0 "
b0 1
b1 !
b1 2
b11 0
b10 -
1#
#1530000
0#
b101011 +
#1535000
b10110010100010101001100010011000100111101010111 4
b10 !
b10 2
b0 0
b11 -
1#
#1540000
0#
b101100 +
#1545000
b10100100100010101000100 4
b100011101010010010001010100010101001110 3
b1 "
b1 1
b0 !
b0 2
b1 0
b0 -
1#
#1550000
b0 0
0#
1'
b101101 +
#1555000
1#
#1560000
b1 0
0#
0'
b101110 +
#1565000
b10110010100010101001100010011000100111101010111 3
b10 "
b10 1
b10 0
b1 -
1#
#1570000
0#
0'
b101111 +
#1575000
b100011101010010010001010100010101001110 4
b10100100100010101000100 3
b0 "
b0 1
b1 !
b1 2
b11 0
b10 -
1#
#1580000
0#
1'
b110000 +
#1585000
b10110010100010101001100010011000100111101010111 4
b10 !
b10 2
b0 0
b11 -
1#
#1590000
0#
0'
b110001 +
#1595000
b10100100100010101000100 4
b100011101010010010001010100010101001110 3
b1 "
b1 1
b0 !
b0 2
b1 0
b0 -
1#
#1600000
0#
b110010 +
#1605000
b10110010100010101001100010011000100111101010111 3
b10 "
b10 1
b10 0
b1 -
1#
