03_week/04_counter/counter.v
// ==================================================
//	[ VLSISYS Lab. ]
//	* Author		: Daseul Moon (daseul@sm.ac.kr)
//	* Filename		: counter.v
//	* Date			: 2025-03-17 11:36:58
//	* Description	: 
// ==================================================

module updw_cnt
#(
	parameter	UPBND	= 31
)
(
	output reg [$clog2(UPBND+1)-1:0] o_cnt,
	input							 i_mode,
	input							 i_clk,
	input						     i_rstn
);

	always @(posedge i_clk or negedge i_rstn) begin
		if(!i_rstn) begin
			o_cnt <= 0;
		end else begin
			if(i_mode) begin
				if(o_cnt == UPBND) begin
					o_cnt <= 0;
				end else begin
					o_cnt <= o_cnt + 1;
				end
			end else begin
				if(o_cnt == 0) begin
					o_cnt <= UPBND;
				end else begin
					o_cnt <= o_cnt - 1;
				end
			end
		end
	end
endmodule

03_week/04_counter/counter_tb.v
// ==================================================
//	[ VLSISYS Lab. ]
//	* Author		: Daseul Moon (daseul@sm.ac.kr)
//	* Filename		: counter_tb.v
//	* Date			: 2025-03-17 11:38:16
//	* Description	: 
// ==================================================

// --------------------------------------------------
//	Define Global Variables
// --------------------------------------------------
`define	CLKFREQ		100		// Clock Freq. (Unit: MHz)
`define	SIMCYCLE	`NVEC	// Sim. Cycles
`define BW_DATA		32		// Bitwidth of ~~
`define BW_ADDR		5		// Bitwidth of ~~
`define BW_CTRL		4		// Bitwidth of ~~
`define NVEC		100		// # of Test Vector

// --------------------------------------------------
//	Includes
// --------------------------------------------------
`include	"counter.v"

module counter_tb;
// --------------------------------------------------
//	DUT Signals & Instantiate
// --------------------------------------------------
	parameter	UPBND = 11;

	wire [$clog2(UPBND+1)-1:0] o_cnt;
	reg						   i_mode;
	reg						   i_clk;
	reg				     	   i_rstn;

	updw_cnt
	#(
		.UPBND (UPBND)
	)
	u_updw_cnt(
		.o_cnt  (o_cnt ),
		.i_mode (i_mode),
		.i_clk  (i_clk ),
		.i_rstn (i_rstn)
	);

// --------------------------------------------------
// 	Clock
// --------------------------------------------------
	always #(500/`CLKFREQ) i_clk = ~i_clk;

// --------------------------------------------------
// 	Task
// --------------------------------------------------
	reg	[8*16-1:0] taskState;
	task init;
		begin
			taskState = "Init";
			i_mode	  = 1;
			i_clk	  = 0;
			i_rstn	  = 0;
		end
	endtask

	task resetNCycle;
		input [31:0] i;
		begin
			taskState = "Reset_On";
			#(i*1000/`CLKFREQ);
			taskState = "Reset_Off";
			i_rstn = 1;
		end
	endtask

// --------------------------------------------------
//	Test Stimulus
// --------------------------------------------------
	integer		i, j;
	initial begin
		init();
		resetNCycle(4);
		for (i=0; i<3*UPBND; i++) begin
			#(1000/`CLKFREQ);
		end
	    i_mode = 0;
		for (i=0; i<3*UPBND; i++) begin
			#(1000/`CLKFREQ);
		end
		$finish;
	end

// --------------------------------------------------
//	Dump VCD
// --------------------------------------------------
	reg	[8*32-1:0]	vcd_file;
	initial begin
		if ($value$plusargs("vcd_file=%s", vcd_file)) begin
			$dumpfile(vcd_file);
			$dumpvars;
		end else begin
			$dumpfile("counter_tb.vcd");
			$dumpvars;
		end
	end

endmodule

03_week/04_counter/vcd/counter.vcd
$date
	Mon Mar 17 11:54:04 2025
$end
$version
	Icarus Verilog
$end
$timescale
	1ps
$end
$scope module counter_tb $end
$var wire 4 ! o_cnt [3:0] $end
$var reg 1 " i_clk $end
$var reg 1 # i_mode $end
$var reg 1 $ i_rstn $end
$var reg 128 % taskState [127:0] $end
$var reg 256 & vcd_file [255:0] $end
$var integer 32 ' i [31:0] $end
$scope module u_updw_cnt $end
$var wire 1 " i_clk $end
$var wire 1 # i_mode $end
$var wire 1 $ i_rstn $end
$var reg 4 ( o_cnt [3:0] $end
$upscope $end
$scope task init $end
$upscope $end
$scope task resetNCycle $end
$var reg 32 ) i [31:0] $end
$upscope $end
$upscope $end
$enddefinitions $end
#0
$dumpvars
b100 )
b0 (
bx '
b10111000101111011101100110001101100100001011110110001101101111011101010110111001110100011001010111001000101110011101100110001101100100 &
b101001001100101011100110110010101110100010111110100111101101110 %
0$
1#
0"
b0 !
$end
#5000
1"
#10000
0"
#15000
1"
#20000
0"
#25000
1"
#30000
0"
#35000
1"
#40000
0"
b0 '
1$
b10100100110010101110011011001010111010001011111010011110110011001100110 %
#45000
b1 !
b1 (
1"
#50000
0"
b1 '
#55000
b10 !
b10 (
1"
#60000
0"
b10 '
#65000
b11 !
b11 (
1"
#70000
0"
b11 '
#75000
b100 !
b100 (
1"
#80000
0"
b100 '
#85000
b101 !
b101 (
1"
#90000
0"
b101 '
#95000
b110 !
b110 (
1"
#100000
0"
b110 '
#105000
b111 !
b111 (
1"
#110000
0"
b111 '
#115000
b1000 !
b1000 (
1"
#120000
0"
b1000 '
#125000
b1001 !
b1001 (
1"
#130000
0"
b1001 '
#135000
b1010 !
b1010 (
1"
#140000
0"
b1010 '
#145000
b1011 !
b1011 (
1"
#150000
0"
b1011 '
#155000
b0 !
b0 (
1"
#160000
0"
b1100 '
#165000
b1 !
b1 (
1"
#170000
0"
b1101 '
#175000
b10 !
b10 (
1"
#180000
0"
b1110 '
#185000
b11 !
b11 (
1"
#190000
0"
b1111 '
#195000
b100 !
b100 (
1"
#200000
0"
b10000 '
#205000
b101 !
b101 (
1"
#210000
0"
b10001 '
#215000
b110 !
b110 (
1"
#220000
0"
b10010 '
#225000
b111 !
b111 (
1"
#230000
0"
b10011 '
#235000
b1000 !
b1000 (
1"
#240000
0"
b10100 '
#245000
b1001 !
b1001 (
1"
#250000
0"
b10101 '
#255000
b1010 !
b1010 (
1"
#260000
0"
b10110 '
#265000
b1011 !
b1011 (
1"
#270000
0"
b10111 '
#275000
b0 !
b0 (
1"
#280000
0"
b11000 '
#285000
b1 !
b1 (
1"
#290000
0"
b11001 '
#295000
b10 !
b10 (
1"
#300000
0"
b11010 '
#305000
b11 !
b11 (
1"
#310000
0"
b11011 '
#315000
b100 !
b100 (
1"
#320000
0"
b11100 '
#325000
b101 !
b101 (
1"
#330000
0"
b11101 '
#335000
b110 !
b110 (
1"
#340000
0"
b11110 '
#345000
b111 !
b111 (
1"
#350000
0"
b11111 '
#355000
b1000 !
b1000 (
1"
#360000
0"
b100000 '
#365000
b1001 !
b1001 (
1"
#370000
0"
0#
b0 '
#375000
b1000 !
b1000 (
1"
#380000
0"
b1 '
#385000
b111 !
b111 (
1"
#390000
0"
b10 '
#395000
b110 !
b110 (
1"
#400000
0"
b11 '
#405000
b101 !
b101 (
1"
#410000
0"
b100 '
#415000
b100 !
b100 (
1"
#420000
0"
b101 '
#425000
b11 !
b11 (
1"
#430000
0"
b110 '
#435000
b10 !
b10 (
1"
#440000
0"
b111 '
#445000
b1 !
b1 (
1"
#450000
0"
b1000 '
#455000
b0 !
b0 (
1"
#460000
0"
b1001 '
#465000
b1011 !
b1011 (
1"
#470000
0"
b1010 '
#475000
b1010 !
b1010 (
1"
#480000
0"
b1011 '
#485000
b1001 !
b1001 (
1"
#490000
0"
b1100 '
#495000
b1000 !
b1000 (
1"
#500000
0"
b1101 '
#505000
b111 !
b111 (
1"
#510000
0"
b1110 '
#515000
b110 !
b110 (
1"
#520000
0"
b1111 '
#525000
b101 !
b101 (
1"
#530000
0"
b10000 '
#535000
b100 !
b100 (
1"
#540000
0"
b10001 '
#545000
b11 !
b11 (
1"
#550000
0"
b10010 '
#555000
b10 !
b10 (
1"
#560000
0"
b10011 '
#565000
b1 !
b1 (
1"
#570000
0"
b10100 '
#575000
b0 !
b0 (
1"
#580000
0"
b10101 '
#585000
b1011 !
b1011 (
1"
#590000
0"
b10110 '
#595000
b1010 !
b1010 (
1"
#600000
0"
b10111 '
#605000
b1001 !
b1001 (
1"
#610000
0"
b11000 '
#615000
b1000 !
b1000 (
1"
#620000
0"
b11001 '
#625000
b111 !
b111 (
1"
#630000
0"
b11010 '
#635000
b110 !
b110 (
1"
#640000
0"
b11011 '
#645000
b101 !
b101 (
1"
#650000
0"
b11100 '
#655000
b100 !
b100 (
1"
#660000
0"
b11101 '
#665000
b11 !
b11 (
1"
#670000
0"
b11110 '
#675000
b10 !
b10 (
1"
#680000
0"
b11111 '
#685000
b1 !
b1 (
1"
#690000
0"
b100000 '
#695000
b0 !
b0 (
1"
#700000
0"
b100001 '
