03_week/07_regfile/regfile.v
// ==================================================
//	[ VLSISYS Lab. ]
//	* Author		: Daseul Moon (daseul@sm.ac.kr)
//	* Filename		: regfile.v
//	* Date			: 2025-03-17 15:33:00
//	* Description	: 
// ==================================================

module regfile
#(
	parameter MIF_FILE = "regfile.mif",
	parameter BW_DATA  = 32,
	parameter BW_ADDR  = 5
)
(
	output [BW_DATA-1:0] o_rd_data0,
	output [BW_DATA-1:0] o_rd_data1,
	input  [BW_ADDR-1:0] i_rd_addr0,
	input  [BW_ADDR-1:0] i_rd_addr1,
	input  [BW_DATA-1:0] i_wr_data,
	input  [BW_ADDR-1:0] i_wr_addr,
	input				 i_wr_en,
	input 				 i_clk
);

	reg [BW_DATA-1:0] rf_arr[0:2**BW_ADDR-1];
	`ifdef MEM_INIT
		initial begin 
			$readmemb(MIF_FILE, rf_arr);
		end
	`endif

	assign o_rd_data0 = rf_arr[i_rd_addr0];
	assign o_rd_data1 = rf_arr[i_rd_addr1];

	always @(posedge i_clk) begin
		if(i_wr_en) begin
			rf_arr[i_wr_addr] <= i_wr_data;
		end else begin
			rf_arr[i_wr_addr] <= rf_arr[i_wr_data];
		end
	end
endmodule

03_week/07_regfile/regfile_tb.v
// ==================================================
//	[ VLSISYS Lab. ]
//	* Author		: Daseul Moon (daseul@sm.ac.kr)
//	* Filename		: regfile_tb.v
//	* Date			: 2025-03-17 15:36:08
//	* Description	: 
// ==================================================

// --------------------------------------------------
//	Define Global Variables
// --------------------------------------------------
`define	CLKFREQ		100		// Clock Freq. (Unit: MHz)
`define	SIMCYCLE	`NVEC	// Sim. Cycles
`define NVEC		2**5		// # of Test Vector
`define MEM_INIT
// --------------------------------------------------
//	Includes
// --------------------------------------------------
`include	"regfile.v"

module regfile_tb;
// --------------------------------------------------
//	DUT Signals & Instantiate
// --------------------------------------------------
	parameter BW_DATA = 32;
	parameter BW_ADDR = 5;

	wire [BW_DATA-1:0] o_rd_data0;
	wire [BW_DATA-1:0] o_rd_data1;

	reg  [BW_ADDR-1:0] i_rd_addr0;
	reg  [BW_ADDR-1:0] i_rd_addr1;
    reg  [BW_DATA-1:0] i_wr_data;
	reg  [BW_ADDR-1:0] i_wr_addr;
	reg 			   i_wr_en;
	reg			       i_clk;

	regfile 
	#(
		.MIF_FILE ("regfile.mif"),
		.BW_DATA  (BW_DATA      ),
		.BW_ADDR  (BW_ADDR	    )
	)
	u_regfile(
		.o_rd_data0 (o_rd_data0),
		.o_rd_data1 (o_rd_data1),
		.i_rd_addr0 (i_rd_addr0),
		.i_rd_addr1 (i_rd_addr1),
		.i_wr_data  (i_wr_data ),
		.i_wr_addr  (i_wr_addr ),
		.i_wr_en	(i_wr_en   ),
		.i_clk		(i_clk	   )
	);
// --------------------------------------------------
// 	Clock
// --------------------------------------------------
	always #(500/`CLKFREQ) i_clk = ~i_clk;

// --------------------------------------------------
// 	Task
// --------------------------------------------------
	reg [8*32-1:0] taskState;
	task init;
		begin
			i_rd_addr0 = 0;
			i_rd_addr1 = 0;
			i_wr_data  = 0;
			i_wr_en    = 0;
			i_clk	   = 0;
		end
	endtask

	task rfWR;
		input [BW_DATA-1:0] ti_wr_data;
		input [BW_ADDR-1:0] ti_wr_addr;
		begin
			@(negedge i_clk) begin
				i_wr_data = ti_wr_data;
				i_wr_addr = ti_wr_addr;
				i_wr_en   = 1;
			end
		end
	endtask

	task rfRD;
		input [BW_ADDR-1:0] ti_rd_addr0;
		input [BW_ADDR-1:0] ti_rd_addr1;
		begin
			@(negedge i_clk) begin
				i_rd_addr0 = ti_rd_addr0;
				i_rd_addr1 = ti_rd_addr1;
				i_wr_en    = 0;
			end
		end
	endtask

// --------------------------------------------------
//	Test Stimulus
// --------------------------------------------------
	integer		i, j;
	initial begin
		init();
		#(4*1000/`CLKFREQ);
		for (i=0; i<`SIMCYCLE; i++) begin
			rfWR(i, i);
		end

		for (i=0; i<`SIMCYCLE; i++) begin
			rfRD(i, i);
		end

		for (i=0; i<`SIMCYCLE; i++) begin
			rfWR(i, i);
			#(1000/`CLKFREQ);
			rfRD(i, i);
		end
		#(1000/`CLKFREQ);
		$finish;
	end

// --------------------------------------------------
//	Dump VCD
// --------------------------------------------------
	reg	[8*32-1:0]	vcd_file;
	initial begin
		if ($value$plusargs("vcd_file=%s", vcd_file)) begin
			$dumpfile(vcd_file);
			$dumpvars;
		end else begin
			$dumpfile("regfile_tb.vcd");
			$dumpvars;
		end
	end

endmodule

03_week/07_regfile/vcd/regfile.vcd
$date
	Mon Mar 17 15:58:08 2025
$end
$version
	Icarus Verilog
$end
$timescale
	1ps
$end
$scope module regfile_tb $end
$var wire 32 ! o_rd_data1 [31:0] $end
$var wire 32 " o_rd_data0 [31:0] $end
$var reg 1 # i_clk $end
$var reg 5 $ i_rd_addr0 [4:0] $end
$var reg 5 % i_rd_addr1 [4:0] $end
$var reg 5 & i_wr_addr [4:0] $end
$var reg 32 ' i_wr_data [31:0] $end
$var reg 1 ( i_wr_en $end
$var reg 256 ) vcd_file [255:0] $end
$var integer 32 * i [31:0] $end
$scope module u_regfile $end
$var wire 1 # i_clk $end
$var wire 5 + i_rd_addr0 [4:0] $end
$var wire 5 , i_rd_addr1 [4:0] $end
$var wire 5 - i_wr_addr [4:0] $end
$var wire 32 . i_wr_data [31:0] $end
$var wire 1 ( i_wr_en $end
$var wire 32 / o_rd_data0 [31:0] $end
$var wire 32 0 o_rd_data1 [31:0] $end
$upscope $end
$scope task init $end
$upscope $end
$scope task rfRD $end
$var reg 5 1 ti_rd_addr0 [4:0] $end
$var reg 5 2 ti_rd_addr1 [4:0] $end
$upscope $end
$scope task rfWR $end
$var reg 5 3 ti_wr_addr [4:0] $end
$var reg 32 4 ti_wr_data [31:0] $end
$upscope $end
$upscope $end
$enddefinitions $end
#0
$dumpvars
bx 4
bx 3
bx 2
bx 1
bx 0
bx /
b0 .
bx -
b0 ,
b0 +
bx *
b10111000101111011101100110001101100100001011110111001001100101011001110110011001101001011011000110010100101110011101100110001101100100 )
0(
b0 '
bx &
b0 %
b0 $
0#
bx "
bx !
$end
#5000
1#
#10000
0#
#15000
1#
#20000
0#
#25000
1#
#30000
0#
#35000
1#
#40000
1(
b0 &
b0 -
0#
b1 3
b1 4
b1 *
#45000
b0 "
b0 /
b0 !
b0 0
1#
#50000
b10 3
b10 4
b10 *
b1 &
b1 -
b1 '
b1 .
0#
#55000
1#
#60000
b11 3
b11 4
b11 *
b10 &
b10 -
b10 '
b10 .
0#
#65000
1#
#70000
b100 3
b100 4
b100 *
b11 &
b11 -
b11 '
b11 .
0#
#75000
1#
#80000
b101 3
b101 4
b101 *
b100 &
b100 -
b100 '
b100 .
0#
#85000
1#
#90000
b110 3
b110 4
b110 *
b101 &
b101 -
b101 '
b101 .
0#
#95000
1#
#100000
b111 3
b111 4
b111 *
b110 &
b110 -
b110 '
b110 .
0#
#105000
1#
#110000
b1000 3
b1000 4
b1000 *
b111 &
b111 -
b111 '
b111 .
0#
#115000
1#
#120000
b1001 3
b1001 4
b1001 *
b1000 &
b1000 -
b1000 '
b1000 .
0#
#125000
1#
#130000
b1010 3
b1010 4
b1010 *
b1001 &
b1001 -
b1001 '
b1001 .
0#
#135000
1#
#140000
b1011 3
b1011 4
b1011 *
b1010 &
b1010 -
b1010 '
b1010 .
0#
#145000
1#
#150000
b1100 3
b1100 4
b1100 *
b1011 &
b1011 -
b1011 '
b1011 .
0#
#155000
1#
#160000
b1101 3
b1101 4
b1101 *
b1100 &
b1100 -
b1100 '
b1100 .
0#
#165000
1#
#170000
b1110 3
b1110 4
b1110 *
b1101 &
b1101 -
b1101 '
b1101 .
0#
#175000
1#
#180000
b1111 3
b1111 4
b1111 *
b1110 &
b1110 -
b1110 '
b1110 .
0#
#185000
1#
#190000
b10000 3
b10000 4
b10000 *
b1111 &
b1111 -
b1111 '
b1111 .
0#
#195000
1#
#200000
b10001 3
b10001 4
b10001 *
b10000 &
b10000 -
b10000 '
b10000 .
0#
#205000
1#
#210000
b10010 3
b10010 4
b10010 *
b10001 &
b10001 -
b10001 '
b10001 .
0#
#215000
1#
#220000
b10011 3
b10011 4
b10011 *
b10010 &
b10010 -
b10010 '
b10010 .
0#
#225000
1#
#230000
b10100 3
b10100 4
b10100 *
b10011 &
b10011 -
b10011 '
b10011 .
0#
#235000
1#
#240000
b10101 3
b10101 4
b10101 *
b10100 &
b10100 -
b10100 '
b10100 .
0#
#245000
1#
#250000
b10110 3
b10110 4
b10110 *
b10101 &
b10101 -
b10101 '
b10101 .
0#
#255000
1#
#260000
b10111 3
b10111 4
b10111 *
b10110 &
b10110 -
b10110 '
b10110 .
0#
#265000
1#
#270000
b11000 3
b11000 4
b11000 *
b10111 &
b10111 -
b10111 '
b10111 .
0#
#275000
1#
#280000
b11001 3
b11001 4
b11001 *
b11000 &
b11000 -
b11000 '
b11000 .
0#
#285000
1#
#290000
b11010 3
b11010 4
b11010 *
b11001 &
b11001 -
b11001 '
b11001 .
0#
#295000
1#
#300000
b11011 3
b11011 4
b11011 *
b11010 &
b11010 -
b11010 '
b11010 .
0#
#305000
1#
#310000
b11100 3
b11100 4
b11100 *
b11011 &
b11011 -
b11011 '
b11011 .
0#
#315000
1#
#320000
b11101 3
b11101 4
b11101 *
b11100 &
b11100 -
b11100 '
b11100 .
0#
#325000
1#
#330000
b11110 3
b11110 4
b11110 *
b11101 &
b11101 -
b11101 '
b11101 .
0#
#335000
1#
#340000
b11111 3
b11111 4
b11111 *
b11110 &
b11110 -
b11110 '
b11110 .
0#
#345000
1#
#350000
b0 2
b0 1
b0 *
b11111 &
b11111 -
b11111 '
b11111 .
0#
#355000
1#
#360000
b1 2
b1 1
b1 *
0(
0#
#365000
1#
#370000
b10 2
b10 1
b10 *
b1 !
b1 0
b1 %
b1 ,
b1 "
b1 /
b1 $
b1 +
0#
#375000
1#
#380000
b11 2
b11 1
b11 *
b10 !
b10 0
b10 %
b10 ,
b10 "
b10 /
b10 $
b10 +
0#
#385000
1#
#390000
b100 2
b100 1
b100 *
b11 !
b11 0
b11 %
b11 ,
b11 "
b11 /
b11 $
b11 +
0#
#395000
1#
#400000
b101 2
b101 1
b101 *
b100 !
b100 0
b100 %
b100 ,
b100 "
b100 /
b100 $
b100 +
0#
#405000
1#
#410000
b110 2
b110 1
b110 *
b101 !
b101 0
b101 %
b101 ,
b101 "
b101 /
b101 $
b101 +
0#
#415000
1#
#420000
b111 2
b111 1
b111 *
b110 !
b110 0
b110 %
b110 ,
b110 "
b110 /
b110 $
b110 +
0#
#425000
1#
#430000
b1000 2
b1000 1
b1000 *
b111 !
b111 0
b111 %
b111 ,
b111 "
b111 /
b111 $
b111 +
0#
#435000
1#
#440000
b1001 2
b1001 1
b1001 *
b1000 !
b1000 0
b1000 %
b1000 ,
b1000 "
b1000 /
b1000 $
b1000 +
0#
#445000
1#
#450000
b1010 2
b1010 1
b1010 *
b1001 !
b1001 0
b1001 %
b1001 ,
b1001 "
b1001 /
b1001 $
b1001 +
0#
#455000
1#
#460000
b1011 2
b1011 1
b1011 *
b1010 !
b1010 0
b1010 %
b1010 ,
b1010 "
b1010 /
b1010 $
b1010 +
0#
#465000
1#
#470000
b1100 2
b1100 1
b1100 *
b1011 !
b1011 0
b1011 %
b1011 ,
b1011 "
b1011 /
b1011 $
b1011 +
0#
#475000
1#
#480000
b1101 2
b1101 1
b1101 *
b1100 !
b1100 0
b1100 %
b1100 ,
b1100 "
b1100 /
b1100 $
b1100 +
0#
#485000
1#
#490000
b1110 2
b1110 1
b1110 *
b1101 !
b1101 0
b1101 %
b1101 ,
b1101 "
b1101 /
b1101 $
b1101 +
0#
#495000
1#
#500000
b1111 2
b1111 1
b1111 *
b1110 !
b1110 0
b1110 %
b1110 ,
b1110 "
b1110 /
b1110 $
b1110 +
0#
#505000
1#
#510000
b10000 2
b10000 1
b10000 *
b1111 !
b1111 0
b1111 %
b1111 ,
b1111 "
b1111 /
b1111 $
b1111 +
0#
#515000
1#
#520000
b10001 2
b10001 1
b10001 *
b10000 !
b10000 0
b10000 %
b10000 ,
b10000 "
b10000 /
b10000 $
b10000 +
0#
#525000
1#
#530000
b10010 2
b10010 1
b10010 *
b10001 !
b10001 0
b10001 %
b10001 ,
b10001 "
b10001 /
b10001 $
b10001 +
0#
#535000
1#
#540000
b10011 2
b10011 1
b10011 *
b10010 !
b10010 0
b10010 %
b10010 ,
b10010 "
b10010 /
b10010 $
b10010 +
0#
#545000
1#
#550000
b10100 2
b10100 1
b10100 *
b10011 !
b10011 0
b10011 %
b10011 ,
b10011 "
b10011 /
b10011 $
b10011 +
0#
#555000
1#
#560000
b10101 2
b10101 1
b10101 *
b10100 !
b10100 0
b10100 %
b10100 ,
b10100 "
b10100 /
b10100 $
b10100 +
0#
#565000
1#
#570000
b10110 2
b10110 1
b10110 *
b10101 !
b10101 0
b10101 %
b10101 ,
b10101 "
b10101 /
b10101 $
b10101 +
0#
#575000
1#
#580000
b10111 2
b10111 1
b10111 *
b10110 !
b10110 0
b10110 %
b10110 ,
b10110 "
b10110 /
b10110 $
b10110 +
0#
#585000
1#
#590000
b11000 2
b11000 1
b11000 *
b10111 !
b10111 0
b10111 %
b10111 ,
b10111 "
b10111 /
b10111 $
b10111 +
0#
#595000
1#
#600000
b11001 2
b11001 1
b11001 *
b11000 !
b11000 0
b11000 %
b11000 ,
b11000 "
b11000 /
b11000 $
b11000 +
0#
#605000
1#
#610000
b11010 2
b11010 1
b11010 *
b11001 !
b11001 0
b11001 %
b11001 ,
b11001 "
b11001 /
b11001 $
b11001 +
0#
#615000
1#
#620000
b11011 2
b11011 1
b11011 *
b11010 !
b11010 0
b11010 %
b11010 ,
b11010 "
b11010 /
b11010 $
b11010 +
0#
#625000
1#
#630000
b11100 2
b11100 1
b11100 *
b11011 !
b11011 0
b11011 %
b11011 ,
b11011 "
b11011 /
b11011 $
b11011 +
0#
#635000
1#
#640000
b11101 2
b11101 1
b11101 *
b11100 !
b11100 0
b11100 %
b11100 ,
b11100 "
b11100 /
b11100 $
b11100 +
0#
#645000
1#
#650000
b11110 2
b11110 1
b11110 *
b11101 !
b11101 0
b11101 %
b11101 ,
b11101 "
b11101 /
b11101 $
b11101 +
0#
#655000
1#
#660000
b11111 2
b11111 1
b11111 *
b11110 !
b11110 0
b11110 %
b11110 ,
b11110 "
b11110 /
b11110 $
b11110 +
0#
#665000
1#
#670000
b0 3
b0 4
b0 *
b11111 !
b11111 0
b11111 %
b11111 ,
b11111 "
b11111 /
b11111 $
b11111 +
0#
#675000
1#
#680000
1(
b0 &
b0 -
b0 '
b0 .
0#
#685000
1#
#690000
b1 3
b1 4
b1 *
0(
b0 !
b0 0
b0 %
b0 ,
b0 "
b0 /
b0 $
b0 +
0#
b0 2
b0 1
#695000
1#
#700000
1(
b1 &
b1 -
b1 '
b1 .
0#
#705000
1#
#710000
b10 3
b10 4
b10 *
0(
b1 !
b1 0
b1 %
b1 ,
b1 "
b1 /
b1 $
b1 +
0#
b1 2
b1 1
#715000
1#
#720000
1(
b10 &
b10 -
b10 '
b10 .
0#
#725000
1#
#730000
b11 3
b11 4
b11 *
0(
b10 !
b10 0
b10 %
b10 ,
b10 "
b10 /
b10 $
b10 +
0#
b10 2
b10 1
#735000
1#
#740000
1(
b11 &
b11 -
b11 '
b11 .
0#
#745000
1#
#750000
b100 3
b100 4
b100 *
0(
b11 !
b11 0
b11 %
b11 ,
b11 "
b11 /
b11 $
b11 +
0#
b11 2
b11 1
#755000
1#
#760000
1(
b100 &
b100 -
b100 '
b100 .
0#
#765000
1#
#770000
b101 3
b101 4
b101 *
0(
b100 !
b100 0
b100 %
b100 ,
b100 "
b100 /
b100 $
b100 +
0#
b100 2
b100 1
#775000
1#
#780000
1(
b101 &
b101 -
b101 '
b101 .
0#
#785000
1#
#790000
b110 3
b110 4
b110 *
0(
b101 !
b101 0
b101 %
b101 ,
b101 "
b101 /
b101 $
b101 +
0#
b101 2
b101 1
#795000
1#
#800000
1(
b110 &
b110 -
b110 '
b110 .
0#
#805000
1#
#810000
b111 3
b111 4
b111 *
0(
b110 !
b110 0
b110 %
b110 ,
b110 "
b110 /
b110 $
b110 +
0#
b110 2
b110 1
#815000
1#
#820000
1(
b111 &
b111 -
b111 '
b111 .
0#
#825000
1#
#830000
b1000 3
b1000 4
b1000 *
0(
b111 !
b111 0
b111 %
b111 ,
b111 "
b111 /
b111 $
b111 +
0#
b111 2
b111 1
#835000
1#
#840000
1(
b1000 &
b1000 -
b1000 '
b1000 .
0#
#845000
1#
#850000
b1001 3
b1001 4
b1001 *
0(
b1000 !
b1000 0
b1000 %
b1000 ,
b1000 "
b1000 /
b1000 $
b1000 +
0#
b1000 2
b1000 1
#855000
1#
#860000
1(
b1001 &
b1001 -
b1001 '
b1001 .
0#
#865000
1#
#870000
b1010 3
b1010 4
b1010 *
0(
b1001 !
b1001 0
b1001 %
b1001 ,
b1001 "
b1001 /
b1001 $
b1001 +
0#
b1001 2
b1001 1
#875000
1#
#880000
1(
b1010 &
b1010 -
b1010 '
b1010 .
0#
#885000
1#
#890000
b1011 3
b1011 4
b1011 *
0(
b1010 !
b1010 0
b1010 %
b1010 ,
b1010 "
b1010 /
b1010 $
b1010 +
0#
b1010 2
b1010 1
#895000
1#
#900000
1(
b1011 &
b1011 -
b1011 '
b1011 .
0#
#905000
1#
#910000
b1100 3
b1100 4
b1100 *
0(
b1011 !
b1011 0
b1011 %
b1011 ,
b1011 "
b1011 /
b1011 $
b1011 +
0#
b1011 2
b1011 1
#915000
1#
#920000
1(
b1100 &
b1100 -
b1100 '
b1100 .
0#
#925000
1#
#930000
b1101 3
b1101 4
b1101 *
0(
b1100 !
b1100 0
b1100 %
b1100 ,
b1100 "
b1100 /
b1100 $
b1100 +
0#
b1100 2
b1100 1
#935000
1#
#940000
1(
b1101 &
b1101 -
b1101 '
b1101 .
0#
#945000
1#
#950000
b1110 3
b1110 4
b1110 *
0(
b1101 !
b1101 0
b1101 %
b1101 ,
b1101 "
b1101 /
b1101 $
b1101 +
0#
b1101 2
b1101 1
#955000
1#
#960000
1(
b1110 &
b1110 -
b1110 '
b1110 .
0#
#965000
1#
#970000
b1111 3
b1111 4
b1111 *
0(
b1110 !
b1110 0
b1110 %
b1110 ,
b1110 "
b1110 /
b1110 $
b1110 +
0#
b1110 2
b1110 1
#975000
1#
#980000
1(
b1111 &
b1111 -
b1111 '
b1111 .
0#
#985000
1#
#990000
b10000 3
b10000 4
b10000 *
0(
b1111 !
b1111 0
b1111 %
b1111 ,
b1111 "
b1111 /
b1111 $
b1111 +
0#
b1111 2
b1111 1
#995000
1#
#1000000
1(
b10000 &
b10000 -
b10000 '
b10000 .
0#
#1005000
1#
#1010000
b10001 3
b10001 4
b10001 *
0(
b10000 !
b10000 0
b10000 %
b10000 ,
b10000 "
b10000 /
b10000 $
b10000 +
0#
b10000 2
b10000 1
#1015000
1#
#1020000
1(
b10001 &
b10001 -
b10001 '
b10001 .
0#
#1025000
1#
#1030000
b10010 3
b10010 4
b10010 *
0(
b10001 !
b10001 0
b10001 %
b10001 ,
b10001 "
b10001 /
b10001 $
b10001 +
0#
b10001 2
b10001 1
#1035000
1#
#1040000
1(
b10010 &
b10010 -
b10010 '
b10010 .
0#
#1045000
1#
#1050000
b10011 3
b10011 4
b10011 *
0(
b10010 !
b10010 0
b10010 %
b10010 ,
b10010 "
b10010 /
b10010 $
b10010 +
0#
b10010 2
b10010 1
#1055000
1#
#1060000
1(
b10011 &
b10011 -
b10011 '
b10011 .
0#
#1065000
1#
#1070000
b10100 3
b10100 4
b10100 *
0(
b10011 !
b10011 0
b10011 %
b10011 ,
b10011 "
b10011 /
b10011 $
b10011 +
0#
b10011 2
b10011 1
#1075000
1#
#1080000
1(
b10100 &
b10100 -
b10100 '
b10100 .
0#
#1085000
1#
#1090000
b10101 3
b10101 4
b10101 *
0(
b10100 !
b10100 0
b10100 %
b10100 ,
b10100 "
b10100 /
b10100 $
b10100 +
0#
b10100 2
b10100 1
#1095000
1#
#1100000
1(
b10101 &
b10101 -
b10101 '
b10101 .
0#
#1105000
1#
#1110000
b10110 3
b10110 4
b10110 *
0(
b10101 !
b10101 0
b10101 %
b10101 ,
b10101 "
b10101 /
b10101 $
b10101 +
0#
b10101 2
b10101 1
#1115000
1#
#1120000
1(
b10110 &
b10110 -
b10110 '
b10110 .
0#
#1125000
1#
#1130000
b10111 3
b10111 4
b10111 *
0(
b10110 !
b10110 0
b10110 %
b10110 ,
b10110 "
b10110 /
b10110 $
b10110 +
0#
b10110 2
b10110 1
#1135000
1#
#1140000
1(
b10111 &
b10111 -
b10111 '
b10111 .
0#
#1145000
1#
#1150000
b11000 3
b11000 4
b11000 *
0(
b10111 !
b10111 0
b10111 %
b10111 ,
b10111 "
b10111 /
b10111 $
b10111 +
0#
b10111 2
b10111 1
#1155000
1#
#1160000
1(
b11000 &
b11000 -
b11000 '
b11000 .
0#
#1165000
1#
#1170000
b11001 3
b11001 4
b11001 *
0(
b11000 !
b11000 0
b11000 %
b11000 ,
b11000 "
b11000 /
b11000 $
b11000 +
0#
b11000 2
b11000 1
#1175000
1#
#1180000
1(
b11001 &
b11001 -
b11001 '
b11001 .
0#
#1185000
1#
#1190000
b11010 3
b11010 4
b11010 *
0(
b11001 !
b11001 0
b11001 %
b11001 ,
b11001 "
b11001 /
b11001 $
b11001 +
0#
b11001 2
b11001 1
#1195000
1#
#1200000
1(
b11010 &
b11010 -
b11010 '
b11010 .
0#
#1205000
1#
#1210000
b11011 3
b11011 4
b11011 *
0(
b11010 !
b11010 0
b11010 %
b11010 ,
b11010 "
b11010 /
b11010 $
b11010 +
0#
b11010 2
b11010 1
#1215000
1#
#1220000
1(
b11011 &
b11011 -
b11011 '
b11011 .
0#
#1225000
1#
#1230000
b11100 3
b11100 4
b11100 *
0(
b11011 !
b11011 0
b11011 %
b11011 ,
b11011 "
b11011 /
b11011 $
b11011 +
0#
b11011 2
b11011 1
#1235000
1#
#1240000
1(
b11100 &
b11100 -
b11100 '
b11100 .
0#
#1245000
1#
#1250000
b11101 3
b11101 4
b11101 *
0(
b11100 !
b11100 0
b11100 %
b11100 ,
b11100 "
b11100 /
b11100 $
b11100 +
0#
b11100 2
b11100 1
#1255000
1#
#1260000
1(
b11101 &
b11101 -
b11101 '
b11101 .
0#
#1265000
1#
#1270000
b11110 3
b11110 4
b11110 *
0(
b11101 !
b11101 0
b11101 %
b11101 ,
b11101 "
b11101 /
b11101 $
b11101 +
0#
b11101 2
b11101 1
#1275000
1#
#1280000
1(
b11110 &
b11110 -
b11110 '
b11110 .
0#
#1285000
1#
#1290000
b11111 3
b11111 4
b11111 *
0(
b11110 !
b11110 0
b11110 %
b11110 ,
b11110 "
b11110 /
b11110 $
b11110 +
0#
b11110 2
b11110 1
#1295000
1#
#1300000
1(
b11111 &
b11111 -
b11111 '
b11111 .
0#
#1305000
1#
#1310000
b100000 *
0(
b11111 !
b11111 0
b11111 %
b11111 ,
b11111 "
b11111 /
b11111 $
b11111 +
0#
b11111 2
b11111 1
