project_01/2_alu/alu.v
// ==================================================
//	[ VLSISYS Lab. ]
//	* Author		: Daseul Moon (daseul@sm.ac.kr)
//	* Filename		: alu.v
//	* Date			: 2025-03-18 13:13:22
//	* Description	: 
// ==================================================

module alu
(
	output reg [31:0] o_y,
	output      	  o_c,
	input 	   [31:0] i_a,
	input  	   [31:0] i_b,
	input  	   [2:0]  i_f
);

	wire [31:0] b_mux;
	wire [31:0] sum;

	assign b_mux      = i_f[2] ? ~i_b : i_b;
	assign {o_c, sum} = i_a + b_mux + i_f[2];

	always @(*) begin
		case(i_f[1:0])
			2'b00: o_y = i_a & b_mux;
			2'b01: o_y = i_a | b_mux;
			2'b10: o_y = i_a + b_mux;
			2'b11: o_y = {{31{1'b0}}, sum[31]};
		endcase
	end

endmodule

project_01/2_alu/alu_tb.v
// ==================================================
//	[ VLSISYS Lab. ]
//	* Author		: Daseul Moon (daseul@sm.ac.kr)
//	* Filename		: alu_tb.v
//	* Date			: 2025-03-18 13:20:36
//	* Description	: 
// ==================================================

// --------------------------------------------------
//	Define Global Variables
// --------------------------------------------------
`define	CLKFREQ		100		// Clock Freq. (Unit: MHz)
`define	SIMCYCLE	`NVEC	// Sim. Cycles
`define NVEC		100		// # of Test Vector

// --------------------------------------------------
//	Includes
// --------------------------------------------------
`include	"alu.v"

module alu_tb;
// --------------------------------------------------
//	DUT Signals & Instantiate
// --------------------------------------------------
	wire [31:0] o_y;
	wire        o_c;
	reg  [31:0] i_a;
	reg  [31:0] i_b;
	reg  [2:0]  i_f;

	alu
	u_alu(
		.o_y (o_y),
		.o_c (o_c),
		.i_a (i_a),
		.i_b (i_b),
		.i_f (i_f)
	);

// --------------------------------------------------
// 	Task
// ---------------------------------------------------
	reg [8*32-1:0] taskState;
	task init;
		begin
			taskState = "Init";
			i_a 	  = 0;
			i_b		  = 0;
			i_f 	  = 0;
		end
	endtask

	task fcode;
		input [8*32-1:0] ti_fcode_string;
		input [2:0]      ti_fcode;
		begin
			taskState = ti_fcode_string;
			i_a       = $urandom;
			i_b		  = $urandom;
			i_f		  = ti_fcode;
			#(1000/`CLKFREQ);
		end
	endtask

// --------------------------------------------------
//	Test Stimulus
// --------------------------------------------------
	integer		i, j;
	initial begin
		init();
		#(4*1000/`CLKFREQ);
		for (i=0; i<`SIMCYCLE; i++) begin
			fcode("A & B", 3'b000  );
			fcode("A | B", 3'b001  );
			fcode("A + B", 3'b010  );
			fcode("A & ~B", 3'b100 );
			fcode("A | ~B", 3'b101 );
			fcode("A - B", 3'b110  );
			fcode("A<B?1:0", 3'b111);
		end
		#(1000/`CLKFREQ);
		$finish;
	end

// --------------------------------------------------
//	Dump VCD
// --------------------------------------------------
	reg	[8*32-1:0]	vcd_file;
	initial begin
		if ($value$plusargs("vcd_file=%s", vcd_file)) begin
			$dumpfile(vcd_file);
			$dumpvars;
		end else begin
			$dumpfile("alu_tb.vcd");
			$dumpvars;
		end
	end

endmodule

project_01/2_alu/vcd/alu.vcd
$date
	Tue Mar 18 13:24:06 2025
$end
$version
	Icarus Verilog
$end
$timescale
	1ps
$end
$scope module alu_tb $end
$var wire 32 ! o_y [31:0] $end
$var wire 1 " o_c $end
$var reg 32 # i_a [31:0] $end
$var reg 32 $ i_b [31:0] $end
$var reg 3 % i_f [2:0] $end
$var reg 256 & taskState [255:0] $end
$var reg 256 ' vcd_file [255:0] $end
$var integer 32 ( i [31:0] $end
$scope module u_alu $end
$var wire 32 ) i_a [31:0] $end
$var wire 32 * i_b [31:0] $end
$var wire 3 + i_f [2:0] $end
$var wire 32 , sum [31:0] $end
$var wire 1 " o_c $end
$var wire 32 - b_mux [31:0] $end
$var reg 32 . o_y [31:0] $end
$upscope $end
$scope task fcode $end
$var reg 3 / ti_fcode [2:0] $end
$var reg 256 0 ti_fcode_string [255:0] $end
$upscope $end
$scope task init $end
$upscope $end
$upscope $end
$enddefinitions $end
#0
$dumpvars
bx 0
bx /
b0 .
b0 -
b0 ,
b0 +
b0 *
b0 )
bx (
b101110001011110111011001100011011001000010111101100001011011000111010100101110011101100110001101100100 '
b1001001011011100110100101110100 &
b0 %
b0 $
b0 #
0"
b0 !
$end
#40000
b10001010000000000 !
b10001010000000000 .
b1000000100010010101111010000001 -
b11010010100111101001001110100101 ,
b1000000100010010101111010000001 $
b1000000100010010101111010000001 *
b10010010000101010011010100100100 #
b10010010000101010011010100100100 )
b100000100100000001001100010000001000010 &
b0 /
b100000100100000001001100010000001000010 0
b0 (
#50000
b110001111100000101011001100011 -
b110101111101001101011001101011 !
b110101111101001101011001101011 .
b110110011101010010110001101100 ,
b1 %
b1 +
b110001111100000101011001100011 $
b110001111100000101011001100011 *
b100100001001101011000001001 #
b100100001001101011000001001 )
b100000100100000011111000010000001000010 &
b1 /
b100000100100000011111000010000001000010 0
#60000
1"
b11000110110111111001100110001101 -
b1001101100110010001010010011010 !
b1001101100110010001010010011010 .
b1001101100110010001010010011010 ,
b10 %
b10 +
b11000110110111111001100110001101 $
b11000110110111111001100110001101 *
b10000110101110010111101100001101 #
b10000110101110010111101100001101 )
b100000100100000001010110010000001000010 &
b10 /
b100000100100000001010110010000001000010 0
#70000
b11110110110010001010110111101101 -
b110010110000001000010001100101 !
b110010110000001000010001100101 .
b101001100010110011001001010011 ,
1"
b100 %
b100 +
b1001001101110101001000010010 $
b1001001101110101001000010010 *
b110010110000101000010001100101 #
b110010110000101000010001100101 )
b10000010010000000100110001000000111111001000010 &
b100 /
b10000010010000000100110001000000111111001000010 0
#80000
0"
b1111001001010000011001011110010 -
b11111001111110111111001111110011 !
b11111001111110111111001111110011 .
b11111010000111000001010111110100 ,
b101 %
b101 +
b10000110110101111100110100001101 $
b10000110110101111100110100001101 *
b10000000111100111110001100000001 #
b10000000111100111110001100000001 )
b10000010010000001111100001000000111111001000010 &
b101 /
b10000010010000001111100001000000111111001000010 0
#90000
b1100001011100100011001011000010 -
b11100100101100010010000111000 !
b11100100101100010010000111000 .
b11100100101100010010000111001 ,
1"
b110 %
b110 +
b10011110100011011100110100111101 $
b10011110100011011100110100111101 *
b10111011001000111111000101110110 #
b10111011001000111111000101110110 )
b100000100100000001011010010000001000010 &
b110 /
b100000100100000001011010010000001000010 0
#100000
b111001110100100000100001110011 -
b0 !
b0 .
b110000101001100110000001100001 ,
b111 %
b111 +
b11000110001011011111011110001100 $
b11000110001011011111011110001100 *
b11110110110101000101011111101101 #
b11110110110101000101011111101101 )
b1000001001111000100001000111111001100010011101000110000 &
b111 /
b1000001001111000100001000111111001100010011101000110000 0
#110000
b1100011001101110010010011000110 -
b1100000001101010010000011000000 !
b1100000001101010010000011000000 .
b1100000001101010000111010111111 ,
b0 %
b0 +
b1100011001101110010010011000110 $
b1100011001101110010010011000110 *
b11111100111111011110100111111001 #
b11111100111111011110100111111001 )
b100000100100000001001100010000001000010 &
b0 /
b100000100100000001001100010000001000010 0
b1 (
#120000
b1010101000100111101001010101010 -
b1110111111101111101011011101111 !
b1110111111101111101011011101111 .
b10111000000010110101011101101111 ,
0"
b1 %
b1 +
b1010101000100111101001010101010 $
b1010101000100111101001010101010 *
b1100010111101111000010011000101 #
b1100010111101111000010011000101 )
b100000100100000011111000010000001000010 &
b1 /
b100000100100000011111000010000001000010 0
#130000
b111011110100100111001001110111 -
b101110100000100110101001011100 !
b101110100000100110101001011100 .
b101110100000100110101001011100 ,
1"
b10 %
b10 +
b111011110100100111001001110111 $
b111011110100100111001001110111 *
b11110010101011111111011111100101 #
b11110010101011111111011111100101 )
b100000100100000001010110010000001000010 &
b10 /
b100000100100000001010110010000001000010 0
#140000
b111000000100110010010001110000 -
b1000000100100000010000010000 !
b1000000100100000010000010000 .
b1000001010001011111101010000011 ,
0"
b100 %
b100 +
b11000111111011001101101110001111 $
b11000111111011001101101110001111 *
b1001001100101101011000010010 #
b1001001100101101011000010010 )
b10000010010000000100110001000000111111001000010 &
b100 /
b10000010010000000100110001000000111111001000010 0
#150000
b10011000100010010110100100110001 -
b11111001101110010110100111110011 !
b11111001101110010110100111110011 .
b10010001101110011101001100100100 ,
1"
b101 %
b101 +
b1100111011101101001011011001110 $
b1100111011101101001011011001110 *
b11111001001100000110100111110010 #
b11111001001100000110100111110010 )
b10000010010000001111100001000000111111001000010 &
b101 /
b10000010010000001111100001000000111111001000010 0
#160000
b10011101001101011011000100111010 -
b10001001101100010110000100010 !
b10001001101100010110000100010 .
b10001001101100010110000100011 ,
b110 %
b110 +
b1100010110010100100111011000101 $
b1100010110010100100111011000101 *
b1110100000000000111101011101000 #
b1110100000000000111101011101000 )
b100000100100000001011010010000001000010 &
b110 /
b100000100100000001011010010000001000010 0
#170000
b10100001011100011101011101000010 -
b0 !
b0 .
b1001111110010100010000010011111 ,
b111 %
b111 +
b1011110100011100010100010111101 $
b1011110100011100010100010111101 *
b10101110010110000100100101011100 #
b10101110010110000100100101011100 )
b1000001001111000100001000111111001100010011101000110000 &
b111 /
b1000001001111000100001000111111001100010011101000110000 0
#180000
b110010101001110010011001100101 -
b10010101000110000000000100101 !
b10010101000110000000000100101 .
b1001001010100100111111010010010 ,
0"
b0 %
b0 +
b110010101001110010011001100101 $
b110010101001110010011001100101 *
b10110101010110101100000101101 #
b10110101010110101100000101101 )
b100000100100000001001100010000001000010 &
b0 /
b100000100100000001001100010000001000010 0
b10 (
#190000
b10000101011100111000011100001010 -
b10110101111111111110011101101011 !
b10110101111111111110011101101011 .
b10110111011000101110100101101101 ,
b1 %
b1 +
b10000101011100111000011100001010 $
b10000101011100111000011100001010 *
b110001111011110110001001100011 #
b110001111011110110001001100011 )
b100000100100000011111000010000001000010 &
b1 /
b100000100100000011111000010000001000010 0
#200000
b10010000011001000010000100100000 -
b11010000100111110100001110100000 !
b11010000100111110100001110100000 .
b11010000100111110100001110100000 ,
b10 %
b10 +
b10010000011001000010000100100000 $
b10010000011001000010000100100000 *
b1000000001110110010001010000000 #
b1000000001110110010001010000000 )
b100000100100000001010110010000001000010 &
b10 /
b100000100100000001010110010000001000010 0
#210000
b10110001001100110011001101100010 -
b10010001001100000000000100100010 !
b10010001001100000000000100100010 .
b10000110101010110111100100001101 ,
1"
b100 %
b100 +
b1001110110011001100110010011101 $
b1001110110011001100110010011101 *
b11010101011110000100010110101010 #
b11010101011110000100010110101010 )
b10000010010000000100110001000000111111001000010 &
b100 /
b10000010010000000100110001000000111111001000010 0
#220000
b11110110011111000100011111101100 -
b11111111011111000111111111111110 !
b11111111011111000111111111111110 .
b1000001100111001000011010000011 ,
1"
b101 %
b101 +
b1001100000111011100000010011 $
b1001100000111011100000010011 *
b1001011001000000011111010010110 #
b1001011001000000011111010010110 )
b10000010010000001111100001000000111111001000010 &
b101 /
b10000010010000001111100001000000111111001000010 0
#230000
b11010110010110000010100110101100 -
b11011101000101000110000110111001 !
b11011101000101000110000110111001 .
b11011101000101000110000110111010 ,
0"
b110 %
b110 +
b101001101001111101011001010011 $
b101001101001111101011001010011 *
b110101111000011100000001101 #
b110101111000011100000001101 )
b100000100100000001011010010000001000010 &
b110 /
b100000100100000001011010010000001000010 0
#240000
b10010101010110011101010100101010 -
b0 !
b0 .
b1001010111110011011001010010110 ,
1"
b111 %
b111 +
b1101010101001100010101011010101 $
b1101010101001100010101011010101 *
b10110101100111111101110101101011 #
b10110101100111111101110101101011 )
b1000001001111000100001000111111001100010011101000110000 &
b111 /
b1000001001111000100001000111111001100010011101000110000 0
#250000
b1010111010101100011111010101110 -
b1000101100000101000000010 !
b1000101100000101000000010 .
b1011000011011011000100010110000 ,
0"
b0 %
b0 +
b1010111010101100011111010101110 $
b1010111010101100011111010101110 *
b1000101110100101000000010 #
b1000101110100101000000010 )
b100000100100000001001100010000001000010 &
b0 /
b100000100100000001001100010000001000010 0
b11 (
#260000
b1100111110001010111001011001111 -
b11101111111111111111101111011111 !
b11101111111111111111101111011111 .
b11110110110001010101101111101100 ,
b1 %
b1 +
b1100111110001010111001011001111 $
b1100111110001010111001011001111 *
b10001110111111111110100100011101 #
b10001110111111111110100100011101 )
b100000100100000011111000010000001000010 &
b1 /
b100000100100000011111000010000001000010 0
#270000
1"
b10000101000010010110010100001010 -
b10110100011011010111000101101 !
b10110100011011010111000101101 .
b10110100011011010111000101101 ,
b10 %
b10 +
b10000101000010010110010100001010 $
b10000101000010010110010100001010 *
b10010001100001000100100100100011 #
b10010001100001000100100100100011 )
b100000100100000001010110010000001000010 &
b10 /
b100000100100000001010110010000001000010 0
#280000
b11100001110011101011001111000011 -
b1100001010000100000001011000010 !
b1100001010000100000001011000010 .
b1000111010000011011111010001110 ,
1"
b100 %
b100 +
b11110001100010100110000111100 $
b11110001100010100110000111100 *
b1100101011100110000101011001010 #
b1100101011100110000101011001010 )
b10000010010000000100110001000000111111001000010 &
b100 /
b10000010010000000100110001000000111111001000010 0
#290000
b111010110100011001111001110101 -
b11111011111110011011111111110111 !
b11111011111110011011111111110111 .
b110100001110100101110001101000 ,
b101 %
b101 +
b11000101001011100110000110001010 $
b11000101001011100110000110001010 *
b11111001011010001011110111110010 #
b11111001011010001011110111110010 )
b10000010010000001111100001000000111111001000010 &
b101 /
b10000010010000001111100001000000111111001000010 0
#300000
b10010011101101001100101100100111 -
b110100011110010111111001101000 !
b110100011110010111111001101000 .
b110100011110010111111001101001 ,
1"
b110 %
b110 +
b1101100010010110011010011011000 $
b1101100010010110011010011011000 *
b10100000110001001011001101000001 #
b10100000110001001011001101000001 )
b100000100100000001011010010000001000010 &
b110 /
b100000100100000001011010010000001000010 0
#310000
b10111011011101011110110101110110 -
b0 !
b0 .
b1110111100101101110000011101111 ,
b111 %
b111 +
b1000100100010100001001010001001 $
b1000100100010100001001010001001 *
b10111100001000001111001101111000 #
b10111100001000001111001101111000 )
b1000001001111000100001000111111001100010011101000110000 &
b111 /
b1000001001111000100001000111111001100010011101000110000 0
#320000
b11011011000000100110010110110110 -
b11010001000000000000010110100010 !
b11010001000000000000010110100010 .
b11010000110001110111001110100001 ,
b0 %
b0 +
b11011011000000100110010110110110 $
b11011011000000100110010110110110 *
b11110101110001010000110111101011 #
b11110101110001010000110111101011 )
b100000100100000001001100010000001000010 &
b0 /
b100000100100000001001100010000001000010 0
b100 (
#330000
b11010111000101010001001110101110 -
b11110111010111111111101111101110 !
b11110111010111111111101111101110 .
b10111010011000010000110101110100 ,
b1 %
b1 +
b11010111000101010001001110101110 $
b11010111000101010001001110101110 *
b11100011010010111111100111000110 #
b11100011010010111111100111000110 )
b100000100100000011111000010000001000010 &
b1 /
b100000100100000011111000010000001000010 0
#340000
0"
b10010101000011111101110100101010 -
b11110011100001001101111111100110 !
b11110011100001001101111111100110 .
b11110011100001001101111111100110 ,
b10 %
b10 +
b10010101000011111101110100101010 $
b10010101000011111101110100101010 *
b1011110011101010000001010111100 #
b1011110011101010000001010111100 )
b100000100100000001010110010000001000010 &
b10 /
b100000100100000001010110010000001000010 0
#350000
b11000111011010000100000110001110 -
b101010000000000000000001010 !
b101010000000000000000001010 .
b11001101001111111101101110011010 ,
b100 %
b100 +
b111000100101111011111001110001 $
b111000100101111011111001110001 *
b101110101111001101000001011 #
b101110101111001101000001011 )
b10000010010000000100110001000000111111001000010 &
b100 /
b10000010010000000100110001000000111111001000010 0
#360000
b1011000000011011010101010110000 -
b11011010111111111110101110110101 !
b11011010111111111110101110110101 .
b11010111111111110110000110110 ,
1"
b101 %
b101 +
b10100111111100100101010101001111 $
b10100111111100100101010101001111 *
b11000010111100100100000110000101 #
b11000010111100100100000110000101 )
b10000010010000001111100001000000111111001000010 &
b101 /
b10000010010000001111100001000000111111001000010 0
#370000
b1100010111110011100110011000101 -
b10000000110001100010110100000000 !
b10000000110001100010110100000000 .
b10000000110001100010110100000001 ,
0"
b110 %
b110 +
b10011101000001100011001100111010 $
b10011101000001100011001100111010 *
b11101110011000110000000111011 #
b11101110011000110000000111011 )
b100000100100000001011010010000001000010 &
b110 /
b100000100100000001011010010000001000010 0
#380000
b1110101010101011011010011101010 -
b1 !
b1 .
b10110100011110001110011101101001 ,
b111 %
b111 +
b10001010101010100100101100010101 $
b10001010101010100100101100010101 *
b111111001000110011001001111110 #
b111111001000110011001001111110 )
b1000001001111000100001000111111001100010011101000110000 &
b111 /
b1000001001111000100001000111111001100010011101000110000 0
#390000
b11101100100111000100101111011001 -
b11101000100110000000101111010001 !
b11101000100110000000101111010001 .
b11100101011101011110011111001010 ,
1"
b0 %
b0 +
b11101100100111000100101111011001 $
b11101100100111000100101111011001 *
b11111000110110011001101111110001 #
b11111000110110011001101111110001 )
b100000100100000001001100010000001000010 &
b0 /
b100000100100000001001100010000001000010 0
b101 (
#400000
b10100110001101011111101101001100 -
b10110111001101111111111101101110 !
b10110111001101111111111101101110 .
b1010111010110010000001010101110 ,
b1 %
b1 +
b10100110001101011111101101001100 $
b10100110001101011111101101001100 *
b10110001001000110000011101100010 #
b10110001001000110000011101100010 )
b100000100100000011111000010000001000010 &
b1 /
b100000100100000011111000010000001000010 0
#410000
b11000111101110011010000110001111 -
b10010111010110101111011100101110 !
b10010111010110101111011100101110 .
b10010111010110101111011100101110 ,
b10 %
b10 +
b11000111101110011010000110001111 $
b11000111101110011010000110001111 *
b11001111101000010101010110011111 #
b11001111101000010101010110011111 )
b100000100100000001010110010000001000010 &
b10 /
b100000100100000001010110010000001000010 0
#420000
b10100100001100101001111101001000 -
b10100100001000001000100101001000 !
b10100100001000001000100101001000 .
b10100000101000000100100101000001 ,
b100 %
b100 +
b1011011110011010110000010110111 $
b1011011110011010110000010110111 *
b11111100011011011010100111111000 #
b11111100011011011010100111111000 )
b10000010010000000100110001000000111111001000010 &
b100 /
b10000010010000000100110001000000111111001000010 0
#430000
b11010001100000100110101110100011 -
b11011111110001100111111110111111 !
b11011111110001100111111110111111 .
b100001010001101100001001000011 ,
1"
b101 %
b101 +
b101110011111011001010001011100 $
b101110011111011001010001011100 *
b1001111110001000101011010011111 #
b1001111110001000101011010011111 )
b10000010010000001111100001000000111111001000010 &
b101 /
b10000010010000001111100001000000111111001000010 0
#440000
b111011001000011100100001110110 -
b1101000111011011000100011010001 !
b1101000111011011000100011010001 .
b1101000111011011000100011010010 ,
0"
b110 %
b110 +
b11000100110111100011011110001001 $
b11000100110111100011011110001001 *
b101101110010111100000001011011 #
b101101110010111100000001011011 )
b100000100100000001011010010000001000010 &
b110 /
b100000100100000001011010010000001000010 0
#450000
b10010111110111001100000100101111 -
b1 !
b1 .
b10111100100010101111001101111001 ,
b111 %
b111 +
b1101000001000110011111011010000 $
b1101000001000110011111011010000 *
b100100101011100011001001001001 #
b100100101011100011001001001001 )
b1000001001111000100001000111111001100010011101000110000 &
b111 /
b1000001001111000100001000111111001100010011101000110000 0
#460000
b101000110001111111110001010001 -
b101000110001101100000001010001 !
b101000110001101100000001010001 .
b10010100110001101011110100101000 ,
0"
b0 %
b0 +
b101000110001111111110001010001 $
b101000110001111111110001010001 *
b1101011111111101100000011010111 #
b1101011111111101100000011010111 )
b100000100100000001001100010000001000010 &
b0 /
b100000100100000001001100010000001000010 0
b110 (
#470000
1"
b10000110000111010111111100001100 -
b11001111001111010111111110011110 !
b11001111001111010111111110011110 .
b1010001001111101010111010100010 ,
b1 %
b1 +
b10000110000111010111111100001100 $
b10000110000111010111111100001100 *
b11001011001000010010111110010110 #
b11001011001000010010111110010110 )
b100000100100000011111000010000001000010 &
b1 /
b100000100100000011111000010000001000010 0
#480000
b11100100010101111110110111001000 -
b1000101100001001011110010001010 !
b1000101100001001011110010001010 .
b1000101100001001011110010001010 ,
1"
b10 %
b10 +
b11100100010101111110110111001000 $
b11100100010101111110110111001000 *
b1100001001011001100111011000010 #
b1100001001011001100111011000010 )
b100000100100000001010110010000001000010 &
b10 /
b100000100100000001010110010000001000010 0
#490000
0"
b1100001000011010001001011000010 -
b100001000000000001001001000010 !
b100001000000000001001001000010 .
b10011100100011110110110100111010 ,
b100 %
b100 +
b10011110111100101110110100111101 $
b10011110111100101110110100111101 *
b111011100000100101101001110111 #
b111011100000100101101001110111 )
b10000010010000000100110001000000111111001000010 &
b100 /
b10000010010000000100110001000000111111001000010 0
#500000
1"
b11000000111110101111111110000001 -
b11001001111111101111111110010011 !
b11001001111111101111111110010011 .
b1001010000001111101101010010100 ,
b101 %
b101 +
b111111000001010000000001111110 $
b111111000001010000000001111110 *
b10001001000011001101101100010010 #
b10001001000011001101101100010010 )
b10000010010000001111100001000000111111001000010 &
b101 /
b10000010010000001111100001000000111111001000010 0
#510000
b1100011001001100001100011000110 -
b11010000010111001101000110011 !
b11010000010111001101000110011 .
b11010000010111001101000110100 ,
b110 %
b110 +
b10011100110110011110011100111001 $
b10011100110110011110011100111001 *
b10110110111001011000000101101101 #
b10110110111001011000000101101101 )
b100000100100000001011010010000001000010 &
b110 /
b100000100100000001011010010000001000010 0
#520000
b10010110000101000000100100101100 -
b0 !
b0 .
b100101111001101001100001001100 ,
1"
b111 %
b111 +
b1101001111010111111011011010011 $
b1101001111010111111011011010011 *
b10001111110100101000111100011111 #
b10001111110100101000111100011111 )
b1000001001111000100001000111111001100010011101000110000 &
b111 /
b1000001001111000100001000111111001100010011101000110000 0
#530000
0"
b111100000101001000100001111000 -
b100000000100000000000 !
b100000000100000000000 .
b11111110111011011011011111111101 ,
b0 %
b0 +
b111100000101001000100001111000 $
b111100000101001000100001111000 *
b11000010110110010010111110000101 #
b11000010110110010010111110000101 )
b100000100100000001001100010000001000010 &
b0 /
b100000100100000001001100010000001000010 0
b111 (
#540000
1"
b10100100100010110100101101001001 -
b10101101110110110101101101011011 !
b10101101110110110101101101011011 .
b1010010011001011010010010100100 ,
b1 %
b1 +
b10100100100010110100101101001001 $
b10100100100010110100101101001001 *
b10101101110110100101100101011011 #
b10101101110110100101100101011011 )
b100000100100000011111000010000001000010 &
b1 /
b100000100100000011111000010000001000010 0
#550000
b10010101000011001010111100101010 -
b10110100111111110101110101101001 !
b10110100111111110101110101101001 .
b10110100111111110101110101101001 ,
0"
b10 %
b10 +
b10010101000011001010111100101010 $
b10010101000011001010111100101010 *
b11111111100101010111000111111 #
b11111111100101010111000111111 )
b100000100100000001010110010000001000010 &
b10 /
b100000100100000001010110010000001000010 0
#560000
b10111100110000001100011101111001 -
b10101100000000000100001101011000 !
b10101100000000000100001101011000 .
b1101000110101100010101011010010 ,
1"
b100 %
b100 +
b1000011001111110011100010000110 $
b1000011001111110011100010000110 *
b10101100000101010110001101011000 #
b10101100000101010110001101011000 )
b10000010010000000100110001000000111111001000010 &
b100 /
b10000010010000000100110001000000111111001000010 0
#570000
0"
b10110001110100000000110101100011 -
b11110111110110100000110111101111 !
b11110111110110100000110111101111 .
b11111000111010100001100111110010 ,
b101 %
b101 +
b1001110001011111111001010011100 $
b1001110001011111111001010011100 *
b1000111000110100000110010001110 #
b1000111000110100000110010001110 )
b10000010010000001111100001000000111111001000010 &
b101 /
b10000010010000001111100001000000111111001000010 0
#580000
b11101100100000100100001111011001 -
b11101001101101111101110111010011 !
b11101001101101111101110111010011 .
b11101001101101111101110111010100 ,
1"
b110 %
b110 +
b10011011111011011110000100110 $
b10011011111011011110000100110 *
b11111101001101011001100111111010 #
b11111101001101011001100111111010 )
b100000100100000001011010010000001000010 &
b110 /
b100000100100000001011010010000001000010 0
#590000
b10101110011101000100101101011100 -
b0 !
b0 .
b1101000000010100110001011010000 ,
b111 %
b111 +
b1010001100010111011010010100011 $
b1010001100010111011010010100011 *
b10111001100101100001011101110011 #
b10111001100101100001011101110011 )
b1000001001111000100001000111111001100010011101000110000 &
b111 /
b1000001001111000100001000111111001100010011101000110000 0
#600000
b1011001110100101001001010110011 -
b10001100100001000000000100011 !
b10001100100001000000000100011 .
b1110001011011000011101011100010 ,
0"
b0 %
b0 +
b1011001110100101001001010110011 $
b1011001110100101001001010110011 *
b10111100110011010100000101111 #
b10111100110011010100000101111 )
b100000100100000001001100010000001000010 &
b0 /
b100000100100000001001100010000001000010 0
b1000 (
#610000
b10100010001010010000110101000100 -
b10101111111110010101111101011111 !
b10101111111110010101111101011111 .
b11010010000000010110001110100011 ,
b1 %
b1 +
b10100010001010010000110101000100 $
b10100010001010010000110101000100 *
b101111110110000101011001011111 #
b101111110110000101011001011111 )
b100000100100000011111000010000001000010 &
b1 /
b100000100100000011111000010000001000010 0
#620000
b1100101100110110011011011001011 -
b1100001100101000011010011000010 !
b1100001100101000011010011000010 .
b1100001100101000011010011000010 ,
1"
b10 %
b10 +
b1100101100110110011011011001011 $
b1100101100110110011011011001011 *
b11111011111110001111110111110111 #
b11111011111110001111110111110111 )
b100000100100000001010110010000001000010 &
b10 /
b100000100100000001010110010000001000010 0
#630000
b1010010110101110010010010100101 -
b1010010000000010000000010100100 !
b1010010000000010000000010100100 .
b11000101111000000011111110001100 ,
0"
b100 %
b100 +
b10101101001010001101101101011010 $
b10101101001010001101101101011010 *
b1110011000010010001101011100110 #
b1110011000010010001101011100110 )
b10000010010000000100110001000000111111001000010 &
b100 /
b10000010010000000100110001000000111111001000010 0
#640000
1"
b10001001011111010001110100010010 -
b10011101111111111101110100111011 !
b10011101111111111101110100111011 .
b11110010011001101111000111100 ,
b101 %
b101 +
b1110110100000101110001011101101 $
b1110110100000101110001011101101 *
b10010100110011111100000100101001 #
b10010100110011111100000100101001 )
b10000010010000001111100001000000111111001000010 &
b101 /
b10000010010000001111100001000000111111001000010 0
#650000
b11001101011000000100100110011010 -
b111010101100111011011001110100 !
b111010101100111011011001110100 .
b111010101100111011011001110101 ,
1"
b110 %
b110 +
b110010100111111011011001100101 $
b110010100111111011011001100101 *
b1101101010100110110110011011010 #
b1101101010100110110110011011010 )
b100000100100000001011010010000001000010 &
b110 /
b100000100100000001011010010000001000010 0
#660000
0"
b10010000010000010110101100100000 -
b1 !
b1 .
b11101010110011000100110111010110 ,
b111 %
b111 +
b1101111101111101001010011011111 $
b1101111101111101001010011011111 *
b1011010100010101110001010110101 #
b1011010100010101110001010110101 )
b1000001001111000100001000111111001100010011101000110000 &
b111 /
b1000001001111000100001000111111001100010011101000110000 0
#670000
b10100010001100011111111101000100 -
b10100000001100010001100101000000 !
b10100000001100010001100101000000 .
b1011111001000110001100010111101 ,
1"
b0 %
b0 +
b10100010001100011111111101000100 $
b10100010001100011111111101000100 *
b10111100111100010001100101111001 #
b10111100111100010001100101111001 )
b100000100100000001001100010000001000010 &
b0 /
b100000100100000001001100010000001000010 0
b1001 (
#680000
0"
b10010101000010010000101100101010 -
b11111101011111010000111111111010 !
b11111101011111010000111111111010 .
b11111101011111010001011111111010 ,
b1 %
b1 +
b10010101000010010000101100101010 $
b10010101000010010000101100101010 *
b1101000011101000000110011010000 #
b1101000011101000000110011010000 )
b100000100100000011111000010000001000010 &
b1 /
b100000100100000011111000010000001000010 0
#690000
b10000111011011111100111100001110 -
b1011101011001100111110010111001 !
b1011101011001100111110010111001 .
b1011101011001100111110010111001 ,
1"
b10 %
b10 +
b10000111011011111100111100001110 $
b10000111011011111100111100001110 *
b11010101111101101010110110101011 #
b11010101111101101010110110101011 )
b100000100100000001010110010000001000010 &
b10 /
b100000100100000001010110010000001000010 0
#700000
b10110010101000010100001101100101 -
b10100010000000010000000101000100 !
b10100010000000010000000101000100 .
b10100000111111101111000101000010 ,
b100 %
b100 +
b1001101010111101011110010011010 $
b1001101010111101011110010011010 *
b11101110010111011010110111011100 #
b11101110010111011010110111011100 )
b10000010010000000100110001000000111111001000010 &
b100 /
b10000010010000000100110001000000111111001000010 0
#710000
b10011110000011101111110100111100 -
b11111110110111111111111111111101 !
b11111110110111111111111111111101 .
b11100111011100111000000111010 ,
b101 %
b101 +
b1100001111100010000001011000011 $
b1100001111100010000001011000011 *
b1111110110111110111001011111101 #
b1111110110111110111001011111101 )
b10000010010000001111100001000000111111001000010 &
b101 /
b10000010010000001111100001000000111111001000010 0
#720000
b1011000100001100001011010110001 -
b11100101010000010000000111 !
b11100101010000010000000111 .
b11100101010000010000001000 ,
b110 %
b110 +
b10100111011110011110100101001110 $
b10100111011110011110100101001110 *
b10101011000011101110110101010110 #
b10101011000011101110110101010110 )
b100000100100000001011010010000001000010 &
b110 /
b100000100100000001011010010000001000010 0
#730000
b11111010110011101100101111110101 -
b0 !
b0 .
b101110101010000100001001011101 ,
1"
b111 %
b111 +
b101001100010011010000001010 $
b101001100010011010000001010 *
b110011110110010111011001100111 #
b110011110110010111011001100111 )
b1000001001111000100001000111111001100010011101000110000 &
b111 /
b1000001001111000100001000111111001100010011101000110000 0
#740000
0"
b11100000011101000101000111000 -
b11000000011101000100000110000 !
b11000000011101000100000110000 .
b11110111011111100100001111101110 ,
b0 %
b0 +
b11100000011101000101000111000 $
b11100000011101000101000111000 *
b11011011011011111011100110110110 #
b11011011011011111011100110110110 )
b100000100100000001001100010000001000010 &
b0 /
b100000100100000001001100010000001000010 0
b1010 (
#750000
1"
b1011100001010111100010010111000 -
b11111100111110111100011111111001 !
b11111100111110111100011111111001 .
b11000111111010100110000110001 ,
b1 %
b1 +
b1011100001010111100010010111000 $
b1011100001010111100010010111000 *
b10111100110100011000011101111001 #
b10111100110100011000011101111001 )
b100000100100000011111000010000001000010 &
b1 /
b100000100100000011111000010000001000010 0
#760000
b11001001110001100101110110010011 -
b10010100001110110001110100100111 !
b10010100001110110001110100100111 .
b10010100001110110001110100100111 ,
b10 %
b10 +
b11001001110001100101110110010011 $
b11001001110001100101110110010011 *
b11001010011101001011111110010100 #
b11001010011101001011111110010100 )
b100000100100000001010110010000001000010 &
b10 /
b100000100100000001010110010000001000010 0
