project_01/6_sram_extension/spsram.v
// ==================================================
//	[ VLSISYS Lab. ]
//	* Author		: Daseul Moon (daseul@sm.ac.kr)
//	* Filename		: spsram.v
//	* Date			: 2025-03-19 12:31:08
//	* Description	: 
// ==================================================

module spsram
#(
	parameter BW_DATA = 32,
	parameter BW_ADDR = 4
)
(
	output [BW_DATA-1:0] o_data,
	input  [BW_DATA-1:0] i_data,
	input  [BW_ADDR-1:0] i_addr,
	input				 i_cen,
	input 				 i_wen,
	input		   	     i_oen,
	input				 i_clk
);

// Memory Write
	reg [BW_DATA-1:0] mem[0:2**BW_ADDR-1];
	always @(posedge i_clk) begin
		if(i_cen && i_wen) begin
			mem[i_addr] <= i_data;
		end else begin
			mem[i_addr] <= mem[i_addr];
		end
	end

// Memory Read
`ifdef SPSRAM_ASYNC
	assign o_data = !i_oen ? 'bz : i_cen && !i_wen ? mem[i_addr] : 'bx;
`else 
	reg [BW_DATA-1:0] o_data;
	always @(posedge i_clk) begin
		if(i_oen) begin
			if(i_cen && !i_wen) begin
				o_data <= mem[i_addr];
			end else begin
				o_data <= 'bx;
			end
		end else begin
			o_data <= 'bz;
		end
	end
`endif

endmodule

project_01/6_sram_extension/sram_extended.v
// ==================================================
//	[ VLSISYS Lab. ]
//	* Author		: Daseul Moon (daseul@sm.ac.kr)
//	* Filename		: sram_extended.v
//	* Date			: 2025-03-19 12:40:44
//	* Description	: 
// ==================================================

`include "spsram.v"

module sram_extended
(
	output [63:0] o_data,
	input  [63:0] i_data,
	input  [5:0]  i_addr,
	input 	 	  i_cen,
	input		  i_wen,
	input		  i_oen,
	input 		  i_clk
);

	genvar row,col;
	generate 
		for(row=0; row<4; row=row+1) begin
			for(col=0; col<2; col=col+1) begin
				spsram
				#(
					.BW_DATA (32),
					.BW_ADDR (4)
				)
				u_spsram(
					.o_data (o_data[32*(col+1)-1-:32]        ),
					.i_data (i_data[32*(col+1)-1-:32]		 ),
					.i_addr (i_addr[3:0]				     ),
					.i_cen  (i_addr[5:4] == row ? 1'b1 : 1'b0),
					.i_wen  (i_wen							 ),
					.i_oen  (i_addr[5:4] == row ? 1'b1 : 1'b0),
					.i_clk  (i_clk						     )
				);
			end
		end
	endgenerate

endmodule

project_01/6_sram_extension/sram_extended_tb.v
// ==================================================
//	[ VLSISYS Lab. ]
//	* Author		: Daseul Moon (daseul@sm.ac.kr)
//	* Filename		: sram_extended_tb.v
//	* Date			: 2025-03-19 13:59:53
//	* Description	: 
// ==================================================

// --------------------------------------------------
//	Define Global Variables
// --------------------------------------------------
`define	CLKFREQ		100		// Clock Freq. (Unit: MHz)
`define	SIMCYCLE	`NVEC	// Sim. Cycles
`define BW_DATA		32		// Bitwidth of ~~
`define BW_ADDR		5		// Bitwidth of ~~
`define BW_CTRL		4		// Bitwidth of ~~
`define NVEC		100		// # of Test Vector

// --------------------------------------------------
//	Includes
// --------------------------------------------------
`include	"sram_extended.v"

module sram_extended_tb;
// --------------------------------------------------
//	DUT Signals & Instantiate
// --------------------------------------------------
	wire [63:0] o_data;
	reg  [63:0] i_data;
	reg  [5:0]  i_addr;
	reg 		i_cen;
	reg 		i_wen;
	reg 		i_oen;
	reg	  	    i_clk;

	sram_extended
	u_sram_extended(
		.o_data (o_data),
		.i_data (i_data),
		.i_addr (i_addr),
		.i_cen  (i_cen ),
		.i_wen  (i_wen ),
		.i_oen  (i_oen ),
		.i_clk  (i_clk )
	);

// --------------------------------------------------
// 	Clock
// --------------------------------------------------
	always #(500/`CLKFREQ) i_clk = ~i_clk;

// --------------------------------------------------
// 	Task
// --------------------------------------------------
	reg [8*32-1:0] taskState;
	task init;
		begin
			taskState = "Init";
			i_data    = 0;
			i_addr	  = 0;
			i_cen	  = 0;
			i_wen	  = 0;
			i_oen	  = 0;
			i_clk 	  = 0;
		end
	endtask

	task memWR;
		input [63:0] ti_data;
		input [5:0]  ti_addr;
		begin
			taskState = "memWR";
			i_data	  = ti_data;
			i_addr    = ti_addr;
			i_cen	  = 1;
			i_wen 	  = 1;
			i_oen	  = 0;
			#(1000/`CLKFREQ);
		end
	endtask

	task memRD;
		input [5:0] ti_addr;
		begin
			taskState = "memRD";
			i_addr    = ti_addr;
			i_cen     = 1;
			i_wen     = 0;
			i_oen     = 1;
			#(1000/`CLKFREQ);
		end
	endtask

// --------------------------------------------------
//	Test Stimulus
// --------------------------------------------------
	integer		i, j;
	initial begin
		init();
		#(4*1000/`CLKFREQ);

		for (i=0; i<2**6; i++) begin
			memWR(i, i);
		end

		for(i=0; i<2**6; i++) begin
			memRD(i);
		end
		#(1000/`CLKFREQ);
		$finish;
	end

// --------------------------------------------------
//	Dump VCD
// --------------------------------------------------
	reg	[8*32-1:0]	vcd_file;
	initial begin
		if ($value$plusargs("vcd_file=%s", vcd_file)) begin
			$dumpfile(vcd_file);
			$dumpvars;
		end else begin
			$dumpfile("sram_extended_tb.vcd");
			$dumpvars;
		end
	end

endmodule

project_01/6_sram_extension/vcd/sram_extended.vcd
$date
	Wed Mar 19 12:50:32 2025
$end
$version
	Icarus Verilog
$end
$timescale
	1ps
$end
$scope module sram_extended_tb $end
$var wire 64 ! o_data [63:0] $end
$var reg 6 " i_addr [5:0] $end
$var reg 1 # i_cen $end
$var reg 1 $ i_clk $end
$var reg 64 % i_data [63:0] $end
$var reg 1 & i_oen $end
$var reg 1 ' i_wen $end
$var reg 256 ( taskState [255:0] $end
$var reg 256 ) vcd_file [255:0] $end
$var integer 32 * i [31:0] $end
$scope module u_sram_extended $end
$var wire 6 + i_addr [5:0] $end
$var wire 1 # i_cen $end
$var wire 1 $ i_clk $end
$var wire 64 , i_data [63:0] $end
$var wire 1 & i_oen $end
$var wire 1 ' i_wen $end
$var wire 64 - o_data [63:0] $end
$scope begin genblk1[0] $end
$scope begin genblk2[0] $end
$scope module u_spsram $end
$var wire 4 . i_addr [3:0] $end
$var wire 1 / i_cen $end
$var wire 1 $ i_clk $end
$var wire 32 0 i_data [31:0] $end
$var wire 1 1 i_oen $end
$var wire 1 ' i_wen $end
$var reg 32 2 o_data [31:0] $end
$upscope $end
$upscope $end
$scope begin genblk2[1] $end
$scope module u_spsram $end
$var wire 4 3 i_addr [3:0] $end
$var wire 1 4 i_cen $end
$var wire 1 $ i_clk $end
$var wire 32 5 i_data [31:0] $end
$var wire 1 6 i_oen $end
$var wire 1 ' i_wen $end
$var reg 32 7 o_data [31:0] $end
$upscope $end
$upscope $end
$upscope $end
$scope begin genblk1[1] $end
$scope begin genblk2[0] $end
$scope module u_spsram $end
$var wire 4 8 i_addr [3:0] $end
$var wire 1 9 i_cen $end
$var wire 1 $ i_clk $end
$var wire 32 : i_data [31:0] $end
$var wire 1 ; i_oen $end
$var wire 1 ' i_wen $end
$var reg 32 < o_data [31:0] $end
$upscope $end
$upscope $end
$scope begin genblk2[1] $end
$scope module u_spsram $end
$var wire 4 = i_addr [3:0] $end
$var wire 1 > i_cen $end
$var wire 1 $ i_clk $end
$var wire 32 ? i_data [31:0] $end
$var wire 1 @ i_oen $end
$var wire 1 ' i_wen $end
$var reg 32 A o_data [31:0] $end
$upscope $end
$upscope $end
$upscope $end
$scope begin genblk1[2] $end
$scope begin genblk2[0] $end
$scope module u_spsram $end
$var wire 4 B i_addr [3:0] $end
$var wire 1 C i_cen $end
$var wire 1 $ i_clk $end
$var wire 32 D i_data [31:0] $end
$var wire 1 E i_oen $end
$var wire 1 ' i_wen $end
$var reg 32 F o_data [31:0] $end
$upscope $end
$upscope $end
$scope begin genblk2[1] $end
$scope module u_spsram $end
$var wire 4 G i_addr [3:0] $end
$var wire 1 H i_cen $end
$var wire 1 $ i_clk $end
$var wire 32 I i_data [31:0] $end
$var wire 1 J i_oen $end
$var wire 1 ' i_wen $end
$var reg 32 K o_data [31:0] $end
$upscope $end
$upscope $end
$upscope $end
$scope begin genblk1[3] $end
$scope begin genblk2[0] $end
$scope module u_spsram $end
$var wire 4 L i_addr [3:0] $end
$var wire 1 M i_cen $end
$var wire 1 $ i_clk $end
$var wire 32 N i_data [31:0] $end
$var wire 1 O i_oen $end
$var wire 1 ' i_wen $end
$var reg 32 P o_data [31:0] $end
$upscope $end
$upscope $end
$scope begin genblk2[1] $end
$scope module u_spsram $end
$var wire 4 Q i_addr [3:0] $end
$var wire 1 R i_cen $end
$var wire 1 $ i_clk $end
$var wire 32 S i_data [31:0] $end
$var wire 1 T i_oen $end
$var wire 1 ' i_wen $end
$var reg 32 U o_data [31:0] $end
$upscope $end
$upscope $end
$upscope $end
$upscope $end
$scope task init $end
$upscope $end
$scope task memRD $end
$var reg 6 V ti_addr [5:0] $end
$upscope $end
$scope task memWR $end
$var reg 6 W ti_addr [5:0] $end
$var reg 64 X ti_data [63:0] $end
$upscope $end
$upscope $end
$enddefinitions $end
#0
$dumpvars
bx X
bx W
bx V
bx U
0T
b0 S
0R
b0 Q
bx P
0O
b0 N
0M
b0 L
bx K
0J
b0 I
0H
b0 G
bx F
0E
b0 D
0C
b0 B
bx A
0@
b0 ?
0>
b0 =
bx <
0;
b0 :
09
b0 8
bx 7
16
b0 5
14
b0 3
bx 2
11
b0 0
1/
b0 .
bx -
b0 ,
b0 +
bx *
b10111000101111011101100110001101100100001011110111001101110010011000010110110101011111011001010111100001110100011001010110111001100100011001010110010000101110011101100110001101100100 )
b1001001011011100110100101110100 (
0'
0&
b0 %
0$
0#
b0 "
bx !
$end
#5000
bz <
bz A
bz F
bz K
bz P
bz U
1$
#10000
0$
#15000
1$
#20000
0$
#25000
1$
#30000
0$
#35000
1$
#40000
0$
1'
1#
b110110101100101011011010101011101010010 (
b0 W
b0 X
b0 *
#45000
1$
#50000
b1 .
b1 3
b1 8
b1 =
b1 B
b1 G
b1 L
b1 Q
b1 0
b1 :
b1 D
b1 N
0$
b1 "
b1 +
b1 %
b1 ,
b1 W
b1 X
b1 *
#55000
1$
#60000
b10 .
b10 3
b10 8
b10 =
b10 B
b10 G
b10 L
b10 Q
b10 0
b10 :
b10 D
b10 N
0$
b10 "
b10 +
b10 %
b10 ,
b10 W
b10 X
b10 *
#65000
1$
#70000
b11 .
b11 3
b11 8
b11 =
b11 B
b11 G
b11 L
b11 Q
b11 0
b11 :
b11 D
b11 N
0$
b11 "
b11 +
b11 %
b11 ,
b11 W
b11 X
b11 *
#75000
1$
#80000
b100 .
b100 3
b100 8
b100 =
b100 B
b100 G
b100 L
b100 Q
b100 0
b100 :
b100 D
b100 N
0$
b100 "
b100 +
b100 %
b100 ,
b100 W
b100 X
b100 *
#85000
1$
#90000
b101 .
b101 3
b101 8
b101 =
b101 B
b101 G
b101 L
b101 Q
b101 0
b101 :
b101 D
b101 N
0$
b101 "
b101 +
b101 %
b101 ,
b101 W
b101 X
b101 *
#95000
1$
#100000
b110 .
b110 3
b110 8
b110 =
b110 B
b110 G
b110 L
b110 Q
b110 0
b110 :
b110 D
b110 N
0$
b110 "
b110 +
b110 %
b110 ,
b110 W
b110 X
b110 *
#105000
1$
#110000
b111 .
b111 3
b111 8
b111 =
b111 B
b111 G
b111 L
b111 Q
b111 0
b111 :
b111 D
b111 N
0$
b111 "
b111 +
b111 %
b111 ,
b111 W
b111 X
b111 *
#115000
1$
#120000
b1000 .
b1000 3
b1000 8
b1000 =
b1000 B
b1000 G
b1000 L
b1000 Q
b1000 0
b1000 :
b1000 D
b1000 N
0$
b1000 "
b1000 +
b1000 %
b1000 ,
b1000 W
b1000 X
b1000 *
#125000
1$
#130000
b1001 .
b1001 3
b1001 8
b1001 =
b1001 B
b1001 G
b1001 L
b1001 Q
b1001 0
b1001 :
b1001 D
b1001 N
0$
b1001 "
b1001 +
b1001 %
b1001 ,
b1001 W
b1001 X
b1001 *
#135000
1$
#140000
b1010 .
b1010 3
b1010 8
b1010 =
b1010 B
b1010 G
b1010 L
b1010 Q
b1010 0
b1010 :
b1010 D
b1010 N
0$
b1010 "
b1010 +
b1010 %
b1010 ,
b1010 W
b1010 X
b1010 *
#145000
1$
#150000
b1011 .
b1011 3
b1011 8
b1011 =
b1011 B
b1011 G
b1011 L
b1011 Q
b1011 0
b1011 :
b1011 D
b1011 N
0$
b1011 "
b1011 +
b1011 %
b1011 ,
b1011 W
b1011 X
b1011 *
#155000
1$
#160000
b1100 .
b1100 3
b1100 8
b1100 =
b1100 B
b1100 G
b1100 L
b1100 Q
b1100 0
b1100 :
b1100 D
b1100 N
0$
b1100 "
b1100 +
b1100 %
b1100 ,
b1100 W
b1100 X
b1100 *
#165000
1$
#170000
b1101 .
b1101 3
b1101 8
b1101 =
b1101 B
b1101 G
b1101 L
b1101 Q
b1101 0
b1101 :
b1101 D
b1101 N
0$
b1101 "
b1101 +
b1101 %
b1101 ,
b1101 W
b1101 X
b1101 *
#175000
1$
#180000
b1110 .
b1110 3
b1110 8
b1110 =
b1110 B
b1110 G
b1110 L
b1110 Q
b1110 0
b1110 :
b1110 D
b1110 N
0$
b1110 "
b1110 +
b1110 %
b1110 ,
b1110 W
b1110 X
b1110 *
#185000
1$
#190000
b1111 .
b1111 3
b1111 8
b1111 =
b1111 B
b1111 G
b1111 L
b1111 Q
b1111 0
b1111 :
b1111 D
b1111 N
0$
b1111 "
b1111 +
b1111 %
b1111 ,
b1111 W
b1111 X
b1111 *
#195000
1$
#200000
0/
01
04
06
19
1;
1>
1@
b0 .
b0 3
b0 8
b0 =
b0 B
b0 G
b0 L
b0 Q
b10000 0
b10000 :
b10000 D
b10000 N
0$
b10000 "
b10000 +
b10000 %
b10000 ,
b10000 W
b10000 X
b10000 *
#205000
bz 2
bz 7
bx <
bx A
1$
#210000
b1 .
b1 3
b1 8
b1 =
b1 B
b1 G
b1 L
b1 Q
b10001 0
b10001 :
b10001 D
b10001 N
0$
b10001 "
b10001 +
b10001 %
b10001 ,
b10001 W
b10001 X
b10001 *
#215000
1$
#220000
b10 .
b10 3
b10 8
b10 =
b10 B
b10 G
b10 L
b10 Q
b10010 0
b10010 :
b10010 D
b10010 N
0$
b10010 "
b10010 +
b10010 %
b10010 ,
b10010 W
b10010 X
b10010 *
#225000
1$
#230000
b11 .
b11 3
b11 8
b11 =
b11 B
b11 G
b11 L
b11 Q
b10011 0
b10011 :
b10011 D
b10011 N
0$
b10011 "
b10011 +
b10011 %
b10011 ,
b10011 W
b10011 X
b10011 *
#235000
1$
#240000
b100 .
b100 3
b100 8
b100 =
b100 B
b100 G
b100 L
b100 Q
b10100 0
b10100 :
b10100 D
b10100 N
0$
b10100 "
b10100 +
b10100 %
b10100 ,
b10100 W
b10100 X
b10100 *
#245000
1$
#250000
b101 .
b101 3
b101 8
b101 =
b101 B
b101 G
b101 L
b101 Q
b10101 0
b10101 :
b10101 D
b10101 N
0$
b10101 "
b10101 +
b10101 %
b10101 ,
b10101 W
b10101 X
b10101 *
#255000
1$
#260000
b110 .
b110 3
b110 8
b110 =
b110 B
b110 G
b110 L
b110 Q
b10110 0
b10110 :
b10110 D
b10110 N
0$
b10110 "
b10110 +
b10110 %
b10110 ,
b10110 W
b10110 X
b10110 *
#265000
1$
#270000
b111 .
b111 3
b111 8
b111 =
b111 B
b111 G
b111 L
b111 Q
b10111 0
b10111 :
b10111 D
b10111 N
0$
b10111 "
b10111 +
b10111 %
b10111 ,
b10111 W
b10111 X
b10111 *
#275000
1$
#280000
b1000 .
b1000 3
b1000 8
b1000 =
b1000 B
b1000 G
b1000 L
b1000 Q
b11000 0
b11000 :
b11000 D
b11000 N
0$
b11000 "
b11000 +
b11000 %
b11000 ,
b11000 W
b11000 X
b11000 *
#285000
1$
#290000
b1001 .
b1001 3
b1001 8
b1001 =
b1001 B
b1001 G
b1001 L
b1001 Q
b11001 0
b11001 :
b11001 D
b11001 N
0$
b11001 "
b11001 +
b11001 %
b11001 ,
b11001 W
b11001 X
b11001 *
#295000
1$
#300000
b1010 .
b1010 3
b1010 8
b1010 =
b1010 B
b1010 G
b1010 L
b1010 Q
b11010 0
b11010 :
b11010 D
b11010 N
0$
b11010 "
b11010 +
b11010 %
b11010 ,
b11010 W
b11010 X
b11010 *
#305000
1$
#310000
b1011 .
b1011 3
b1011 8
b1011 =
b1011 B
b1011 G
b1011 L
b1011 Q
b11011 0
b11011 :
b11011 D
b11011 N
0$
b11011 "
b11011 +
b11011 %
b11011 ,
b11011 W
b11011 X
b11011 *
#315000
1$
#320000
b1100 .
b1100 3
b1100 8
b1100 =
b1100 B
b1100 G
b1100 L
b1100 Q
b11100 0
b11100 :
b11100 D
b11100 N
0$
b11100 "
b11100 +
b11100 %
b11100 ,
b11100 W
b11100 X
b11100 *
#325000
1$
#330000
b1101 .
b1101 3
b1101 8
b1101 =
b1101 B
b1101 G
b1101 L
b1101 Q
b11101 0
b11101 :
b11101 D
b11101 N
0$
b11101 "
b11101 +
b11101 %
b11101 ,
b11101 W
b11101 X
b11101 *
#335000
1$
#340000
b1110 .
b1110 3
b1110 8
b1110 =
b1110 B
b1110 G
b1110 L
b1110 Q
b11110 0
b11110 :
b11110 D
b11110 N
0$
b11110 "
b11110 +
b11110 %
b11110 ,
b11110 W
b11110 X
b11110 *
#345000
1$
#350000
b1111 .
b1111 3
b1111 8
b1111 =
b1111 B
b1111 G
b1111 L
b1111 Q
b11111 0
b11111 :
b11111 D
b11111 N
0$
b11111 "
b11111 +
b11111 %
b11111 ,
b11111 W
b11111 X
b11111 *
#355000
1$
#360000
09
0;
0>
0@
1C
1E
1H
1J
b0 .
b0 3
b0 8
b0 =
b0 B
b0 G
b0 L
b0 Q
b100000 0
b100000 :
b100000 D
b100000 N
0$
b100000 "
b100000 +
b100000 %
b100000 ,
b100000 W
b100000 X
b100000 *
#365000
bz <
bz A
bx F
bx K
1$
#370000
b1 .
b1 3
b1 8
b1 =
b1 B
b1 G
b1 L
b1 Q
b100001 0
b100001 :
b100001 D
b100001 N
0$
b100001 "
b100001 +
b100001 %
b100001 ,
b100001 W
b100001 X
b100001 *
#375000
1$
#380000
b10 .
b10 3
b10 8
b10 =
b10 B
b10 G
b10 L
b10 Q
b100010 0
b100010 :
b100010 D
b100010 N
0$
b100010 "
b100010 +
b100010 %
b100010 ,
b100010 W
b100010 X
b100010 *
#385000
1$
#390000
b11 .
b11 3
b11 8
b11 =
b11 B
b11 G
b11 L
b11 Q
b100011 0
b100011 :
b100011 D
b100011 N
0$
b100011 "
b100011 +
b100011 %
b100011 ,
b100011 W
b100011 X
b100011 *
#395000
1$
#400000
b100 .
b100 3
b100 8
b100 =
b100 B
b100 G
b100 L
b100 Q
b100100 0
b100100 :
b100100 D
b100100 N
0$
b100100 "
b100100 +
b100100 %
b100100 ,
b100100 W
b100100 X
b100100 *
#405000
1$
#410000
b101 .
b101 3
b101 8
b101 =
b101 B
b101 G
b101 L
b101 Q
b100101 0
b100101 :
b100101 D
b100101 N
0$
b100101 "
b100101 +
b100101 %
b100101 ,
b100101 W
b100101 X
b100101 *
#415000
1$
#420000
b110 .
b110 3
b110 8
b110 =
b110 B
b110 G
b110 L
b110 Q
b100110 0
b100110 :
b100110 D
b100110 N
0$
b100110 "
b100110 +
b100110 %
b100110 ,
b100110 W
b100110 X
b100110 *
#425000
1$
#430000
b111 .
b111 3
b111 8
b111 =
b111 B
b111 G
b111 L
b111 Q
b100111 0
b100111 :
b100111 D
b100111 N
0$
b100111 "
b100111 +
b100111 %
b100111 ,
b100111 W
b100111 X
b100111 *
#435000
1$
#440000
b1000 .
b1000 3
b1000 8
b1000 =
b1000 B
b1000 G
b1000 L
b1000 Q
b101000 0
b101000 :
b101000 D
b101000 N
0$
b101000 "
b101000 +
b101000 %
b101000 ,
b101000 W
b101000 X
b101000 *
#445000
1$
#450000
b1001 .
b1001 3
b1001 8
b1001 =
b1001 B
b1001 G
b1001 L
b1001 Q
b101001 0
b101001 :
b101001 D
b101001 N
0$
b101001 "
b101001 +
b101001 %
b101001 ,
b101001 W
b101001 X
b101001 *
#455000
1$
#460000
b1010 .
b1010 3
b1010 8
b1010 =
b1010 B
b1010 G
b1010 L
b1010 Q
b101010 0
b101010 :
b101010 D
b101010 N
0$
b101010 "
b101010 +
b101010 %
b101010 ,
b101010 W
b101010 X
b101010 *
#465000
1$
#470000
b1011 .
b1011 3
b1011 8
b1011 =
b1011 B
b1011 G
b1011 L
b1011 Q
b101011 0
b101011 :
b101011 D
b101011 N
0$
b101011 "
b101011 +
b101011 %
b101011 ,
b101011 W
b101011 X
b101011 *
#475000
1$
#480000
b1100 .
b1100 3
b1100 8
b1100 =
b1100 B
b1100 G
b1100 L
b1100 Q
b101100 0
b101100 :
b101100 D
b101100 N
0$
b101100 "
b101100 +
b101100 %
b101100 ,
b101100 W
b101100 X
b101100 *
#485000
1$
#490000
b1101 .
b1101 3
b1101 8
b1101 =
b1101 B
b1101 G
b1101 L
b1101 Q
b101101 0
b101101 :
b101101 D
b101101 N
0$
b101101 "
b101101 +
b101101 %
b101101 ,
b101101 W
b101101 X
b101101 *
#495000
1$
#500000
b1110 .
b1110 3
b1110 8
b1110 =
b1110 B
b1110 G
b1110 L
b1110 Q
b101110 0
b101110 :
b101110 D
b101110 N
0$
b101110 "
b101110 +
b101110 %
b101110 ,
b101110 W
b101110 X
b101110 *
#505000
1$
#510000
b1111 .
b1111 3
b1111 8
b1111 =
b1111 B
b1111 G
b1111 L
b1111 Q
b101111 0
b101111 :
b101111 D
b101111 N
0$
b101111 "
b101111 +
b101111 %
b101111 ,
b101111 W
b101111 X
b101111 *
#515000
1$
#520000
0C
0E
0H
0J
1M
1O
1R
1T
b0 .
b0 3
b0 8
b0 =
b0 B
b0 G
b0 L
b0 Q
b110000 0
b110000 :
b110000 D
b110000 N
0$
b110000 "
b110000 +
b110000 %
b110000 ,
b110000 W
b110000 X
b110000 *
#525000
bz F
bz K
bx P
bx U
1$
#530000
b1 .
b1 3
b1 8
b1 =
b1 B
b1 G
b1 L
b1 Q
b110001 0
b110001 :
b110001 D
b110001 N
0$
b110001 "
b110001 +
b110001 %
b110001 ,
b110001 W
b110001 X
b110001 *
#535000
1$
#540000
b10 .
b10 3
b10 8
b10 =
b10 B
b10 G
b10 L
b10 Q
b110010 0
b110010 :
b110010 D
b110010 N
0$
b110010 "
b110010 +
b110010 %
b110010 ,
b110010 W
b110010 X
b110010 *
#545000
1$
#550000
b11 .
b11 3
b11 8
b11 =
b11 B
b11 G
b11 L
b11 Q
b110011 0
b110011 :
b110011 D
b110011 N
0$
b110011 "
b110011 +
b110011 %
b110011 ,
b110011 W
b110011 X
b110011 *
#555000
1$
#560000
b100 .
b100 3
b100 8
b100 =
b100 B
b100 G
b100 L
b100 Q
b110100 0
b110100 :
b110100 D
b110100 N
0$
b110100 "
b110100 +
b110100 %
b110100 ,
b110100 W
b110100 X
b110100 *
#565000
1$
#570000
b101 .
b101 3
b101 8
b101 =
b101 B
b101 G
b101 L
b101 Q
b110101 0
b110101 :
b110101 D
b110101 N
0$
b110101 "
b110101 +
b110101 %
b110101 ,
b110101 W
b110101 X
b110101 *
#575000
1$
#580000
b110 .
b110 3
b110 8
b110 =
b110 B
b110 G
b110 L
b110 Q
b110110 0
b110110 :
b110110 D
b110110 N
0$
b110110 "
b110110 +
b110110 %
b110110 ,
b110110 W
b110110 X
b110110 *
#585000
1$
#590000
b111 .
b111 3
b111 8
b111 =
b111 B
b111 G
b111 L
b111 Q
b110111 0
b110111 :
b110111 D
b110111 N
0$
b110111 "
b110111 +
b110111 %
b110111 ,
b110111 W
b110111 X
b110111 *
#595000
1$
#600000
b1000 .
b1000 3
b1000 8
b1000 =
b1000 B
b1000 G
b1000 L
b1000 Q
b111000 0
b111000 :
b111000 D
b111000 N
0$
b111000 "
b111000 +
b111000 %
b111000 ,
b111000 W
b111000 X
b111000 *
#605000
1$
#610000
b1001 .
b1001 3
b1001 8
b1001 =
b1001 B
b1001 G
b1001 L
b1001 Q
b111001 0
b111001 :
b111001 D
b111001 N
0$
b111001 "
b111001 +
b111001 %
b111001 ,
b111001 W
b111001 X
b111001 *
#615000
1$
#620000
b1010 .
b1010 3
b1010 8
b1010 =
b1010 B
b1010 G
b1010 L
b1010 Q
b111010 0
b111010 :
b111010 D
b111010 N
0$
b111010 "
b111010 +
b111010 %
b111010 ,
b111010 W
b111010 X
b111010 *
#625000
1$
#630000
b1011 .
b1011 3
b1011 8
b1011 =
b1011 B
b1011 G
b1011 L
b1011 Q
b111011 0
b111011 :
b111011 D
b111011 N
0$
b111011 "
b111011 +
b111011 %
b111011 ,
b111011 W
b111011 X
b111011 *
#635000
1$
#640000
b1100 .
b1100 3
b1100 8
b1100 =
b1100 B
b1100 G
b1100 L
b1100 Q
b111100 0
b111100 :
b111100 D
b111100 N
0$
b111100 "
b111100 +
b111100 %
b111100 ,
b111100 W
b111100 X
b111100 *
#645000
1$
#650000
b1101 .
b1101 3
b1101 8
b1101 =
b1101 B
b1101 G
b1101 L
b1101 Q
b111101 0
b111101 :
b111101 D
b111101 N
0$
b111101 "
b111101 +
b111101 %
b111101 ,
b111101 W
b111101 X
b111101 *
#655000
1$
#660000
b1110 .
b1110 3
b1110 8
b1110 =
b1110 B
b1110 G
b1110 L
b1110 Q
b111110 0
b111110 :
b111110 D
b111110 N
0$
b111110 "
b111110 +
b111110 %
b111110 ,
b111110 W
b111110 X
b111110 *
#665000
1$
#670000
b1111 .
b1111 3
b1111 8
b1111 =
b1111 B
b1111 G
b1111 L
b1111 Q
b111111 0
b111111 :
b111111 D
b111111 N
0$
b111111 "
b111111 +
b111111 %
b111111 ,
b111111 W
b111111 X
b111111 *
#675000
1$
#680000
1/
11
14
16
0M
0O
0R
0T
b0 .
b0 3
b0 8
b0 =
b0 B
b0 G
b0 L
b0 Q
0$
1&
0'
b0 "
b0 +
b110110101100101011011010101001001000100 (
b0 V
b0 *
#685000
b0 2
b0 7
bz P
b0 !
b0 -
bz U
1$
#690000
b1 .
b1 3
b1 8
b1 =
b1 B
b1 G
b1 L
b1 Q
0$
b1 "
b1 +
b1 V
b1 *
#695000
b1 !
b1 -
b1 2
1$
#700000
b10 .
b10 3
b10 8
b10 =
b10 B
b10 G
b10 L
b10 Q
0$
b10 "
b10 +
b10 V
b10 *
#705000
b10 !
b10 -
b10 2
1$
#710000
b11 .
b11 3
b11 8
b11 =
b11 B
b11 G
b11 L
b11 Q
0$
b11 "
b11 +
b11 V
b11 *
#715000
b11 !
b11 -
b11 2
1$
#720000
b100 .
b100 3
b100 8
b100 =
b100 B
b100 G
b100 L
b100 Q
0$
b100 "
b100 +
b100 V
b100 *
#725000
b100 !
b100 -
b100 2
1$
#730000
b101 .
b101 3
b101 8
b101 =
b101 B
b101 G
b101 L
b101 Q
0$
b101 "
b101 +
b101 V
b101 *
#735000
b101 !
b101 -
b101 2
1$
#740000
b110 .
b110 3
b110 8
b110 =
b110 B
b110 G
b110 L
b110 Q
0$
b110 "
b110 +
b110 V
b110 *
#745000
b110 !
b110 -
b110 2
1$
#750000
b111 .
b111 3
b111 8
b111 =
b111 B
b111 G
b111 L
b111 Q
0$
b111 "
b111 +
b111 V
b111 *
#755000
b111 !
b111 -
b111 2
1$
#760000
b1000 .
b1000 3
b1000 8
b1000 =
b1000 B
b1000 G
b1000 L
b1000 Q
0$
b1000 "
b1000 +
b1000 V
b1000 *
#765000
b1000 !
b1000 -
b1000 2
1$
#770000
b1001 .
b1001 3
b1001 8
b1001 =
b1001 B
b1001 G
b1001 L
b1001 Q
0$
b1001 "
b1001 +
b1001 V
b1001 *
#775000
b1001 !
b1001 -
b1001 2
1$
#780000
b1010 .
b1010 3
b1010 8
b1010 =
b1010 B
b1010 G
b1010 L
b1010 Q
0$
b1010 "
b1010 +
b1010 V
b1010 *
#785000
b1010 !
b1010 -
b1010 2
1$
#790000
b1011 .
b1011 3
b1011 8
b1011 =
b1011 B
b1011 G
b1011 L
b1011 Q
0$
b1011 "
b1011 +
b1011 V
b1011 *
#795000
b1011 !
b1011 -
b1011 2
1$
#800000
b1100 .
b1100 3
b1100 8
b1100 =
b1100 B
b1100 G
b1100 L
b1100 Q
0$
b1100 "
b1100 +
b1100 V
b1100 *
#805000
b1100 !
b1100 -
b1100 2
1$
#810000
b1101 .
b1101 3
b1101 8
b1101 =
b1101 B
b1101 G
b1101 L
b1101 Q
0$
b1101 "
b1101 +
b1101 V
b1101 *
#815000
b1101 !
b1101 -
b1101 2
1$
#820000
b1110 .
b1110 3
b1110 8
b1110 =
b1110 B
b1110 G
b1110 L
b1110 Q
0$
b1110 "
b1110 +
b1110 V
b1110 *
#825000
b1110 !
b1110 -
b1110 2
1$
#830000
b1111 .
b1111 3
b1111 8
b1111 =
b1111 B
b1111 G
b1111 L
b1111 Q
0$
b1111 "
b1111 +
b1111 V
b1111 *
#835000
b1111 !
b1111 -
b1111 2
1$
#840000
0/
01
04
06
19
1;
1>
1@
b0 .
b0 3
b0 8
b0 =
b0 B
b0 G
b0 L
b0 Q
0$
b10000 "
b10000 +
b10000 V
b10000 *
#845000
bz 2
bz 7
b10000 !
b10000 -
b10000 <
b0 A
1$
#850000
b1 .
b1 3
b1 8
b1 =
b1 B
b1 G
b1 L
b1 Q
0$
b10001 "
b10001 +
b10001 V
b10001 *
#855000
b10001 !
b10001 -
b10001 <
1$
#860000
b10 .
b10 3
b10 8
b10 =
b10 B
b10 G
b10 L
b10 Q
0$
b10010 "
b10010 +
b10010 V
b10010 *
#865000
b10010 !
b10010 -
b10010 <
1$
#870000
b11 .
b11 3
b11 8
b11 =
b11 B
b11 G
b11 L
b11 Q
0$
b10011 "
b10011 +
b10011 V
b10011 *
#875000
b10011 !
b10011 -
b10011 <
1$
#880000
b100 .
b100 3
b100 8
b100 =
b100 B
b100 G
b100 L
b100 Q
0$
b10100 "
b10100 +
b10100 V
b10100 *
#885000
b10100 !
b10100 -
b10100 <
1$
