03_week/06_sram/spsram.v
// ==================================================
//	[ VLSISYS Lab. ]
//	* Author		: Daseul Moon (daseul@sm.ac.kr)
//	* Filename		: spsram.v
//	* Date			: 2025-03-17 13:59:31
//	* Description	: 
// ==================================================

module spsram
#(
	parameter BW_DATA  =  32, // momory bandwidth
	parameter BW_ADDR  =  4   // address bandwidth
)
(
	output	[BW_DATA-1:0] o_data,
	input   [BW_DATA-1:0] i_data,
	input   [BW_ADDR-1:0] i_addr,
	input				  i_cen, // chip enable (active high)
	input 				  i_wen, // write enable (active high)
	input  				  i_oen, // output enable (active high)
	input 				  i_clk
);

	// Memory Write
    reg [BW_DATA-1:0] mem[0:2**BW_ADDR-1];
	always @(posedge i_clk) begin
		if(i_cen && i_wen) begin
			mem[i_addr] <= i_data;
		end else begin
			mem[i_addr] <= mem[i_addr];
		end
	end

	// Memory Read
	`ifdef SPSRAM_ASYNC
		assign o_data = !i_oen ? 'bz :
						i_cen && !i_wen ? mem[i_addr] : 'bx;
	`else
		reg [BW_DATA-1:0] o_data;
		always @(posedge i_clk) begin
			if(i_oen) begin
				if(i_cen && !i_wen) begin
					o_data <= mem[i_addr];
				end else begin
					o_data <= 'bx;
				end
			end else begin
				o_data <= 'bz;
			end
		end
	`endif
endmodule

03_week/06_sram/spsram_doubled.v
// ==================================================
//	[ VLSISYS Lab. ]
//	* Author		: Daseul Moon (daseul@sm.ac.kr)
//	* Filename		: spsram_doubled.v
//	* Date			: 2025-03-17 15:04:52
//	* Description	: 
// ==================================================

`include	"spsram.v"

module spsram_doubled
(
	output [31:0]	o_data,
	input  [31:0]	i_data,
	input  [4:0]    i_addr,
	input 			i_cen,
	input    		i_wen,
	input 			i_oen,
	input  			i_clk
);

	spsram
	#(
		.BW_DATA (32),
		.BW_ADDR (4 )
	)
	u_spsram_0(
		.o_data (o_data     ),
		.i_data (i_data     ),
		.i_addr (i_addr[3:0]),
		.i_cen  (~i_addr[4] ),
		.i_wen  (i_wen      ),
		.i_oen  (~i_addr[4] ),
		.i_clk  (i_clk 		)
	);
	
	spsram
	#(
		.BW_DATA (32),
		.BW_ADDR (4 )
	)
	u_spsram_1(
		.o_data (o_data     ),
		.i_data (i_data		),
		.i_addr (i_addr[3:0]),
		.i_cen  (~i_addr[4] ),
		.i_wen  (i_wen		),
		.i_oen  (~i_addr[4] ),
		.i_clk  (i_clk		)
	);

endmodule

03_week/06_sram/spsram_doubled_tb.v
// ==================================================
//	[ VLSISYS Lab. ]
//	* Author		: Daseul Moon (daseul@sm.ac.kr)
//	* Filename		: spsram_doubled_tb.v
//	* Date			: 2025-03-17 15:26:16
//	* Description	: 
// ==================================================

// --------------------------------------------------
//	Define Global Variables
// --------------------------------------------------
`define	CLKFREQ		100		// Clock Freq. (Unit: MHz)
`define	SIMCYCLE	`NVEC	// Sim. Cycles
`define NVEC		100		// # of Test Vector

// --------------------------------------------------
//	Includes
// --------------------------------------------------
`include	"spsram_doubled.v"

module spsram_doubled_tb;
// --------------------------------------------------
//	DUT Signals & Instantiate
// --------------------------------------------------
	wire [31:0] o_data;
	reg  [31:0] i_data;
	reg  [4:0]  i_addr;
	reg 		i_cen;
	reg 		i_wen;
	reg 		i_oen;
	reg			i_clk;

	spsram_doubled
	u_spsram_doubled(
		.o_data (o_data),
		.i_data (i_data),
		.i_addr (i_addr),
		.i_cen  (i_cen ),
		.i_wen  (i_wen ),
		.i_oen  (i_oen ),
		.i_clk  (i_clk )
	);

// --------------------------------------------------
// 	Clock
// --------------------------------------------------
	always #(500/`CLKFREQ) i_clk = ~ i_clk;

// --------------------------------------------------
// 	Task
// --------------------------------------------------
	reg [8*32-1:0] taskState;
	task init;
		begin
			i_data = 0;
			i_addr = 0;
			i_cen  = 0;
			i_wen  = 0;
			i_oen  = 0;
			i_clk  = 0;
		end
	endtask

	task memWR;
		input [31:0] ti_data;
		input [4:0]  ti_addr;
		begin
			@(negedge i_clk) begin
				i_data = ti_data;
				i_addr = ti_addr;
				i_cen  = 1;
				i_wen  = 1;
				i_oen  = 0;
			end
		end
	endtask

	task memRD;
		input [31:0] ti_addr;
		begin
			@(negedge i_clk) begin
				i_addr = ti_addr;
				i_cen  = 1;
				i_wen  = 0;
				i_oen  = 1;
			end
		end
	endtask

// --------------------------------------------------
//	Test Stimulus
// --------------------------------------------------
	integer		i, j;
	initial begin
		init();
		#(4*1000/`CLKFREQ);
		for (i=0; i<`SIMCYCLE; i++) begin
			memWR(i, i);
		end

		for (i=0; i<`SIMCYCLE; i++) begin
			memRD(i);
		end
		#(1000/`CLKFREQ);
		$finish;
	end

// --------------------------------------------------
//	Dump VCD
// --------------------------------------------------
	reg	[8*32-1:0]	vcd_file;
	initial begin
		if ($value$plusargs("vcd_file=%s", vcd_file)) begin
			$dumpfile(vcd_file);
			$dumpvars;
		end else begin
			$dumpfile("spsram_doubled_tb.vcd");
			$dumpvars;
		end
	end

endmodule

03_week/06_sram/vcd/spsram_doubled.vcd
$date
	Mon Mar 17 15:14:36 2025
$end
$version
	Icarus Verilog
$end
$timescale
	1ps
$end
$scope module spsram_doubled_tb $end
$var wire 32 ! o_data [31:0] $end
$var reg 5 " i_addr [4:0] $end
$var reg 1 # i_cen $end
$var reg 1 $ i_clk $end
$var reg 32 % i_data [31:0] $end
$var reg 1 & i_oen $end
$var reg 1 ' i_wen $end
$var reg 256 ( vcd_file [255:0] $end
$var integer 32 ) i [31:0] $end
$scope module u_spsram_doubled $end
$var wire 5 * i_addr [4:0] $end
$var wire 1 # i_cen $end
$var wire 1 $ i_clk $end
$var wire 32 + i_data [31:0] $end
$var wire 1 & i_oen $end
$var wire 1 ' i_wen $end
$var wire 32 , o_data [31:0] $end
$scope module u_spsram_0 $end
$var wire 4 - i_addr [3:0] $end
$var wire 1 . i_cen $end
$var wire 1 $ i_clk $end
$var wire 32 / i_data [31:0] $end
$var wire 1 0 i_oen $end
$var wire 1 ' i_wen $end
$var reg 32 1 o_data [31:0] $end
$upscope $end
$scope module u_spsram_1 $end
$var wire 4 2 i_addr [3:0] $end
$var wire 1 3 i_cen $end
$var wire 1 $ i_clk $end
$var wire 32 4 i_data [31:0] $end
$var wire 1 5 i_oen $end
$var wire 1 ' i_wen $end
$var reg 32 6 o_data [31:0] $end
$upscope $end
$upscope $end
$scope task init $end
$upscope $end
$scope task memRD $end
$var reg 32 7 ti_addr [31:0] $end
$upscope $end
$scope task memWR $end
$var reg 5 8 ti_addr [4:0] $end
$var reg 32 9 ti_data [31:0] $end
$upscope $end
$upscope $end
$enddefinitions $end
#0
$dumpvars
bx 9
bx 8
bx 7
bx 6
15
b0 4
13
b0 2
bx 1
10
b0 /
1.
b0 -
bx ,
b0 +
b0 *
bx )
b1011100010111101110110011000110110010000101111011100110111000001110011011100100110000101101101010111110110010001101111011101010110001001101100011001010110010000101110011101100110001101100100 (
0'
0&
b0 %
0$
0#
b0 "
bx !
$end
#5000
1$
#10000
0$
#15000
1$
#20000
0$
#25000
1$
#30000
0$
#35000
1$
#40000
1'
1#
0$
b1 8
b1 9
b1 )
#45000
1$
#50000
b1 -
b1 2
b10 8
b10 9
b10 )
b1 "
b1 *
b1 %
b1 +
b1 /
b1 4
0$
#55000
1$
#60000
b10 -
b10 2
b11 8
b11 9
b11 )
b10 "
b10 *
b10 %
b10 +
b10 /
b10 4
0$
#65000
1$
#70000
b11 -
b11 2
b100 8
b100 9
b100 )
b11 "
b11 *
b11 %
b11 +
b11 /
b11 4
0$
#75000
1$
#80000
b100 -
b100 2
b101 8
b101 9
b101 )
b100 "
b100 *
b100 %
b100 +
b100 /
b100 4
0$
#85000
1$
#90000
b101 -
b101 2
b110 8
b110 9
b110 )
b101 "
b101 *
b101 %
b101 +
b101 /
b101 4
0$
#95000
1$
#100000
b110 -
b110 2
b111 8
b111 9
b111 )
b110 "
b110 *
b110 %
b110 +
b110 /
b110 4
0$
#105000
1$
#110000
b111 -
b111 2
b1000 8
b1000 9
b1000 )
b111 "
b111 *
b111 %
b111 +
b111 /
b111 4
0$
#115000
1$
#120000
b1000 -
b1000 2
b1001 8
b1001 9
b1001 )
b1000 "
b1000 *
b1000 %
b1000 +
b1000 /
b1000 4
0$
#125000
1$
#130000
b1001 -
b1001 2
b1010 8
b1010 9
b1010 )
b1001 "
b1001 *
b1001 %
b1001 +
b1001 /
b1001 4
0$
#135000
1$
#140000
b1010 -
b1010 2
b1011 8
b1011 9
b1011 )
b1010 "
b1010 *
b1010 %
b1010 +
b1010 /
b1010 4
0$
#145000
1$
#150000
b1011 -
b1011 2
b1100 8
b1100 9
b1100 )
b1011 "
b1011 *
b1011 %
b1011 +
b1011 /
b1011 4
0$
#155000
1$
#160000
b1100 -
b1100 2
b1101 8
b1101 9
b1101 )
b1100 "
b1100 *
b1100 %
b1100 +
b1100 /
b1100 4
0$
#165000
1$
#170000
b1101 -
b1101 2
b1110 8
b1110 9
b1110 )
b1101 "
b1101 *
b1101 %
b1101 +
b1101 /
b1101 4
0$
#175000
1$
#180000
b1110 -
b1110 2
b1111 8
b1111 9
b1111 )
b1110 "
b1110 *
b1110 %
b1110 +
b1110 /
b1110 4
0$
#185000
1$
#190000
b1111 -
b1111 2
b10000 8
b10000 9
b10000 )
b1111 "
b1111 *
b1111 %
b1111 +
b1111 /
b1111 4
0$
#195000
1$
#200000
0.
00
03
05
b0 -
b0 2
b10001 8
b10001 9
b10001 )
b10000 "
b10000 *
b10000 %
b10000 +
b10000 /
b10000 4
0$
#205000
bz !
bz ,
bz 1
bz 6
1$
#210000
b1 -
b1 2
b10010 8
b10010 9
b10010 )
b10001 "
b10001 *
b10001 %
b10001 +
b10001 /
b10001 4
0$
#215000
1$
#220000
b10 -
b10 2
b10011 8
b10011 9
b10011 )
b10010 "
b10010 *
b10010 %
b10010 +
b10010 /
b10010 4
0$
#225000
1$
#230000
b11 -
b11 2
b10100 8
b10100 9
b10100 )
b10011 "
b10011 *
b10011 %
b10011 +
b10011 /
b10011 4
0$
#235000
1$
#240000
b100 -
b100 2
b10101 8
b10101 9
b10101 )
b10100 "
b10100 *
b10100 %
b10100 +
b10100 /
b10100 4
0$
#245000
1$
#250000
b101 -
b101 2
b10110 8
b10110 9
b10110 )
b10101 "
b10101 *
b10101 %
b10101 +
b10101 /
b10101 4
0$
#255000
1$
#260000
b110 -
b110 2
b10111 8
b10111 9
b10111 )
b10110 "
b10110 *
b10110 %
b10110 +
b10110 /
b10110 4
0$
#265000
1$
#270000
b111 -
b111 2
b11000 8
b11000 9
b11000 )
b10111 "
b10111 *
b10111 %
b10111 +
b10111 /
b10111 4
0$
#275000
1$
#280000
b1000 -
b1000 2
b11001 8
b11001 9
b11001 )
b11000 "
b11000 *
b11000 %
b11000 +
b11000 /
b11000 4
0$
#285000
1$
#290000
b1001 -
b1001 2
b11010 8
b11010 9
b11010 )
b11001 "
b11001 *
b11001 %
b11001 +
b11001 /
b11001 4
0$
#295000
1$
#300000
b1010 -
b1010 2
b11011 8
b11011 9
b11011 )
b11010 "
b11010 *
b11010 %
b11010 +
b11010 /
b11010 4
0$
#305000
1$
#310000
b1011 -
b1011 2
b11100 8
b11100 9
b11100 )
b11011 "
b11011 *
b11011 %
b11011 +
b11011 /
b11011 4
0$
#315000
1$
#320000
b1100 -
b1100 2
b11101 8
b11101 9
b11101 )
b11100 "
b11100 *
b11100 %
b11100 +
b11100 /
b11100 4
0$
#325000
1$
#330000
b1101 -
b1101 2
b11110 8
b11110 9
b11110 )
b11101 "
b11101 *
b11101 %
b11101 +
b11101 /
b11101 4
0$
#335000
1$
#340000
b1110 -
b1110 2
b11111 8
b11111 9
b11111 )
b11110 "
b11110 *
b11110 %
b11110 +
b11110 /
b11110 4
0$
#345000
1$
#350000
b1111 -
b1111 2
b0 8
b100000 9
b100000 )
b11111 "
b11111 *
b11111 %
b11111 +
b11111 /
b11111 4
0$
#355000
1$
#360000
1.
10
13
15
b0 -
b0 2
b1 8
b100001 9
b100001 )
b0 "
b0 *
b100000 %
b100000 +
b100000 /
b100000 4
0$
#365000
bx 1
bx !
bx ,
bx 6
1$
#370000
b1 -
b1 2
b10 8
b100010 9
b100010 )
b1 "
b1 *
b100001 %
b100001 +
b100001 /
b100001 4
0$
#375000
1$
#380000
b10 -
b10 2
b11 8
b100011 9
b100011 )
b10 "
b10 *
b100010 %
b100010 +
b100010 /
b100010 4
0$
#385000
1$
#390000
b11 -
b11 2
b100 8
b100100 9
b100100 )
b11 "
b11 *
b100011 %
b100011 +
b100011 /
b100011 4
0$
#395000
1$
#400000
b100 -
b100 2
b101 8
b100101 9
b100101 )
b100 "
b100 *
b100100 %
b100100 +
b100100 /
b100100 4
0$
#405000
1$
#410000
b101 -
b101 2
b110 8
b100110 9
b100110 )
b101 "
b101 *
b100101 %
b100101 +
b100101 /
b100101 4
0$
#415000
1$
#420000
b110 -
b110 2
b111 8
b100111 9
b100111 )
b110 "
b110 *
b100110 %
b100110 +
b100110 /
b100110 4
0$
#425000
1$
#430000
b111 -
b111 2
b1000 8
b101000 9
b101000 )
b111 "
b111 *
b100111 %
b100111 +
b100111 /
b100111 4
0$
#435000
1$
#440000
b1000 -
b1000 2
b1001 8
b101001 9
b101001 )
b1000 "
b1000 *
b101000 %
b101000 +
b101000 /
b101000 4
0$
#445000
1$
#450000
b1001 -
b1001 2
b1010 8
b101010 9
b101010 )
b1001 "
b1001 *
b101001 %
b101001 +
b101001 /
b101001 4
0$
#455000
1$
#460000
b1010 -
b1010 2
b1011 8
b101011 9
b101011 )
b1010 "
b1010 *
b101010 %
b101010 +
b101010 /
b101010 4
0$
#465000
1$
#470000
b1011 -
b1011 2
b1100 8
b101100 9
b101100 )
b1011 "
b1011 *
b101011 %
b101011 +
b101011 /
b101011 4
0$
#475000
1$
#480000
b1100 -
b1100 2
b1101 8
b101101 9
b101101 )
b1100 "
b1100 *
b101100 %
b101100 +
b101100 /
b101100 4
0$
#485000
1$
#490000
b1101 -
b1101 2
b1110 8
b101110 9
b101110 )
b1101 "
b1101 *
b101101 %
b101101 +
b101101 /
b101101 4
0$
#495000
1$
#500000
b1110 -
b1110 2
b1111 8
b101111 9
b101111 )
b1110 "
b1110 *
b101110 %
b101110 +
b101110 /
b101110 4
0$
#505000
1$
#510000
b1111 -
b1111 2
b10000 8
b110000 9
b110000 )
b1111 "
b1111 *
b101111 %
b101111 +
b101111 /
b101111 4
0$
#515000
1$
#520000
0.
00
03
05
b0 -
b0 2
b10001 8
b110001 9
b110001 )
b10000 "
b10000 *
b110000 %
b110000 +
b110000 /
b110000 4
0$
#525000
bz !
bz ,
bz 1
bz 6
1$
#530000
b1 -
b1 2
b10010 8
b110010 9
b110010 )
b10001 "
b10001 *
b110001 %
b110001 +
b110001 /
b110001 4
0$
#535000
1$
#540000
b10 -
b10 2
b10011 8
b110011 9
b110011 )
b10010 "
b10010 *
b110010 %
b110010 +
b110010 /
b110010 4
0$
#545000
1$
#550000
b11 -
b11 2
b10100 8
b110100 9
b110100 )
b10011 "
b10011 *
b110011 %
b110011 +
b110011 /
b110011 4
0$
#555000
1$
#560000
b100 -
b100 2
b10101 8
b110101 9
b110101 )
b10100 "
b10100 *
b110100 %
b110100 +
b110100 /
b110100 4
0$
#565000
1$
#570000
b101 -
b101 2
b10110 8
b110110 9
b110110 )
b10101 "
b10101 *
b110101 %
b110101 +
b110101 /
b110101 4
0$
#575000
1$
#580000
b110 -
b110 2
b10111 8
b110111 9
b110111 )
b10110 "
b10110 *
b110110 %
b110110 +
b110110 /
b110110 4
0$
#585000
1$
#590000
b111 -
b111 2
b11000 8
b111000 9
b111000 )
b10111 "
b10111 *
b110111 %
b110111 +
b110111 /
b110111 4
0$
#595000
1$
#600000
b1000 -
b1000 2
b11001 8
b111001 9
b111001 )
b11000 "
b11000 *
b111000 %
b111000 +
b111000 /
b111000 4
0$
#605000
1$
#610000
b1001 -
b1001 2
b11010 8
b111010 9
b111010 )
b11001 "
b11001 *
b111001 %
b111001 +
b111001 /
b111001 4
0$
#615000
1$
#620000
b1010 -
b1010 2
b11011 8
b111011 9
b111011 )
b11010 "
b11010 *
b111010 %
b111010 +
b111010 /
b111010 4
0$
#625000
1$
#630000
b1011 -
b1011 2
b11100 8
b111100 9
b111100 )
b11011 "
b11011 *
b111011 %
b111011 +
b111011 /
b111011 4
0$
#635000
1$
#640000
b1100 -
b1100 2
b11101 8
b111101 9
b111101 )
b11100 "
b11100 *
b111100 %
b111100 +
b111100 /
b111100 4
0$
#645000
1$
#650000
b1101 -
b1101 2
b11110 8
b111110 9
b111110 )
b11101 "
b11101 *
b111101 %
b111101 +
b111101 /
b111101 4
0$
#655000
1$
#660000
b1110 -
b1110 2
b11111 8
b111111 9
b111111 )
b11110 "
b11110 *
b111110 %
b111110 +
b111110 /
b111110 4
0$
#665000
1$
#670000
b1111 -
b1111 2
b0 8
b1000000 9
b1000000 )
b11111 "
b11111 *
b111111 %
b111111 +
b111111 /
b111111 4
0$
#675000
1$
#680000
1.
10
13
15
b0 -
b0 2
b1 8
b1000001 9
b1000001 )
b0 "
b0 *
b1000000 %
b1000000 +
b1000000 /
b1000000 4
0$
#685000
bx 1
bx !
bx ,
bx 6
1$
#690000
b1 -
b1 2
b10 8
b1000010 9
b1000010 )
b1 "
b1 *
b1000001 %
b1000001 +
b1000001 /
b1000001 4
0$
#695000
1$
#700000
b10 -
b10 2
b11 8
b1000011 9
b1000011 )
b10 "
b10 *
b1000010 %
b1000010 +
b1000010 /
b1000010 4
0$
#705000
1$
#710000
b11 -
b11 2
b100 8
b1000100 9
b1000100 )
b11 "
b11 *
b1000011 %
b1000011 +
b1000011 /
b1000011 4
0$
#715000
1$
#720000
b100 -
b100 2
b101 8
b1000101 9
b1000101 )
b100 "
b100 *
b1000100 %
b1000100 +
b1000100 /
b1000100 4
0$
#725000
1$
#730000
b101 -
b101 2
b110 8
b1000110 9
b1000110 )
b101 "
b101 *
b1000101 %
b1000101 +
b1000101 /
b1000101 4
0$
#735000
1$
#740000
b110 -
b110 2
b111 8
b1000111 9
b1000111 )
b110 "
b110 *
b1000110 %
b1000110 +
b1000110 /
b1000110 4
0$
#745000
1$
#750000
b111 -
b111 2
b1000 8
b1001000 9
b1001000 )
b111 "
b111 *
b1000111 %
b1000111 +
b1000111 /
b1000111 4
0$
#755000
1$
#760000
b1000 -
b1000 2
b1001 8
b1001001 9
b1001001 )
b1000 "
b1000 *
b1001000 %
b1001000 +
b1001000 /
b1001000 4
0$
#765000
1$
#770000
b1001 -
b1001 2
b1010 8
b1001010 9
b1001010 )
b1001 "
b1001 *
b1001001 %
b1001001 +
b1001001 /
b1001001 4
0$
#775000
1$
#780000
b1010 -
b1010 2
b1011 8
b1001011 9
b1001011 )
b1010 "
b1010 *
b1001010 %
b1001010 +
b1001010 /
b1001010 4
0$
#785000
1$
#790000
b1011 -
b1011 2
b1100 8
b1001100 9
b1001100 )
b1011 "
b1011 *
b1001011 %
b1001011 +
b1001011 /
b1001011 4
0$
#795000
1$
#800000
b1100 -
b1100 2
b1101 8
b1001101 9
b1001101 )
b1100 "
b1100 *
b1001100 %
b1001100 +
b1001100 /
b1001100 4
0$
#805000
1$
#810000
b1101 -
b1101 2
b1110 8
b1001110 9
b1001110 )
b1101 "
b1101 *
b1001101 %
b1001101 +
b1001101 /
b1001101 4
0$
#815000
1$
#820000
b1110 -
b1110 2
b1111 8
b1001111 9
b1001111 )
b1110 "
b1110 *
b1001110 %
b1001110 +
b1001110 /
b1001110 4
0$
#825000
1$
#830000
b1111 -
b1111 2
b10000 8
b1010000 9
b1010000 )
b1111 "
b1111 *
b1001111 %
b1001111 +
b1001111 /
b1001111 4
0$
#835000
1$
#840000
0.
00
03
05
b0 -
b0 2
b10001 8
b1010001 9
b1010001 )
b10000 "
b10000 *
b1010000 %
b1010000 +
b1010000 /
b1010000 4
0$
#845000
bz !
bz ,
bz 1
bz 6
1$
#850000
b1 -
b1 2
b10010 8
b1010010 9
b1010010 )
b10001 "
b10001 *
b1010001 %
b1010001 +
b1010001 /
b1010001 4
0$
#855000
1$
#860000
b10 -
b10 2
b10011 8
b1010011 9
b1010011 )
b10010 "
b10010 *
b1010010 %
b1010010 +
b1010010 /
b1010010 4
0$
#865000
1$
#870000
b11 -
b11 2
b10100 8
b1010100 9
b1010100 )
b10011 "
b10011 *
b1010011 %
b1010011 +
b1010011 /
b1010011 4
0$
#875000
1$
#880000
b100 -
b100 2
b10101 8
b1010101 9
b1010101 )
b10100 "
b10100 *
b1010100 %
b1010100 +
b1010100 /
b1010100 4
0$
#885000
1$
#890000
b101 -
b101 2
b10110 8
b1010110 9
b1010110 )
b10101 "
b10101 *
b1010101 %
b1010101 +
b1010101 /
b1010101 4
0$
#895000
1$
#900000
b110 -
b110 2
b10111 8
b1010111 9
b1010111 )
b10110 "
b10110 *
b1010110 %
b1010110 +
b1010110 /
b1010110 4
0$
#905000
1$
#910000
b111 -
b111 2
b11000 8
b1011000 9
b1011000 )
b10111 "
b10111 *
b1010111 %
b1010111 +
b1010111 /
b1010111 4
0$
#915000
1$
#920000
b1000 -
b1000 2
b11001 8
b1011001 9
b1011001 )
b11000 "
b11000 *
b1011000 %
b1011000 +
b1011000 /
b1011000 4
0$
#925000
1$
#930000
b1001 -
b1001 2
b11010 8
b1011010 9
b1011010 )
b11001 "
b11001 *
b1011001 %
b1011001 +
b1011001 /
b1011001 4
0$
#935000
1$
#940000
b1010 -
b1010 2
b11011 8
b1011011 9
b1011011 )
b11010 "
b11010 *
b1011010 %
b1011010 +
b1011010 /
b1011010 4
0$
#945000
1$
#950000
b1011 -
b1011 2
b11100 8
b1011100 9
b1011100 )
b11011 "
b11011 *
b1011011 %
b1011011 +
b1011011 /
b1011011 4
0$
#955000
1$
#960000
b1100 -
b1100 2
b11101 8
b1011101 9
b1011101 )
b11100 "
b11100 *
b1011100 %
b1011100 +
b1011100 /
b1011100 4
0$
#965000
1$
#970000
b1101 -
b1101 2
b11110 8
b1011110 9
b1011110 )
b11101 "
b11101 *
b1011101 %
b1011101 +
b1011101 /
b1011101 4
0$
#975000
1$
#980000
b1110 -
b1110 2
b11111 8
b1011111 9
b1011111 )
b11110 "
b11110 *
b1011110 %
b1011110 +
b1011110 /
b1011110 4
0$
#985000
1$
#990000
b1111 -
b1111 2
b0 8
b1100000 9
b1100000 )
b11111 "
b11111 *
b1011111 %
b1011111 +
b1011111 /
b1011111 4
0$
#995000
1$
#1000000
1.
10
13
15
b0 -
b0 2
b1 8
b1100001 9
b1100001 )
b0 "
b0 *
b1100000 %
b1100000 +
b1100000 /
b1100000 4
0$
#1005000
bx 1
bx !
bx ,
bx 6
1$
#1010000
b1 -
b1 2
b10 8
b1100010 9
b1100010 )
b1 "
b1 *
b1100001 %
b1100001 +
b1100001 /
b1100001 4
0$
#1015000
1$
#1020000
b10 -
b10 2
b11 8
b1100011 9
b1100011 )
b10 "
b10 *
b1100010 %
b1100010 +
b1100010 /
b1100010 4
0$
#1025000
1$
#1030000
b11 -
b11 2
b0 7
b0 )
b11 "
b11 *
b1100011 %
b1100011 +
b1100011 /
b1100011 4
0$
#1035000
1$
#1040000
b0 -
b0 2
b1 7
b1 )
1&
0'
b0 "
b0 *
0$
#1045000
b1100000 !
b1100000 ,
b1100000 1
b1100000 6
1$
#1050000
b1 -
b1 2
b10 7
b10 )
b1 "
b1 *
0$
#1055000
b1100001 6
b1100001 !
b1100001 ,
b1100001 1
1$
#1060000
b10 -
b10 2
b11 7
b11 )
b10 "
b10 *
0$
#1065000
b1100010 1
b1100010 !
b1100010 ,
b1100010 6
1$
#1070000
b11 -
b11 2
b100 7
b100 )
b11 "
b11 *
0$
#1075000
b1100011 6
b1100011 !
b1100011 ,
b1100011 1
1$
#1080000
b100 -
b100 2
b101 7
b101 )
b100 "
b100 *
0$
#1085000
b1000100 1
b1000100 !
b1000100 ,
b1000100 6
1$
#1090000
b101 -
b101 2
b110 7
b110 )
b101 "
b101 *
0$
#1095000
b1000101 6
b1000101 !
b1000101 ,
b1000101 1
1$
#1100000
b110 -
b110 2
b111 7
b111 )
b110 "
b110 *
0$
#1105000
b1000110 1
b1000110 !
b1000110 ,
b1000110 6
1$
#1110000
b111 -
b111 2
b1000 7
b1000 )
b111 "
b111 *
0$
#1115000
b1000111 6
b1000111 !
b1000111 ,
b1000111 1
1$
#1120000
b1000 -
b1000 2
b1001 7
b1001 )
b1000 "
b1000 *
0$
#1125000
b1001000 1
b1001000 !
b1001000 ,
b1001000 6
1$
#1130000
b1001 -
b1001 2
b1010 7
b1010 )
b1001 "
b1001 *
0$
#1135000
b1001001 6
b1001001 !
b1001001 ,
b1001001 1
1$
#1140000
b1010 -
b1010 2
b1011 7
b1011 )
b1010 "
b1010 *
0$
#1145000
b1001010 1
b1001010 !
b1001010 ,
b1001010 6
1$
#1150000
b1011 -
b1011 2
b1100 7
b1100 )
b1011 "
b1011 *
0$
#1155000
b1001011 6
b1001011 !
b1001011 ,
b1001011 1
1$
#1160000
b1100 -
b1100 2
b1101 7
b1101 )
b1100 "
b1100 *
0$
#1165000
b1001100 1
b1001100 !
b1001100 ,
b1001100 6
1$
#1170000
b1101 -
b1101 2
b1110 7
b1110 )
b1101 "
b1101 *
0$
#1175000
b1001101 6
b1001101 !
b1001101 ,
b1001101 1
1$
#1180000
b1110 -
b1110 2
b1111 7
b1111 )
b1110 "
b1110 *
0$
#1185000
b1001110 1
b1001110 !
b1001110 ,
b1001110 6
1$
#1190000
b1111 -
b1111 2
b10000 7
b10000 )
b1111 "
b1111 *
0$
#1195000
b1001111 6
b1001111 !
b1001111 ,
b1001111 1
1$
#1200000
0.
00
03
05
b0 -
b0 2
b10001 7
b10001 )
b10000 "
b10000 *
0$
#1205000
bz !
bz ,
bz 1
bz 6
1$
#1210000
b1 -
b1 2
b10010 7
b10010 )
b10001 "
b10001 *
0$
#1215000
1$
#1220000
b10 -
b10 2
b10011 7
b10011 )
b10010 "
b10010 *
0$
#1225000
1$
#1230000
b11 -
b11 2
b10100 7
b10100 )
b10011 "
b10011 *
0$
#1235000
1$
#1240000
b100 -
b100 2
b10101 7
b10101 )
b10100 "
b10100 *
0$
#1245000
1$
#1250000
b101 -
b101 2
b10110 7
b10110 )
b10101 "
b10101 *
0$
#1255000
1$
#1260000
b110 -
b110 2
b10111 7
b10111 )
b10110 "
b10110 *
0$
#1265000
1$
#1270000
b111 -
b111 2
b11000 7
b11000 )
b10111 "
b10111 *
0$
#1275000
1$
#1280000
b1000 -
b1000 2
b11001 7
b11001 )
b11000 "
b11000 *
0$
#1285000
1$
#1290000
b1001 -
b1001 2
b11010 7
b11010 )
b11001 "
b11001 *
0$
#1295000
1$
#1300000
b1010 -
b1010 2
b11011 7
b11011 )
b11010 "
b11010 *
0$
#1305000
1$
#1310000
b1011 -
b1011 2
b11100 7
b11100 )
b11011 "
b11011 *
0$
#1315000
1$
#1320000
b1100 -
b1100 2
b11101 7
b11101 )
b11100 "
b11100 *
0$
#1325000
1$
#1330000
b1101 -
b1101 2
b11110 7
b11110 )
b11101 "
b11101 *
0$
#1335000
1$
#1340000
b1110 -
b1110 2
b11111 7
b11111 )
b11110 "
b11110 *
0$
#1345000
1$
#1350000
b1111 -
b1111 2
b100000 7
b100000 )
b11111 "
b11111 *
0$
#1355000
1$
#1360000
1.
10
13
15
b0 -
b0 2
b100001 7
b100001 )
b0 "
b0 *
0$
#1365000
b1100000 1
b1100000 !
b1100000 ,
b1100000 6
1$
#1370000
b1 -
b1 2
b100010 7
b100010 )
b1 "
b1 *
0$
#1375000
b1100001 6
b1100001 !
b1100001 ,
b1100001 1
1$
#1380000
b10 -
b10 2
b100011 7
b100011 )
b10 "
b10 *
0$
#1385000
b1100010 1
b1100010 !
b1100010 ,
b1100010 6
1$
#1390000
b11 -
b11 2
b100100 7
b100100 )
b11 "
b11 *
0$
#1395000
b1100011 6
b1100011 !
b1100011 ,
b1100011 1
1$
#1400000
b100 -
b100 2
b100101 7
b100101 )
b100 "
b100 *
0$
#1405000
b1000100 1
b1000100 !
b1000100 ,
b1000100 6
1$
#1410000
b101 -
b101 2
b100110 7
b100110 )
b101 "
b101 *
0$
#1415000
b1000101 6
b1000101 !
b1000101 ,
b1000101 1
1$
#1420000
b110 -
b110 2
b100111 7
b100111 )
b110 "
b110 *
0$
#1425000
b1000110 1
b1000110 !
b1000110 ,
b1000110 6
1$
#1430000
b111 -
b111 2
b101000 7
b101000 )
b111 "
b111 *
0$
#1435000
b1000111 6
b1000111 !
b1000111 ,
b1000111 1
1$
#1440000
b1000 -
b1000 2
b101001 7
b101001 )
b1000 "
b1000 *
0$
#1445000
b1001000 1
b1001000 !
b1001000 ,
b1001000 6
1$
#1450000
b1001 -
b1001 2
b101010 7
b101010 )
b1001 "
b1001 *
0$
#1455000
b1001001 6
b1001001 !
b1001001 ,
b1001001 1
1$
#1460000
b1010 -
b1010 2
b101011 7
b101011 )
b1010 "
b1010 *
0$
#1465000
b1001010 1
b1001010 !
b1001010 ,
b1001010 6
1$
#1470000
b1011 -
b1011 2
b101100 7
b101100 )
b1011 "
b1011 *
0$
#1475000
b1001011 6
b1001011 !
b1001011 ,
b1001011 1
1$
#1480000
b1100 -
b1100 2
b101101 7
b101101 )
b1100 "
b1100 *
0$
#1485000
b1001100 1
b1001100 !
b1001100 ,
b1001100 6
1$
#1490000
b1101 -
b1101 2
b101110 7
b101110 )
b1101 "
b1101 *
0$
#1495000
b1001101 6
b1001101 !
b1001101 ,
b1001101 1
1$
#1500000
b1110 -
b1110 2
b101111 7
b101111 )
b1110 "
b1110 *
0$
#1505000
b1001110 1
b1001110 !
b1001110 ,
b1001110 6
1$
#1510000
b1111 -
b1111 2
b110000 7
b110000 )
b1111 "
b1111 *
0$
