project_01/1_barrel_shifter/barrel_shifter.v
// ==================================================
//	[ VLSISYS Lab. ]
//	* Author		: Daseul Moon (daseul@sm.ac.kr)
//	* Filename		: barrel_shifter.v
//	* Date			: 2025-03-18 11:56:47
//	* Description	: 
// ==================================================

module barrel_shifter
(
	output [7:0] o_y,
	input  [7:0] i_a,
	input  [2:0] i_k
);

	wire [7:0] pass_or_shift4;
	wire [7:0] pass_or_shift2;

	genvar i;
	generate 
		for (i=0; i<8; i=i+1) begin
			mux2
			u_mux2_0(
				.o_out (pass_or_shift4[i]),
				.i_in0 (i_a[i] 		     ),
				.i_in1 (i_a[(i+4)%8]     ),
				.i_sel (i_k[2]			 )
			);
		end

		for (i=0; i<8; i=i+1) begin
			mux2
			u_mux2_1(
				.o_out (pass_or_shift2[i]	   ),
				.i_in0 (pass_or_shift4[i]	   ),
				.i_in1 (pass_or_shift4[(i+2)%8]),
				.i_sel (i_k[1] 				   )
			);
		end

		for (i=0; i<8; i=i+1) begin
			mux2
			u_mux2_2(
				.o_out (o_y[i]			  	   ),
				.i_in0 (pass_or_shift2[i]	   ),
				.i_in1 (pass_or_shift2[(i+1)%8]),
				.i_sel (i_k[0]				   )
			);
		end
	endgenerate

endmodule

module mux2
(
	output o_out,
	input  i_in0,
	input  i_in1,
	input  i_sel
);

	assign o_out = i_sel ? i_in1 : i_in0;

endmodule

project_01/1_barrel_shifter/barrel_shifter_tb.v
// ==================================================
//	[ VLSISYS Lab. ]
//	* Author		: Daseul Moon (daseul@sm.ac.kr)
//	* Filename		: barrel_shifter_tb.v
//	* Date			: 2025-03-18 12:42:14
//	* Description	: 
// ==================================================

// --------------------------------------------------
//	Define Global Variables
// --------------------------------------------------
`define	CLKFREQ		100		// Clock Freq. (Unit: MHz)
`define	SIMCYCLE	`NVEC	// Sim. Cycles
`define NVEC		100		// # of Test Vector

// --------------------------------------------------
//	Includes
// --------------------------------------------------
`include	"barrel_shifter.v"

module barrel_shifter_tb;
// --------------------------------------------------
//	DUT Signals & Instantiate
// --------------------------------------------------
	wire [7:0] o_y;
	reg  [7:0] i_a;
	reg  [2:0] i_k;

	barrel_shifter
	u_barrel_shifter(
		.o_y (o_y),
		.i_a (i_a),
		.i_k (i_k)
	);

// -------------------------------------------------
// 	Task
// -------------------------------------------------
	task init;
		begin
			i_a = 0;
			i_k = 0;
		end
	endtask

// --------------------------------------------------
//	Test Stimulus
// --------------------------------------------------
	integer		i, j;
	integer  	err;
	reg [7:0]   temp;
	initial begin
		init();
		err = 0;
		#(1000/`CLKFREQ);

		for (i=0; i<`SIMCYCLE; i++) begin
			{i_a, i_k} = $urandom;
			temp = (i_a << (8-i_k)) | (i_a >> i_k);
			#(1000/`CLKFREQ);
			if (o_y != temp) begin
				err++;
			end
		end
		#(1000/`CLKFREQ);
		$finish;
	end

// --------------------------------------------------
//	Dump VCD
// --------------------------------------------------
	reg	[8*32-1:0]	vcd_file;
	initial begin
		if ($value$plusargs("vcd_file=%s", vcd_file)) begin
			$dumpfile(vcd_file);
			$dumpvars;
		end else begin
			$dumpfile("barrel_shifter_tb.vcd");
			$dumpvars;
		end
	end

endmodule

project_01/1_barrel_shifter/vcd/barrel_shifter.vcd
$date
	Tue Mar 18 12:42:14 2025
$end
$version
	Icarus Verilog
$end
$timescale
	1ps
$end
$scope module barrel_shifter_tb $end
$var wire 8 ! o_y [7:0] $end
$var reg 8 " i_a [7:0] $end
$var reg 3 # i_k [2:0] $end
$var reg 8 $ temp [7:0] $end
$var reg 256 % vcd_file [255:0] $end
$var integer 32 & err [31:0] $end
$var integer 32 ' i [31:0] $end
$scope module u_barrel_shifter $end
$var wire 8 ( i_a [7:0] $end
$var wire 3 ) i_k [2:0] $end
$var wire 8 * pass_or_shift4 [7:0] $end
$var wire 8 + pass_or_shift2 [7:0] $end
$var wire 8 , o_y [7:0] $end
$scope begin genblk1[0] $end
$scope module u_mux2_0 $end
$var wire 1 - i_in0 $end
$var wire 1 . i_in1 $end
$var wire 1 / i_sel $end
$var wire 1 0 o_out $end
$upscope $end
$upscope $end
$scope begin genblk1[1] $end
$scope module u_mux2_0 $end
$var wire 1 1 i_in0 $end
$var wire 1 2 i_in1 $end
$var wire 1 3 i_sel $end
$var wire 1 4 o_out $end
$upscope $end
$upscope $end
$scope begin genblk1[2] $end
$scope module u_mux2_0 $end
$var wire 1 5 i_in0 $end
$var wire 1 6 i_in1 $end
$var wire 1 7 i_sel $end
$var wire 1 8 o_out $end
$upscope $end
$upscope $end
$scope begin genblk1[3] $end
$scope module u_mux2_0 $end
$var wire 1 9 i_in0 $end
$var wire 1 : i_in1 $end
$var wire 1 ; i_sel $end
$var wire 1 < o_out $end
$upscope $end
$upscope $end
$scope begin genblk1[4] $end
$scope module u_mux2_0 $end
$var wire 1 = i_in0 $end
$var wire 1 > i_in1 $end
$var wire 1 ? i_sel $end
$var wire 1 @ o_out $end
$upscope $end
$upscope $end
$scope begin genblk1[5] $end
$scope module u_mux2_0 $end
$var wire 1 A i_in0 $end
$var wire 1 B i_in1 $end
$var wire 1 C i_sel $end
$var wire 1 D o_out $end
$upscope $end
$upscope $end
$scope begin genblk1[6] $end
$scope module u_mux2_0 $end
$var wire 1 E i_in0 $end
$var wire 1 F i_in1 $end
$var wire 1 G i_sel $end
$var wire 1 H o_out $end
$upscope $end
$upscope $end
$scope begin genblk1[7] $end
$scope module u_mux2_0 $end
$var wire 1 I i_in0 $end
$var wire 1 J i_in1 $end
$var wire 1 K i_sel $end
$var wire 1 L o_out $end
$upscope $end
$upscope $end
$scope begin genblk2[0] $end
$scope module u_mux2_1 $end
$var wire 1 M i_in0 $end
$var wire 1 N i_in1 $end
$var wire 1 O i_sel $end
$var wire 1 P o_out $end
$upscope $end
$upscope $end
$scope begin genblk2[1] $end
$scope module u_mux2_1 $end
$var wire 1 Q i_in0 $end
$var wire 1 R i_in1 $end
$var wire 1 S i_sel $end
$var wire 1 T o_out $end
$upscope $end
$upscope $end
$scope begin genblk2[2] $end
$scope module u_mux2_1 $end
$var wire 1 U i_in0 $end
$var wire 1 V i_in1 $end
$var wire 1 W i_sel $end
$var wire 1 X o_out $end
$upscope $end
$upscope $end
$scope begin genblk2[3] $end
$scope module u_mux2_1 $end
$var wire 1 Y i_in0 $end
$var wire 1 Z i_in1 $end
$var wire 1 [ i_sel $end
$var wire 1 \ o_out $end
$upscope $end
$upscope $end
$scope begin genblk2[4] $end
$scope module u_mux2_1 $end
$var wire 1 ] i_in0 $end
$var wire 1 ^ i_in1 $end
$var wire 1 _ i_sel $end
$var wire 1 ` o_out $end
$upscope $end
$upscope $end
$scope begin genblk2[5] $end
$scope module u_mux2_1 $end
$var wire 1 a i_in0 $end
$var wire 1 b i_in1 $end
$var wire 1 c i_sel $end
$var wire 1 d o_out $end
$upscope $end
$upscope $end
$scope begin genblk2[6] $end
$scope module u_mux2_1 $end
$var wire 1 e i_in0 $end
$var wire 1 f i_in1 $end
$var wire 1 g i_sel $end
$var wire 1 h o_out $end
$upscope $end
$upscope $end
$scope begin genblk2[7] $end
$scope module u_mux2_1 $end
$var wire 1 i i_in0 $end
$var wire 1 j i_in1 $end
$var wire 1 k i_sel $end
$var wire 1 l o_out $end
$upscope $end
$upscope $end
$scope begin genblk3[0] $end
$scope module u_mux2_2 $end
$var wire 1 m i_in0 $end
$var wire 1 n i_in1 $end
$var wire 1 o i_sel $end
$var wire 1 p o_out $end
$upscope $end
$upscope $end
$scope begin genblk3[1] $end
$scope module u_mux2_2 $end
$var wire 1 q i_in0 $end
$var wire 1 r i_in1 $end
$var wire 1 s i_sel $end
$var wire 1 t o_out $end
$upscope $end
$upscope $end
$scope begin genblk3[2] $end
$scope module u_mux2_2 $end
$var wire 1 u i_in0 $end
$var wire 1 v i_in1 $end
$var wire 1 w i_sel $end
$var wire 1 x o_out $end
$upscope $end
$upscope $end
$scope begin genblk3[3] $end
$scope module u_mux2_2 $end
$var wire 1 y i_in0 $end
$var wire 1 z i_in1 $end
$var wire 1 { i_sel $end
$var wire 1 | o_out $end
$upscope $end
$upscope $end
$scope begin genblk3[4] $end
$scope module u_mux2_2 $end
$var wire 1 } i_in0 $end
$var wire 1 ~ i_in1 $end
$var wire 1 !" i_sel $end
$var wire 1 "" o_out $end
$upscope $end
$upscope $end
$scope begin genblk3[5] $end
$scope module u_mux2_2 $end
$var wire 1 #" i_in0 $end
$var wire 1 $" i_in1 $end
$var wire 1 %" i_sel $end
$var wire 1 &" o_out $end
$upscope $end
$upscope $end
$scope begin genblk3[6] $end
$scope module u_mux2_2 $end
$var wire 1 '" i_in0 $end
$var wire 1 (" i_in1 $end
$var wire 1 )" i_sel $end
$var wire 1 *" o_out $end
$upscope $end
$upscope $end
$scope begin genblk3[7] $end
$scope module u_mux2_2 $end
$var wire 1 +" i_in0 $end
$var wire 1 ," i_in1 $end
$var wire 1 -" i_sel $end
$var wire 1 ." o_out $end
$upscope $end
$upscope $end
$upscope $end
$scope task init $end
$upscope $end
$upscope $end
$enddefinitions $end
#0
$dumpvars
0."
0-"
0,"
0+"
0*"
0)"
0("
0'"
0&"
0%"
0$"
0#"
0""
0!"
0~
0}
0|
0{
0z
0y
0x
0w
0v
0u
0t
0s
0r
0q
0p
0o
0n
0m
0l
0k
0j
0i
0h
0g
0f
0e
0d
0c
0b
0a
0`
0_
0^
0]
0\
0[
0Z
0Y
0X
0W
0V
0U
0T
0S
0R
0Q
0P
0O
0N
0M
0L
0K
0J
0I
0H
0G
0F
0E
0D
0C
0B
0A
0@
0?
0>
0=
0<
0;
0:
09
08
07
06
05
04
03
02
01
00
0/
0.
0-
b0 ,
b0 +
b0 *
b0 )
b0 (
bx '
b0 &
b1011100010111101110110011000110110010000101111011000100110000101110010011100100110010101101100010111110111001101101000011010010110011001110100011001010111001000101110011101100110001101100100 %
bx $
b0 #
b0 "
b0 !
$end
#10000
1t
1|
b1001010 !
b1001010 ,
1*"
1n
1q
1v
1y
1$"
1'"
1T
1\
b1001010 +
1h
1Q
1j
1R
1Y
1^
1e
14
1<
b1001010 *
1H
12
15
1:
1A
1F
1I
1/
13
17
1;
1?
1C
1G
1K
b1001010 $
b10100100 "
b10100100 (
b100 #
b100 )
b0 '
#20000
0n
0q
0v
0y
1z
1}
1("
1+"
0T
0\
1`
b11010000 +
1l
0Q
0j
0R
0Y
1V
1]
1b
1i
04
0<
1@
b11010000 *
1L
0p
0t
0x
1|
1&"
b1101000 !
b1101000 ,
1*"
1.
02
05
16
1=
0A
1E
0F
0/
03
07
0;
0?
0C
0G
0K
1o
1s
1w
1{
1!"
1%"
1)"
1-"
b1101000 $
b11010000 "
b11010000 (
b1 #
b1 )
b1 '
#30000
1."
b11100000 !
b11100000 ,
0|
1m
1,"
0z
0}
1P
b11000001 +
0`
1M
1f
0V
0]
10
b11000001 *
0@
1-
0.
0=
1>
b11100000 $
b11000001 "
b11000001 (
b10 '
#40000
0&"
1p
0$"
0'"
1n
1q
0h
1T
1."
1|
1""
b10011001 !
b10011001 ,
0*"
0M
0f
1N
1U
1R
1Y
1m
1,"
1z
1}
1~
1#"
0("
0+"
00
18
b11001100 *
1<
1P
1`
1d
b110011 +
0l
0-
15
19
0>
1F
1J
1O
1S
1W
1[
1_
1c
1g
1k
b10011001 $
b11001100 "
b11001100 (
b11 #
b11 )
b11 '
#50000
0."
1p
1t
0x
1|
0""
0&"
b1011 !
b1011 ,
0*"
1Q
1j
0R
0Y
1V
1]
0^
0e
0b
0i
0m
0,"
1n
1q
1r
1u
0v
0y
1z
1}
0~
0#"
0$"
0'"
0("
0+"
14
0<
1@
0H
b10110 *
0L
0P
1T
1X
0\
1`
0d
0h
b10110 +
0l
1-
12
05
09
0:
1>
1A
0F
0I
0J
1/
13
17
1;
1?
1C
1G
1K
0O
0S
0W
0[
0_
0c
0g
0k
b1011 $
b1100001 "
b1100001 (
b101 #
b101 )
b100 '
#60000
1."
b10001001 !
b10001001 ,
0t
1m
1,"
0r
0u
1P
b10011 +
0X
1M
1f
0N
0U
10
b10011 *
08
1.
06
1=
0E
b10001001 $
b110001 "
b110001 (
b101 '
#70000
0."
0p
1x
0|
1&"
b1100100 !
b1100100 ,
1*"
0m
0,"
0n
0q
1v
1y
0z
0}
1$"
1'"
1("
1+"
0P
0T
1\
0`
1h
b11001000 +
1l
0M
0f
0Q
0j
1R
1Y
0V
0]
1^
1e
1b
1i
00
04
1<
0@
1H
b11001000 *
1L
0-
0.
02
15
19
1:
0=
0>
0A
1F
1I
1J
b1100100 $
b10001100 "
b10001100 (
b110 '
#80000
0t
1""
0*"
1Q
1j
0R
0Y
0b
0i
0n
0q
0v
0y
1z
1}
0~
0#"
0$"
0'"
1("
1+"
14
0<
b1000010 *
0L
0T
0\
1`
0d
0h
b10010000 +
1l
0x
0|
0&"
b10010000 !
b10010000 ,
1."
11
05
16
09
0:
1B
1E
0F
0I
0J
0/
03
07
0;
0?
0C
0G
0K
1O
1S
1W
1[
1_
1c
1g
1k
0o
0s
0w
0{
0!"
0%"
0)"
0-"
b10010000 $
b1000010 "
b1000010 (
b10 #
b10 )
b111 '
#90000
1~
1#"
1d
0p
1&"
0Q
0j
1Z
1a
0n
0q
0z
0}
1$"
1'"
0("
0+"
04
b1100000 *
1D
0T
0`
1h
b1100000 +
0l
0|
1""
0*"
b110000 !
b110000 ,
0."
01
12
1A
0B
0O
0S
0W
0[
0_
0c
0g
0k
1o
1s
1w
1{
1!"
1%"
1)"
1-"
b110000 $
b1100000 "
b1100000 (
b1 #
b1 )
b1000 '
#100000
1p
1x
1|
0""
b1101 !
b1101 ,
0&"
1n
1q
1v
1y
1z
1}
0~
0#"
0$"
0'"
1T
1\
1`
0d
b11010 +
0h
1Q
1j
1R
1Y
1V
1]
0Z
0a
0^
0e
14
1<
1@
0D
b11010 *
0H
1-
06
1:
1>
0E
1I
1/
13
17
1;
1?
1C
1G
1K
b1101 $
b10100001 "
b10100001 (
b101 #
b101 )
b1001 '
#110000
1&"
0n
0q
1~
1#"
0T
1d
1|
1."
0R
0Y
0V
0]
1Z
1a
1^
1e
1b
1i
0r
0u
1v
1y
1z
1}
1("
1+"
0<
0@
1D
1H
b11100010 *
1L
0X
1\
1`
b10111000 +
1l
0p
0t
0x
b10111000 !
b10111000 ,
1""
0-
11
15
19
0:
0>
1B
1F
0I
1J
1O
1S
1W
1[
1_
1c
1g
1k
0o
0s
0w
0{
0!"
0%"
0)"
0-"
b10111000 $
b101110 "
b101110 (
b110 #
b110 )
b1010 '
#120000
0("
0+"
0l
1p
1|
1R
1Y
1V
1]
0b
0i
1n
1q
1v
1y
1z
1}
1$"
1'"
1<
1@
b1111010 *
0L
1T
1\
1`
b1111010 +
1h
1x
1&"
0*"
b111101 !
b111101 ,
0."
1-
09
1:
1>
1I
0J
0O
0S
0W
0[
0_
0c
0g
0k
1o
1s
1w
1{
1!"
1%"
1)"
1-"
b111101 $
b10100111 "
b10100111 (
b101 #
b101 )
b1011 '
#130000
1."
1t
0""
b11101111 !
b11101111 ,
1*"
1m
1,"
1r
1u
0~
0#"
1("
1+"
1P
1X
0d
b11011111 +
1l
1M
1f
1N
1U
0Z
0a
1b
1i
10
18
0D
b11011111 *
1L
1.
01
16
19
1=
0B
1E
1J
b11101111 $
b11111101 "
b11111101 (
b1100 '
#140000
0*"
0."
0$"
0'"
0("
0+"
0h
b11111 +
0l
0^
0e
0b
0i
0H
b11111 *
0L
1""
b11111 !
b11111 ,
0&"
05
09
0F
0J
0o
0s
0w
0{
0!"
0%"
0)"
0-"
b11111 $
b11110001 "
b11110001 (
b100 #
b100 )
b1101 '
#150000
1~
1#"
b111111 +
1d
1Z
1a
b111111 *
1D
1""
b10011111 !
b10011111 ,
1."
11
15
06
19
0:
1B
0E
1F
0I
1J
0/
03
07
0;
0?
0C
0G
0K
1o
1s
1w
1{
1!"
1%"
1)"
1-"
b10011111 $
b111111 "
b111111 (
b1 #
b1 )
b1110 '
#160000
0p
0x
0|
0m
0,"
0r
0u
0v
0y
0P
0X
0\
0""
1*"
0Q
0j
0N
0U
0V
0]
0Z
0a
1b
1i
0z
0}
1~
1#"
1$"
1'"
0("
0+"
04
08
0@
0D
b10001001 *
1L
0`
1d
1h
b1100010 +
0l
1&"
b1100010 !
b1100010 ,
0."
0-
01
02
05
1:
0>
0A
0B
0F
1I
1/
13
17
1;
1?
1C
1G
1K
1O
1S
1W
1[
1_
1c
1g
1k
0o
0s
0w
0{
0!"
0%"
0)"
0-"
b1100010 $
b10011000 "
b10011000 (
b110 #
b110 )
b1111 '
#170000
1."
1x
0&"
1m
1,"
0n
0q
1v
1y
0~
0#"
0$"
0'"
1("
1+"
1P
0T
1\
0d
0h
b10001001 +
1l
0p
0t
0""
b11000100 !
b11000100 ,
1*"
0O
0S
0W
0[
0_
0c
0g
0k
1o
1s
1w
1{
1!"
1%"
1)"
1-"
b11000100 $
b101 #
b101 )
b10000 '
#180000
1""
1r
1u
1z
1}
1X
1`
0t
0&"
0."
1N
1U
0R
0Y
1V
1]
1^
1e
0b
0i
1m
1,"
0n
0q
0v
0y
0~
0#"
1$"
1'"
0("
0+"
18
0<
1@
1H
b1010101 *
0L
1P
0T
0\
0d
1h
b1010101 +
0l
1p
1x
0|
b1010101 !
b1010101 ,
1*"
1-
15
16
09
0:
1>
1E
1F
0I
0J
0/
03
07
0;
0?
0C
0G
0K
1O
1S
1W
1[
1_
1c
1g
1k
0o
0s
0w
0{
0!"
0%"
0)"
0-"
b1010101 $
b1010101 "
b1010101 (
b10 #
b10 )
b10001 '
#190000
1n
1q
1v
1y
0z
0}
1("
1+"
1T
1\
0`
b11001111 +
1l
1Q
1j
1R
1Y
0V
0]
1b
1i
14
1<
0@
b11001111 *
1L
1p
1t
1x
0|
0""
1&"
1*"
b11100111 !
b11100111 ,
1."
0-
12
19
1:
0>
1A
1I
1J
1/
13
17
1;
1?
1C
1G
1K
0O
0S
0W
0[
0_
0c
0g
0k
1o
1s
1w
1{
1!"
1%"
1)"
1-"
b11100111 $
b11111100 "
b11111100 (
b101 #
b101 )
b10010 '
#200000
0&"
0*"
0p
0$"
0'"
0("
0+"
0n
0q
0h
0l
0T
0t
1x
1|
b10011100 !
b10011100 ,
1""
0M
0f
0Q
0j
0R
0Y
1Z
1a
0r
0u
1v
1y
1z
1}
1~
1#"
00
04
0<
b11100100 *
1D
0X
1\
1`
b111001 +
1d
0.
11
02
0:
0=
0A
1B
0I
1O
1S
1W
1[
1_
1c
1g
1k
b10011100 $
b1001110 "
b1001110 (
b111 #
b111 )
b10011 '
#210000
0|
1("
1+"
0m
0,"
0v
0y
1l
0P
b10110000 +
0\
1Q
1j
0N
0U
0Z
0a
14
08
b11000010 *
0D
0p
0x
1&"
b10110000 !
b10110000 ,
1."
05
09
1:
0F
1I
0J
0/
03
07
0;
0?
0C
0G
0K
0o
0s
0w
0{
0!"
0%"
0)"
0-"
b10110000 $
b11000010 "
b11000010 (
b10 #
b10 )
b10100 '
#220000
1t
0""
1$"
1'"
1m
1,"
1r
1u
0z
0}
0~
0#"
1h
1P
1X
0`
b11000101 +
0d
1M
1f
1N
1U
1V
1]
0^
0e
0b
0i
10
18
1@
0H
b10111 *
0L
0|
1&"
1*"
b11100010 !
b11100010 ,
1."
1-
1.
01
12
0:
1=
1>
1A
0B
0I
1/
13
17
1;
1?
1C
1G
1K
1o
1s
1w
1{
1!"
1%"
1)"
1-"
b11100010 $
b1110001 "
b1110001 (
b111 #
b111 )
b10101 '
#230000
0*"
1|
0$"
0'"
1n
1q
1v
1y
0h
1T
b10001111 +
1\
0M
0f
1R
1Y
1Z
1a
00
1<
b111110 *
1D
1p
1t
1x
b10001111 !
b10001111 ,
0&"
0-
11
15
06
19
0>
1B
0E
1F
1J
0/
03
07
0;
0?
0C
0G
0K
0o
0s
0w
0{
0!"
0%"
0)"
0-"
b10001111 $
b111110 "
b111110 (
b10 #
b10 )
b10110 '
#240000
1*"
0."
0|
b1100111 !
b1100111 ,
1&"
1$"
1'"
0("
0+"
0v
0y
1~
1#"
1h
0l
0\
b1100111 +
1d
1M
1f
0Q
0j
0Z
0a
1b
1i
10
04
0D
b10011101 *
1L
1-
01
02
05
16
1:
1>
0A
0B
1E
0F
1I
1/
13
17
1;
1?
1C
1G
1K
b1100111 $
b11011001 "
b11011001 (
b110 #
b110 )
b10111 '
#250000
0t
1|
1""
0&"
1*"
b1011101 !
b1011101 ,
0."
1^
1e
0b
0i
0n
0q
1v
1y
1z
1}
0~
0#"
1$"
1'"
0("
0+"
1H
b1011101 *
0L
0T
1\
1`
0d
1h
b1011101 +
0l
15
0:
1F
0I
0/
03
07
0;
0?
0C
0G
0K
0O
0S
0W
0[
0_
0c
0g
0k
b1011101 $
b1011101 "
b1011101 (
b0 #
b0 )
b11000 '
#260000
0|
0z
0}
0$"
0'"
1("
1+"
0`
0h
b10001101 +
1l
0V
0]
0^
0e
1b
1i
0@
0H
b10001101 *
1L
0p
1t
0""
0&"
1*"
b11000110 !
b11000110 ,
1."
0-
05
1:
0>
0F
1I
1/
13
17
1;
1?
1C
1G
1K
1o
1s
1w
1{
1!"
1%"
1)"
1-"
b11000110 $
b11011000 "
b11011000 (
b101 #
b101 )
b11001 '
#270000
0x
1""
1&"
0m
0,"
1n
1q
0r
0u
0v
0y
1z
1}
1~
1#"
0P
1T
0X
0\
1`
b10110010 +
1d
0M
0f
1Q
1j
0N
0U
0R
0Y
1V
1]
1Z
1a
00
14
08
0<
1@
b10110010 *
1D
0p
1t
0|
b10110010 !
b10110010 ,
0*"
1-
0.
11
12
06
0:
0=
1>
1A
1B
0E
0I
0o
0s
0w
0{
0!"
0%"
0)"
0-"
b10110010 $
b101011 "
b101011 (
b100 #
b100 )
b11010 '
#280000
1m
1,"
0n
0q
1$"
1'"
0("
0+"
1P
0T
1h
b1110001 +
0l
1M
1f
0Q
0j
1^
1e
0b
0i
10
04
1H
b1110001 *
0L
0p
0t
1|
1&"
0*"
b10111000 !
b10111000 ,
1."
1.
02
15
09
1=
0A
1F
0J
1o
1s
1w
1{
1!"
1%"
1)"
1-"
b10111000 $
b10111 "
b10111 (
b101 #
b101 )
b11011 '
#290000
0."
b101000 !
b101000 ,
0""
0m
0,"
0~
0#"
0P
b1010000 +
0d
0M
0f
0Z
0a
00
b1010000 *
0D
0.
01
0=
0B
b101000 $
b101 "
b101 (
b11100 '
#300000
1t
1x
0|
b1100110 !
b1100110 ,
1*"
1r
1u
1v
1y
0z
0}
1("
1+"
1X
1\
0`
b11001100 +
1l
1N
1U
1R
1Y
0V
0]
1b
1i
18
1<
0@
b11001100 *
1L
0-
16
19
1:
0>
1E
1I
1J
b1100110 $
b11001100 "
b11001100 (
b11101 '
#310000
1."
1p
0t
0x
1|
0""
0&"
b10001001 !
b10001001 ,
0*"
0b
0i
1m
1,"
1n
1q
0r
0u
0v
0y
1z
1}
0~
0#"
0$"
0'"
0("
0+"
b1001100 *
0L
1P
1T
0X
0\
1`
0d
0h
b10011 +
0l
0:
0I
0/
03
07
0;
0?
0C
0G
0K
1O
1S
1W
1[
1_
1c
1g
1k
b10001001 $
b1001100 "
b1001100 (
b11 #
b11 )
b11110 '
#320000
1*"
0p
1&"
1$"
1'"
0m
0,"
0n
0q
1v
1y
1~
1#"
1h
0P
0T
1\
b1111000 +
1d
1M
1f
0N
0U
0R
0Y
1Z
1a
1b
1i
10
08
0<
1D
b11100001 *
1L
0t
1|
1""
b1111000 !
b1111000 ,
0."
1-
12
05
09
1:
1>
1A
0F
1I
0J
0o
0s
0w
0{
0!"
0%"
0)"
0-"
b1111000 $
b11100001 "
b11100001 (
b10 #
b10 )
b11111 '
#330000
0&"
0~
0#"
0d
0p
0|
1""
b1010000 !
b1010000 ,
0."
0M
0f
1V
1]
0Z
0a
0b
0i
0m
0,"
0v
0y
1z
1}
0("
0+"
00
1@
0D
b1010000 *
0L
0P
0\
1`
b1010000 +
0l
0-
1.
02
0:
1=
0>
0A
0I
0O
0S
0W
0[
0_
0c
0g
0k
b1010000 $
b1010000 "
b1010000 (
b0 #
b0 )
b100000 '
#340000
1x
0""
1&"
b100100 !
b100100 ,
0*"
1r
1u
0z
0}
1~
1#"
0$"
0'"
1X
0`
1d
b100100 +
0h
1N
1U
0V
0]
1Z
1a
0^
0e
18
0@
1D
b100100 *
0H
0.
12
15
06
0=
1A
0E
1F
b100100 $
b100100 "
b100100 (
b100001 '
#350000
1*"
1$"
1'"
1h
1p
1x
1|
b1101101 !
b1101101 ,
1&"
1M
1f
1V
1]
1b
1i
1m
1,"
1r
1u
1v
1y
1~
1#"
10
1@
b10110101 *
1L
1P
1X
1\
b1101101 +
1d
1-
1.
1:
1=
1>
1I
1O
1S
1W
1[
1_
1c
1g
1k
b1101101 $
b10110101 "
b10110101 (
b10 #
b10 )
b100010 '
#360000
0r
0u
0X
1x
0&"
0N
0U
1R
1Y
0b
0i
1v
1y
1z
1}
0$"
0'"
0("
0+"
08
1<
b111001 *
0L
1\
1`
0h
b111001 +
0l
0p
0t
1|
1""
0*"
b10011100 !
b10011100 ,
1."
11
02
05
0A
1B
0F
1/
13
17
1;
1?
1C
1G
1K
0O
0S
0W
0[
0_
0c
0g
0k
1o
1s
1w
1{
1!"
1%"
1)"
1-"
b10011100 $
b10010011 "
b10010011 (
b101 #
b101 )
b100011 '
#370000
1t
0""
1*"
1N
1U
0V
0]
1m
1,"
1n
1q
0r
0u
0z
0}
0~
0#"
1$"
1'"
18
b101101 *
0@
1P
1T
0X
0`
0d
b1001011 +
1h
1p
0x
0&"
b1001011 !
b1001011 ,
0."
0-
16
0>
1E
1O
1S
1W
1[
1_
1c
1g
1k
0o
0s
0w
0{
0!"
0%"
0)"
0-"
b1001011 $
b11010010 "
b11010010 (
b110 #
b110 )
b100100 '
#380000
0p
0$"
0'"
1("
1+"
0m
0,"
0n
0q
0v
0y
0h
1l
0P
0T
b10000000 +
0\
0M
0f
1Q
1j
0N
0U
0R
0Y
0Z
0a
00
14
08
0<
b10 *
0D
0t
0x
0|
0&"
1*"
b1000000 !
b1000000 ,
0."
0.
06
0:
0=
0E
0I
0/
03
07
0;
0?
0C
0G
0K
1o
1s
1w
1{
1!"
1%"
1)"
1-"
b1000000 $
b10 "
b10 (
b11 #
b11 )
b100101 '
#390000
1|
1z
1}
1`
0p
b1000 !
b1000 ,
0*"
0Q
0j
1V
1]
0n
0q
0("
0+"
04
b10000 *
1@
0T
b10000 +
0l
1-
01
1>
0B
1/
13
17
1;
1?
1C
1G
1K
0O
0S
0W
0[
0_
0c
0g
0k
b1000 $
b1 "
b1 (
b101 #
b101 )
b100110 '
#400000
1*"
1p
1""
1("
1+"
1n
1q
1~
1#"
1l
1T
1d
0t
b1011001 !
b1011001 ,
1|
1Q
1j
1R
1Y
0V
0]
1^
1e
1b
1i
0r
0u
1z
1}
14
1<
0@
1H
b11001010 *
1L
0X
b10110010 +
1`
0-
11
16
19
1:
0>
1B
1E
1I
1J
0/
03
07
0;
0?
0C
0G
0K
1O
1S
1W
1[
1_
1c
1g
1k
b1011001 $
b11001010 "
b11001010 (
b11 #
b11 )
b100111 '
#410000
1&"
0*"
1."
1x
b10110101 !
b10110101 ,
0|
1$"
1'"
0("
0+"
1m
1,"
1v
1y
0z
0}
1h
0l
1P
1\
b1101011 +
0`
1M
1f
0Q
0j
1N
1U
1Z
1a
0^
0e
10
04
18
1D
b10101101 *
0H
1-
01
12
15
06
1>
1A
0B
0E
1F
b10110101 $
b10101101 "
b10101101 (
b101000 '
#420000
0x
0v
0y
0\
0p
1t
0&"
b11010010 !
b11010010 ,
1*"
0R
0Y
0n
0q
1r
1u
0$"
0'"
1("
1+"
b10100101 *
0<
0T
1X
0h
b10100101 +
1l
0-
1.
11
02
05
16
0:
1=
0>
0A
1B
1E
0F
0I
1/
13
17
1;
1?
1C
1G
1K
0O
0S
0W
0[
0_
0c
0g
0k
b11010010 $
b1011010 "
b1011010 (
b101 #
b101 )
b101001 '
#430000
0m
0,"
1z
1}
0~
0#"
0P
1`
0d
0|
0."
0M
0f
0N
0U
0Z
0a
1^
1e
0b
0i
0r
0u
0v
0y
0$"
0'"
0("
0+"
00
08
0D
1H
b1000000 *
0L
0X
0\
0h
b10000 +
0l
0p
0t
0x
1""
0&"
b10000 !
b10000 ,
0*"
0.
01
09
0=
0B
0J
0/
03
07
0;
0?
0C
0G
0K
1O
1S
1W
1[
1_
1c
1g
1k
0o
0s
0w
0{
0!"
0%"
0)"
0-"
b10000 $
b1000000 "
b1000000 (
b10 #
b10 )
b101010 '
#440000
1*"
1p
1t
b1010111 !
b1010111 ,
1x
1$"
1'"
1m
1,"
1n
1q
1r
1u
1h
1P
1T
b1010111 +
1X
1M
1f
1N
1U
1R
1Y
1V
1]
10
18
1<
b1011101 *
1@
1-
1.
15
1:
1=
1>
1F
1I
1/
13
17
1;
1?
1C
1G
1K
b1010111 $
b11010101 "
b11010101 (
b110 #
b110 )
b101011 '
#450000
0t
0m
0,"
0r
0u
1~
1#"
0$"
0'"
0P
0X
1d
0h
1p
0M
0f
1Q
1j
0N
0U
0R
0Y
1Z
1a
0^
0e
1n
1q
0v
0y
00
14
08
0<
1D
b110010 *
0H
1T
b110010 +
0\
0x
1|
1""
0&"
0*"
b11001 !
b11001 ,
0."
0.
11
12
05
06
0:
0=
1A
1B
0E
0F
0I
0O
0S
0W
0[
0_
0c
0g
0k
1o
1s
1w
1{
1!"
1%"
1)"
1-"
b11001 $
b100011 "
b100011 (
b101 #
b101 )
b101100 '
