03_week/03_sync_vs_async/sync_vs_async.v
// ==================================================
//	[ VLSISYS Lab. ]
//	* Author		: Daseul Moon (daseul@sm.ac.kr)
//	* Filename		: sync_vs_async.v
//	* Date			: 2025-03-17 10:53:08
//	* Description	: 
// ==================================================

module dff_sync
#(
	parameter	BW_DATA	= 32
)
(
	output reg [BW_DATA-1:0]	o_q,
	input	   [BW_DATA-1:0]	i_d,
	input						i_clk,
	input						i_rstn
);

	always @(posedge i_clk) begin
		if(!i_rstn) begin
			o_q <= 1'b0;
		end else begin
			o_q <= i_d;
		end
	end
endmodule

module dff_async
#(
	parameter	BW_DATA	= 32
)
(
	output reg [BW_DATA-1:0]	o_q,
	input	   [BW_DATA-1:0]    i_d,
	input						i_clk,
	input       				i_rstn
);

	always @(posedge i_clk or negedge i_rstn) begin
		if(!i_rstn) begin
			o_q <= 1'b0;
		end else begin
			o_q <= i_d;
		end
	end
endmodule

03_week/03_sync_vs_async/sync_vs_async_tb.v
// ==================================================
//	[ VLSISYS Lab. ]
//	* Author		: Daseul Moon (daseul@sm.ac.kr)
//	* Filename		: sync_vs_async_tb.v
//	* Date			: 2025-03-17 11:00:18
//	* Description	: 
// ==================================================

// --------------------------------------------------
//	Define Global Variables
// --------------------------------------------------
`define	CLKFREQ		100		// Clock Freq. (Unit: MHz)
`define	SIMCYCLE	`NVEC	// Sim. Cycles
`define BW_DATA		32		// Bitwidth of ~~
`define NVEC 		100

// --------------------------------------------------
//	Includes
// --------------------------------------------------
`include	"sync_vs_async.v"

module sync_vs_async_tb;
// --------------------------------------------------
//	DUT Signals & Instantiate
// --------------------------------------------------
	wire [`BW_DATA-1:0] o_q_sync;
	wire [`BW_DATA-1:0] o_q_async;
	reg	 [`BW_DATA-1:0] i_d;
	reg					i_clk;
	reg					i_rstn;

	dff_sync
	#(
		.BW_DATA	(`BW_DATA)
	)
	u_dff_sync(
		.o_q    (o_q_sync),
		.i_d    (i_d	 ),
		.i_clk  (i_clk	 ),
		.i_rstn (i_rstn	 )
	);

	dff_async
	#(
		.BW_DATA	(`BW_DATA)
	)
	u_dff_aysnc(
		.o_q    (o_q_async),
		.i_d    (i_d      ),
		.i_clk  (i_clk	  ),
		.i_rstn (i_rstn	  )
	);

// -------------------------------------------------
//	Clock
// -------------------------------------------------
	always	#(500/`CLKFREQ) i_clk = ~i_clk;

	task 	resetReleaseAfterNCycle;
		input [31:0]	n;
		begin
			#(n*1000/`CLKFREQ);
			i_rstn = 1;
		end	
	endtask

// --------------------------------------------------
//	Test Stimulus
// --------------------------------------------------
	integer		i, j;
	initial begin
		i_d    = 0;
		i_clk  = 0;
		i_rstn = 0;
		resetReleaseAfterNCycle(4);

		for (i=0; i<`SIMCYCLE; i++) begin
			j	= $urandom_range(0,10);
			#((j*0.1)*1000/`CLKFREQ);
			i_d	   = $urandom;
			i_rstn = $urandom;
			#((1-(j*0.1))*1000/`CLKFREQ);
		end
		$finish;
	end

// --------------------------------------------------
//	Dump VCD
// --------------------------------------------------
	reg	[8*32-1:0]	vcd_file;
	initial begin
		if ($value$plusargs("vcd_file=%s", vcd_file)) begin
			$dumpfile(vcd_file);
			$dumpvars;
		end else begin
			$dumpfile("sync_vs_async_tb.vcd");
			$dumpvars;
		end
	end

endmodule

03_week/03_sync_vs_async/vcd/sync_vs_async.vcd
$date
	Mon Mar 17 11:28:03 2025
$end
$version
	Icarus Verilog
$end
$timescale
	1ps
$end
$scope module sync_vs_async_tb $end
$var wire 32 ! o_q_sync [31:0] $end
$var wire 32 " o_q_async [31:0] $end
$var reg 1 # i_clk $end
$var reg 32 $ i_d [31:0] $end
$var reg 1 % i_rstn $end
$var reg 256 & vcd_file [255:0] $end
$var integer 32 ' i [31:0] $end
$var integer 32 ( j [31:0] $end
$scope module u_dff_aysnc $end
$var wire 1 # i_clk $end
$var wire 32 ) i_d [31:0] $end
$var wire 1 % i_rstn $end
$var reg 32 * o_q [31:0] $end
$upscope $end
$scope module u_dff_sync $end
$var wire 1 # i_clk $end
$var wire 32 + i_d [31:0] $end
$var wire 1 % i_rstn $end
$var reg 32 , o_q [31:0] $end
$upscope $end
$scope task resetReleaseAfterNCycle $end
$var reg 32 - n [31:0] $end
$upscope $end
$upscope $end
$enddefinitions $end
#0
$dumpvars
b100 -
bx ,
b0 +
b0 *
b0 )
bx (
bx '
b10111000101111011101100110001101100100001011110111001101111001011011100110001101011111011101100111001101011111011000010111001101111001011011100110001100101110011101100110001101100100 &
0%
b0 $
0#
b0 "
bx !
$end
#5000
b0 !
b0 ,
1#
#10000
0#
#15000
1#
#20000
0#
#25000
1#
#30000
0#
#35000
1#
#40000
0#
b110 (
b0 '
1%
#45000
1#
#46000
b1000000100010010101111010000001 $
b1000000100010010101111010000001 )
b1000000100010010101111010000001 +
#50000
b10 (
b1 '
0#
#52000
b10000110101110010111101100001101 $
b10000110101110010111101100001101 )
b10000110101110010111101100001101 +
#55000
b10000110101110010111101100001101 "
b10000110101110010111101100001101 *
b10000110101110010111101100001101 !
b10000110101110010111101100001101 ,
1#
#60000
0#
b10 '
#62000
b1001001101110101001000010010 $
b1001001101110101001000010010 )
b1001001101110101001000010010 +
#65000
b1001001101110101001000010010 "
b1001001101110101001000010010 *
b1001001101110101001000010010 !
b1001001101110101001000010010 ,
1#
#70000
0#
b101 (
b11 '
#75000
b10111011001000111111000101110110 "
b10111011001000111111000101110110 *
b10111011001000111111000101110110 !
b10111011001000111111000101110110 ,
1#
b10111011001000111111000101110110 $
b10111011001000111111000101110110 )
b10111011001000111111000101110110 +
#80000
0#
b1010 (
b100 '
#85000
1#
#90000
b100 (
b101 '
0#
b11000110001011011111011110001100 $
b11000110001011011111011110001100 )
b11000110001011011111011110001100 +
#94000
b0 "
b0 *
0%
b1100010111101111000010011000101 $
b1100010111101111000010011000101 )
b1100010111101111000010011000101 +
#95000
b0 !
b0 ,
1#
#100000
0#
b1010 (
b110 '
#105000
1#
#110000
b1000 (
b111 '
0#
b111011110100100111001001110111 $
b111011110100100111001001110111 )
b111011110100100111001001110111 +
#115000
1#
#118000
b11111001001100000110100111110010 $
b11111001001100000110100111110010 )
b11111001001100000110100111110010 +
#120000
b100 (
b1000 '
0#
#124000
b1100010110010100100111011000101 $
b1100010110010100100111011000101 )
b1100010110010100100111011000101 +
#125000
1#
#130000
0#
b1001 '
#134000
1%
b10110101010110101100000101101 $
b10110101010110101100000101101 )
b10110101010110101100000101101 +
#135000
b10110101010110101100000101101 "
b10110101010110101100000101101 *
b10110101010110101100000101101 !
b10110101010110101100000101101 ,
1#
#140000
0#
b10 (
b1010 '
#142000
b0 "
b0 *
0%
b10000101011100111000011100001010 $
b10000101011100111000011100001010 )
b10000101011100111000011100001010 +
#145000
b0 !
b0 ,
1#
#150000
0#
b110 (
b1011 '
#155000
1#
#156000
1%
b11010101011110000100010110101010 $
b11010101011110000100010110101010 )
b11010101011110000100010110101010 +
#160000
b11 (
b1100 '
0#
#163000
b1001100000111011100000010011 $
b1001100000111011100000010011 )
b1001100000111011100000010011 +
#165000
b1001100000111011100000010011 "
b1001100000111011100000010011 *
b1001100000111011100000010011 !
b1001100000111011100000010011 ,
1#
#170000
0#
b1 (
b1101 '
#171000
b10110101100111111101110101101011 $
b10110101100111111101110101101011 )
b10110101100111111101110101101011 +
#175000
b10110101100111111101110101101011 "
b10110101100111111101110101101011 *
b10110101100111111101110101101011 !
b10110101100111111101110101101011 ,
1#
#180000
b1010111010101100011111010101110 $
b1010111010101100011111010101110 )
b1010111010101100011111010101110 +
0#
b0 (
b1110 '
#185000
b1010111010101100011111010101110 "
b1010111010101100011111010101110 *
b1010111010101100011111010101110 !
b1010111010101100011111010101110 ,
1#
#190000
0#
b100 (
b1111 '
#194000
b0 "
b0 *
0%
b10010001100001000100100100100011 $
b10010001100001000100100100100011 )
b10010001100001000100100100100011 +
#195000
b0 !
b0 ,
1#
#200000
0#
b10000 '
#204000
b11110001100010100110000111100 $
b11110001100010100110000111100 )
b11110001100010100110000111100 +
#205000
1#
#210000
0#
b1000 (
b10001 '
#215000
1#
#218000
b10100000110001001011001101000001 $
b10100000110001001011001101000001 )
b10100000110001001011001101000001 +
#220000
b10010 '
0#
#225000
1#
#228000
1%
b1000100100010100001001010001001 $
b1000100100010100001001010001001 )
b1000100100010100001001010001001 +
#230000
b1001 (
b10011 '
0#
#235000
b1000100100010100001001010001001 "
b1000100100010100001001010001001 *
b1000100100010100001001010001001 !
b1000100100010100001001010001001 ,
1#
#239000
b0 "
b0 *
0%
b11100011010010111111100111000110 $
b11100011010010111111100111000110 )
b11100011010010111111100111000110 +
#240000
b100 (
b10100 '
0#
#244000
1%
b10010101000011111101110100101010 $
b10010101000011111101110100101010 )
b10010101000011111101110100101010 +
#245000
b10010101000011111101110100101010 "
b10010101000011111101110100101010 *
b10010101000011111101110100101010 !
b10010101000011111101110100101010 ,
1#
#250000
0#
b10 (
b10101 '
#252000
b11000010111100100100000110000101 $
b11000010111100100100000110000101 )
b11000010111100100100000110000101 +
#255000
b11000010111100100100000110000101 "
b11000010111100100100000110000101 *
b11000010111100100100000110000101 !
b11000010111100100100000110000101 ,
1#
#260000
0#
b1 (
b10110 '
#261000
b0 "
b0 *
0%
b10011101000001100011001100111010 $
b10011101000001100011001100111010 )
b10011101000001100011001100111010 +
#265000
b0 !
b0 ,
1#
#270000
0#
b101 (
b10111 '
#275000
b11111000110110011001101111110001 "
b11111000110110011001101111110001 *
b11111000110110011001101111110001 !
b11111000110110011001101111110001 ,
1#
1%
b11111000110110011001101111110001 $
b11111000110110011001101111110001 )
b11111000110110011001101111110001 +
#280000
0#
b111 (
b11000 '
#285000
1#
#287000
b10100110001101011111101101001100 $
b10100110001101011111101101001100 )
b10100110001101011111101101001100 +
#290000
b1000 (
b11001 '
0#
#295000
b10100110001101011111101101001100 "
b10100110001101011111101101001100 *
b10100110001101011111101101001100 !
b10100110001101011111101101001100 ,
1#
#298000
b11111100011011011010100111111000 $
b11111100011011011010100111111000 )
b11111100011011011010100111111000 +
#300000
b11 (
b11010 '
0#
#303000
b101110011111011001010001011100 $
b101110011111011001010001011100 )
b101110011111011001010001011100 +
#305000
b101110011111011001010001011100 "
b101110011111011001010001011100 *
b101110011111011001010001011100 !
b101110011111011001010001011100 ,
1#
#310000
0#
b1000 (
b11011 '
#315000
1#
#318000
b0 "
b0 *
0%
b100100101011100011001001001001 $
b100100101011100011001001001001 )
b100100101011100011001001001001 +
#320000
b100 (
b11100 '
0#
#324000
b101000110001111111110001010001 $
b101000110001111111110001010001 )
b101000110001111111110001010001 +
#325000
b0 !
b0 ,
1#
#330000
0#
b101 (
b11101 '
#335000
1#
b1100001001011001100111011000010 $
b1100001001011001100111011000010 )
b1100001001011001100111011000010 +
#340000
0#
b10 (
b11110 '
#342000
b10011110111100101110110100111101 $
b10011110111100101110110100111101 )
b10011110111100101110110100111101 +
#345000
1#
#350000
0#
b11111 '
#352000
1%
b10110110111001011000000101101101 $
b10110110111001011000000101101101 )
b10110110111001011000000101101101 +
#355000
b10110110111001011000000101101101 "
b10110110111001011000000101101101 *
b10110110111001011000000101101101 !
b10110110111001011000000101101101 ,
1#
#360000
0#
b110 (
b100000 '
#365000
1#
#366000
b1101001111010111111011011010011 $
b1101001111010111111011011010011 )
b1101001111010111111011011010011 +
#370000
b10 (
b100001 '
0#
#372000
b10101101110110100101100101011011 $
b10101101110110100101100101011011 )
b10101101110110100101100101011011 +
#375000
b10101101110110100101100101011011 "
b10101101110110100101100101011011 *
b10101101110110100101100101011011 !
b10101101110110100101100101011011 ,
1#
#380000
0#
b1 (
b100010 '
#381000
b0 "
b0 *
0%
b10010101000011001010111100101010 $
b10010101000011001010111100101010 )
b10010101000011001010111100101010 +
#385000
b0 !
b0 ,
1#
#390000
0#
b10 (
b100011 '
#392000
b1000111000110100000110010001110 $
b1000111000110100000110010001110 )
b1000111000110100000110010001110 +
#395000
1#
#400000
0#
b1010 (
b100100 '
#405000
1#
#410000
b11 (
b100101 '
0#
1%
b10011011111011011110000100110 $
b10011011111011011110000100110 )
b10011011111011011110000100110 +
#413000
b10111100110011010100000101111 $
b10111100110011010100000101111 )
b10111100110011010100000101111 +
#415000
b10111100110011010100000101111 "
b10111100110011010100000101111 *
b10111100110011010100000101111 !
b10111100110011010100000101111 ,
1#
#420000
0#
b10 (
b100110 '
#422000
b10100010001010010000110101000100 $
b10100010001010010000110101000100 )
b10100010001010010000110101000100 +
#425000
b10100010001010010000110101000100 "
b10100010001010010000110101000100 *
b10100010001010010000110101000100 !
b10100010001010010000110101000100 ,
1#
#430000
0#
b100 (
b100111 '
#434000
b0 "
b0 *
0%
b1110011000010010001101011100110 $
b1110011000010010001101011100110 )
b1110011000010010001101011100110 +
#435000
b0 !
b0 ,
1#
#440000
0#
b110 (
b101000 '
#445000
1#
#446000
b1110110100000101110001011101101 $
b1110110100000101110001011101101 )
b1110110100000101110001011101101 +
#450000
b10 (
b101001 '
0#
#452000
1%
b1011010100010101110001010110101 $
b1011010100010101110001010110101 )
b1011010100010101110001010110101 +
#455000
b1011010100010101110001010110101 "
b1011010100010101110001010110101 *
b1011010100010101110001010110101 !
b1011010100010101110001010110101 ,
1#
#460000
0#
b1000 (
b101010 '
#465000
1#
#468000
b0 "
b0 *
0%
b10100010001100011111111101000100 $
b10100010001100011111111101000100 )
b10100010001100011111111101000100 +
#470000
b110 (
b101011 '
0#
#475000
b0 !
b0 ,
1#
#476000
b11010101111101101010110110101011 $
b11010101111101101010110110101011 )
b11010101111101101010110110101011 +
#480000
b1010 (
b101100 '
0#
#485000
1#
#490000
b100 (
b101101 '
0#
1%
b1001101010111101011110010011010 $
b1001101010111101011110010011010 )
b1001101010111101011110010011010 +
#494000
0%
b10101011000011101110110101010110 $
b10101011000011101110110101010110 )
b10101011000011101110110101010110 +
#495000
1#
#500000
0#
b10 (
b101110 '
#502000
b101001100010011010000001010 $
b101001100010011010000001010 )
b101001100010011010000001010 +
#505000
1#
#510000
0#
b1 (
b101111 '
#511000
b10111100110100011000011101111001 $
b10111100110100011000011101111001 )
b10111100110100011000011101111001 +
#515000
1#
#520000
0#
b1000 (
b110000 '
#525000
1#
#528000
b11001001110001100101110110010011 $
b11001001110001100101110110010011 )
b11001001110001100101110110010011 +
#530000
b1 (
b110001 '
0#
#531000
1%
b11101101110010110110100111011011 $
b11101101110010110110100111011011 )
b11101101110010110110100111011011 +
#535000
b11101101110010110110100111011011 "
b11101101110010110110100111011011 *
b11101101110010110110100111011011 !
b11101101110010110110100111011011 ,
1#
#540000
0#
b1010 (
b110010 '
#545000
1#
#550000
b0 "
b0 *
b1001 (
b110011 '
0#
0%
b110110101001000010011001101101 $
b110110101001000010011001101101 )
b110110101001000010011001101101 +
#555000
b0 !
b0 ,
1#
#559000
1%
b11011011000101110010110110110110 $
b11011011000101110010110110110110 )
b11011011000101110010110110110110 +
#560000
b1 (
b110100 '
0#
#561000
b10000010011101001001101100000100 $
b10000010011101001001101100000100 )
b10000010011101001001101100000100 +
#565000
b10000010011101001001101100000100 "
b10000010011101001001101100000100 *
b10000010011101001001101100000100 !
b10000010011101001001101100000100 ,
1#
#570000
0#
b111 (
b110101 '
#575000
1#
#577000
b0 "
b0 *
0%
b1011010011011101011101010110100 $
b1011010011011101011101010110100 )
b1011010011011101011101010110100 +
#580000
b110 (
b110110 '
0#
#585000
b0 !
b0 ,
1#
#586000
1%
b10110100100000000010000101101 $
b10110100100000000010000101101 )
b10110100100000000010000101101 +
#590000
b1 (
b110111 '
0#
#591000
0%
b100011101111110010000001000 $
b100011101111110010000001000 )
b100011101111110010000001000 +
#595000
1#
#600000
0#
b101 (
b111000 '
#605000
1#
b10010100100111100000011100101001 $
b10010100100111100000011100101001 )
b10010100100111100000011100101001 +
#610000
0#
b1000 (
b111001 '
#615000
1#
#618000
1%
b1101101001101000000100011011010 $
b1101101001101000000100011011010 )
b1101101001101000000100011011010 +
#620000
b111 (
b111010 '
0#
#625000
b1101101001101000000100011011010 "
b1101101001101000000100011011010 *
b1101101001101000000100011011010 !
b1101101001101000000100011011010 ,
1#
#627000
b111000010101011100010001110000 $
b111000010101011100010001110000 )
b111000010101011100010001110000 +
#630000
b1001 (
b111011 '
0#
#635000
b111000010101011100010001110000 "
b111000010101011100010001110000 *
b111000010101011100010001110000 !
b111000010101011100010001110000 ,
1#
#639000
b0 "
b0 *
0%
b10101111001110101011001101011110 $
b10101111001110101011001101011110 )
b10101111001110101011001101011110 +
#640000
b1010 (
b111100 '
0#
#645000
b0 !
b0 ,
1#
#650000
b110 (
b111101 '
0#
1%
b1101001001001111011000011010 $
b1101001001001111011000011010 )
b1101001001001111011000011010 +
#655000
b1101001001001111011000011010 "
b1101001001001111011000011010 *
b1101001001001111011000011010 !
b1101001001001111011000011010 ,
1#
#656000
b0 "
b0 *
0%
b11001011001001110011011110010110 $
b11001011001001110011011110010110 )
b11001011001001110011011110010110 +
#660000
b111110 '
0#
#665000
b0 !
b0 ,
1#
#666000
1%
b1011011010001100001101010110110 $
b1011011010001100001101010110110 )
b1011011010001100001101010110110 +
#670000
b1010 (
b111111 '
0#
#675000
b1011011010001100001101010110110 "
b1011011010001100001101010110110 *
b1011011010001100001101010110110 !
b1011011010001100001101010110110 ,
1#
#680000
b0 "
b0 *
b1000 (
b1000000 '
0#
0%
b11000011011000010101011110000110 $
b11000011011000010101011110000110 )
b11000011011000010101011110000110 +
#685000
b0 !
b0 ,
1#
#688000
1%
b1101101100011011000000011011011 $
b1101101100011011000000011011011 )
b1101101100011011000000011011011 +
#690000
b1000001 '
0#
#695000
b1101101100011011000000011011011 "
b1101101100011011000000011011011 *
b1101101100011011000000011011011 !
b1101101100011011000000011011011 ,
1#
#698000
b1111101001010001110010011111010 $
b1111101001010001110010011111010 )
b1111101001010001110010011111010 +
#700000
b101 (
b1000010 '
0#
#705000
b0 "
b0 *
b0 !
b0 ,
0%
b1010000111101010111100010100001 $
b1010000111101010111100010100001 )
b1010000111101010111100010100001 +
1#
#710000
b1 (
b1000011 '
0#
#711000
1%
b11111010100011000101100111110101 $
b11111010100011000101100111110101 )
b11111010100011000101100111110101 +
#715000
b11111010100011000101100111110101 "
b11111010100011000101100111110101 *
b11111010100011000101100111110101 !
b11111010100011000101100111110101 ,
1#
#720000
b11100000101100010111010111000001 $
b11100000101100010111010111000001 )
b11100000101100010111010111000001 +
0#
b0 (
b1000100 '
#725000
b11100000101100010111010111000001 "
b11100000101100010111010111000001 *
b11100000101100010111010111000001 !
b11100000101100010111010111000001 ,
1#
#730000
0#
b11 (
b1000101 '
#733000
b10100101101100100111101101001011 $
b10100101101100100111101101001011 )
b10100101101100100111101101001011 +
#735000
b10100101101100100111101101001011 "
b10100101101100100111101101001011 *
b10100101101100100111101101001011 !
b10100101101100100111101101001011 ,
1#
#740000
0#
b101 (
b1000110 '
#745000
b0 !
b0 ,
b0 "
b0 *
1#
0%
b1000101010100000001011010001010 $
b1000101010100000001011010001010 )
b1000101010100000001011010001010 +
#750000
0#
b11 (
b1000111 '
#753000
1%
b11010100100111101111110110101001 $
b11010100100111101111110110101001 )
b11010100100111101111110110101001 +
#755000
b11010100100111101111110110101001 "
b11010100100111101111110110101001 *
b11010100100111101111110110101001 !
b11010100100111101111110110101001 ,
1#
#760000
0#
b101 (
b1001000 '
#765000
b1110011001101000110011011100110 "
b1110011001101000110011011100110 *
b1110011001101000110011011100110 !
b1110011001101000110011011100110 ,
1#
b1110011001101000110011011100110 $
b1110011001101000110011011100110 )
b1110011001101000110011011100110 +
#770000
0#
b110 (
b1001001 '
#775000
1#
#776000
b10010101010110100001110100101010 $
b10010101010110100001110100101010 )
b10010101010110100001110100101010 +
#780000
b1000 (
b1001010 '
0#
#785000
b10010101010110100001110100101010 "
b10010101010110100001110100101010 *
b10010101010110100001110100101010 !
b10010101010110100001110100101010 ,
1#
#788000
b11100011011011110011000111000 $
b11100011011011110011000111000 )
b11100011011011110011000111000 +
#790000
b1001 (
b1001011 '
0#
#795000
b11100011011011110011000111000 "
b11100011011011110011000111000 *
b11100011011011110011000111000 !
b11100011011011110011000111000 ,
1#
#799000
b11100101001000110100010111001010 $
b11100101001000110100010111001010 )
b11100101001000110100010111001010 +
#800000
b111 (
b1001100 '
0#
#805000
b11100101001000110100010111001010 "
b11100101001000110100010111001010 *
b11100101001000110100010111001010 !
b11100101001000110100010111001010 ,
1#
#807000
b0 "
b0 *
0%
b1100011101101111010111011000111 $
b1100011101101111010111011000111 )
b1100011101101111010111011000111 +
#810000
b1001 (
b1001101 '
0#
#815000
b0 !
b0 ,
1#
#819000
1%
b11100010000101101010101111000100 $
b11100010000101101010101111000100 )
b11100010000101101010101111000100 +
#820000
b1000 (
b1001110 '
0#
#825000
b11100010000101101010101111000100 "
b11100010000101101010101111000100 *
b11100010000101101010101111000100 !
b11100010000101101010101111000100 ,
1#
#828000
b1011010001001101001101010110100 $
b1011010001001101001101010110100 )
b1011010001001101001101010110100 +
#830000
b10 (
b1001111 '
0#
#832000
b0 "
b0 *
0%
b11111101011011011111010111111010 $
b11111101011011011111010111111010 )
b11111101011011011111010111111010 +
#835000
b0 !
b0 ,
1#
#840000
0#
b110 (
b1010000 '
#845000
1#
#846000
b1011110110011100101111010111101 $
b1011110110011100101111010111101 )
b1011110110011100101111010111101 +
#850000
b100 (
b1010001 '
0#
#854000
1%
b11100101010000111100111111001010 $
b11100101010000111100111111001010 )
b11100101010000111100111111001010 +
#855000
b11100101010000111100111111001010 "
b11100101010000111100111111001010 *
b11100101010000111100111111001010 !
b11100101010000111100111111001010 ,
1#
#860000
0#
b11 (
b1010010 '
#863000
b11000111011001011010100110001110 $
b11000111011001011010100110001110 )
b11000111011001011010100110001110 +
#865000
b11000111011001011010100110001110 "
b11000111011001011010100110001110 *
b11000111011001011010100110001110 !
b11000111011001011010100110001110 ,
1#
#870000
b1110111100000101001000011101111 $
b1110111100000101001000011101111 )
b1110111100000101001000011101111 +
0#
b0 (
b1010011 '
#875000
b1110111100000101001000011101111 "
b1110111100000101001000011101111 *
b1110111100000101001000011101111 !
b1110111100000101001000011101111 ,
1#
#880000
0#
b110 (
b1010100 '
#885000
1#
#886000
b111010101100010100100001110101 $
b111010101100010100100001110101 )
b111010101100010100100001110101 +
#890000
b111 (
b1010101 '
0#
#895000
b111010101100010100100001110101 "
b111010101100010100100001110101 *
b111010101100010100100001110101 !
b111010101100010100100001110101 ,
1#
#897000
b0 "
b0 *
0%
b11000100011001011110011110001000 $
b11000100011001011110011110001000 )
b11000100011001011110011110001000 +
#900000
b1000 (
b1010110 '
0#
#905000
b0 !
b0 ,
1#
#908000
b11001001001111100100010110010010 $
b11001001001111100100010110010010 )
b11001001001111100100010110010010 +
#910000
b10100101101101110101111101001011 $
b10100101101101110101111101001011 )
b10100101101101110101111101001011 +
b0 (
b1010111 '
0#
#915000
1#
#920000
b10000110101100110000010100001101 $
b10000110101100110000010100001101 )
b10000110101100110000010100001101 +
0#
b1011000 '
#925000
1#
#930000
0#
b110 (
b1011001 '
#935000
1#
#936000
b11101000101011100001101111010001 $
b11101000101011100001101111010001 )
b11101000101011100001101111010001 +
#940000
b1 (
b1011010 '
0#
#941000
b11101101111110110010000111011 $
b11101101111110110010000111011 )
b11101101111110110010000111011 +
#945000
1#
#950000
0#
b111 (
b1011011 '
#955000
1#
#957000
1%
b101011000110010110001001010110 $
b101011000110010110001001010110 )
b101011000110010110001001010110 +
#960000
b100 (
b1011100 '
0#
#964000
b10011100111110001000000100 $
b10011100111110001000000100 )
b10011100111110001000000100 +
#965000
b10011100111110001000000100 "
b10011100111110001000000100 *
b10011100111110001000000100 !
b10011100111110001000000100 ,
1#
#970000
0#
b1011101 '
#974000
b0 "
b0 *
0%
b10001001001111100100110100010010 $
b10001001001111100100110100010010 )
b10001001001111100100110100010010 +
#975000
b0 !
b0 ,
1#
#980000
0#
b1 (
b1011110 '
#981000
1%
b1110010100001111011011011100101 $
b1110010100001111011011011100101 )
b1110010100001111011011011100101 +
#985000
b1110010100001111011011011100101 "
b1110010100001111011011011100101 *
b1110010100001111011011011100101 !
b1110010100001111011011011100101 ,
1#
#990000
0#
b110 (
b1011111 '
#995000
1#
#996000
b0 "
b0 *
0%
b11000000100100000101110110000001 $
b11000000100100000101110110000001 )
b11000000100100000101110110000001 +
#1000000
b1100000 '
0#
#1005000
b0 !
b0 ,
1#
#1006000
1%
b11010000110101011111100110100001 $
b11010000110101011111100110100001 )
b11010000110101011111100110100001 +
#1010000
0%
b10101100001011010010001101011000 $
b10101100001011010010001101011000 )
b10101100001011010010001101011000 +
b0 (
b1100001 '
0#
#1015000
1#
#1020000
0#
b101 (
b1100010 '
#1025000
1#
b1001000110011011010000010010 $
b1001000110011011010000010010 )
b1001000110011011010000010010 +
#1030000
0#
b11 (
b1100011 '
#1033000
1%
b10101010110000101101010101010101 $
b10101010110000101101010101010101 )
b10101010110000101101010101010101 +
#1035000
b10101010110000101101010101010101 "
b10101010110000101101010101010101 *
b10101010110000101101010101010101 !
b10101010110000101101010101010101 ,
1#
#1040000
0#
b1100100 '
